Workbook

Sheet Dashboard
B2: Today's Notora Due Dates | K2: Today's S2A Due Dates
B4: Today's Date | D4: =TODAY() -> 46275 | K4: Today's Date | L4: =TODAY() -> 46275
B6: 50% Design | D6: 100% IFR | E6: IFP | F6: IFC | K6: 50% Design | L6: 100% IFR | M6: IFP | N6: IFC
B7: =_xlfn.XLOOKUP($D$4,Design!$K$2:$K$130,Design!$A$2:$A$130, "Nothing Due",0,1) -> Nothing Due | D7: =C16 -> - | E7: =C17 -> - | F7: =C18 -> - | K7: =C28 -> - | L7: =C29 -> - | M7: =C30 -> - | N7: =C31 -> -
B8: =_xlfn.XLOOKUP($D$4,Design!$K$2:$K$130,Design!$A$2:$A$130, "Nothing Due",0,-1) -> Nothing Due | D8: =_xlfn.XLOOKUP($D$4,Design!$M$2:$M$151,Design!$A$2:$A$151, "Nothing Due",0,-1) -> Nothing Due | E8: =_xlfn.XLOOKUP($D$4,Design!$O$2:$O$151,Design!$A$2:$A$151, "Nothing Due",0,-1) -> Nothing Due | F8: =_xlfn.XLOOKUP($D$4,Design!Q2:Q151,Design!$A$2:$A$151, "Nothing Due",0,-1) -> Nothing Due | K8: =_xlfn.XLOOKUP($D$4,Design!$K$2:$K$151,Design!$A$2:$A$151, "Nothing Due",0,-1) -> Nothing Due | L8: =_xlfn.XLOOKUP($D$4,Design!$M$2:$M$151,Design!$A$2:$A$151, "Nothing Due",0,-1) -> Nothing Due | M8: =_xlfn.XLOOKUP($D$4,Design!$O$2:$O$151,Design!$A$2:$A$151, "Nothing Due",0,-1) -> Nothing Due | N8: =_xlfn.XLOOKUP($D$4,Design!W2:W151,Design!$A$2:$A$151, "Nothing Due",0,-1) -> Nothing Due
B10: Notora Due Dates
B13: Todays Date | D13: =TODAY() -> 46275
C15: =TODAY() -> 46275 | D15: =WORKDAY(D13,1) -> 46276 | E15: =WORKDAY(D15,1) -> 46279 | F15: =WORKDAY(E15,1) -> 46280 | G15: =WORKDAY(F15,1) -> 46281 | H15: =WORKDAY(G15,1) -> 46282 | I15: =WORKDAY(H15,1) -> 46283 | J15: =WORKDAY(I15,1) -> 46286 | K15: =WORKDAY(J15,1) -> 46287 | L15: =WORKDAY(K15,1) -> 46288 | ... N15: =WORKDAY(M15,1) -> 46290
B16: 50% Design | C16: =_xlfn.XLOOKUP(C15,Design!$K$2:$K$151,Design!$A$2:$A$151, "-",0,1) -> - | D16: =_xlfn.XLOOKUP(D15,Design!$K$2:$K$151,Design!$A$2:$A$151, "-",0,1) -> - | E16: =_xlfn.XLOOKUP(E15,Design!$K$2:$K$151,Design!$A$2:$A$151, "-",0,1) -> - | F16: =_xlfn.XLOOKUP(F15,Design!$K$2:$K$151,Design!$A$2:$A$151, "-",0,1) -> - | G16: =_xlfn.XLOOKUP(G15,Design!$K$2:$K$151,Design!$A$2:$A$151, "-",0,1) -> - | H16: =_xlfn.XLOOKUP(H15,Design!$K$2:$K$151,Design!$A$2:$A$151, "-",0,1) -> - | I16: =_xlfn.XLOOKUP(I15,Design!$K$2:$K$151,Design!$A$2:$A$151, "-",0,1) -> - | J16: =_xlfn.XLOOKUP(J15,Design!$K$2:$K$151,Design!$A$2:$A$151, "-",0,1) -> - | ... N16: =_xlfn.XLOOKUP(N15,Design!$K$2:$K$151,Design!$A$2:$A$151, "-",0,1) -> -
B17: 100% IFR | C17: =_xlfn.XLOOKUP(C15,Design!$M$2:$M$151,Design!$A$2:$A$151, "-",0,1) -> - | D17: =_xlfn.XLOOKUP(D15,Design!$M$2:$M$151,Design!$A$2:$A$151, "-",0,1) -> - | E17: =_xlfn.XLOOKUP(E15,Design!$M$2:$M$151,Design!$A$2:$A$151, "-",0,1) -> - | F17: =_xlfn.XLOOKUP(F15,Design!$M$2:$M$151,Design!$A$2:$A$151, "-",0,1) -> - | G17: =_xlfn.XLOOKUP(G15,Design!$M$2:$M$151,Design!$A$2:$A$151, "-",0,1) -> - | H17: =_xlfn.XLOOKUP(H15,Design!$M$2:$M$151,Design!$A$2:$A$151, "-",0,1) -> - | I17: =_xlfn.XLOOKUP(I15,Design!$M$2:$M$151,Design!$A$2:$A$151, "-",0,1) -> - | J17: =_xlfn.XLOOKUP(J15,Design!$M$2:$M$151,Design!$A$2:$A$151, "-",0,1) -> - | ... N17: =_xlfn.XLOOKUP(N15,Design!$M$2:$M$151,Design!$A$2:$A$151, "-",0,1) -> -
B18: IFP | C18: =_xlfn.XLOOKUP(C15,Design!$O$2:$O$151,Design!$A$2:$A$151, "-",0,1) -> - | D18: =_xlfn.XLOOKUP(D15,Design!$O$2:$O$151,Design!$A$2:$A$151, "-",0,1) -> - | E18: =_xlfn.XLOOKUP(E15,Design!$O$2:$O$151,Design!$A$2:$A$151, "-",0,1) -> - | F18: =_xlfn.XLOOKUP(F15,Design!$O$2:$O$151,Design!$A$2:$A$151, " - ",0,1) -> - | G18: =_xlfn.XLOOKUP(G15,Design!$O$2:$O$151,Design!$A$2:$A$151, "-",0,1) -> - | H18: =_xlfn.XLOOKUP(H15,Design!$O$2:$O$151,Design!$A$2:$A$151, "-",0,1) -> - | I18: =_xlfn.XLOOKUP(I15,Design!$O$2:$O$151,Design!$A$2:$A$151, "-",0,1) -> - | J18: =_xlfn.XLOOKUP(J15,Design!$O$2:$O$151,Design!$A$2:$A$151, "-",0,1) -> - | K18: =_xlfn.XLOOKUP(K15,Design!$O$2:$O$151,Design!$A$2:$A$151, "-",0,1) -> - | L18: =_xlfn.XLOOKUP(L15,Design!$O$2:$O$151,Design!$A$2:$A$151, "-",0,1) -> - | M18: =_xlfn.XLOOKUP(M15,Design!$O$2:$O$151,Design!$A$2:$A$151, "-",0,1) -> - | N18: =_xlfn.XLOOKUP(N15,Design!$O$2:$O$151,Design!$A$2:$A$151, "-",0,1) -> -
B19: IFC | C19: =_xlfn.XLOOKUP(C15,Design!$Q$2:$Q$151,Design!$A$2:$A$151, "-",0,1) -> - | D19: =_xlfn.XLOOKUP(D15,Design!$Q$2:$Q$151,Design!$A$2:$A$151, "-",0,1) -> - | E19: =_xlfn.XLOOKUP(E15,Design!$Q$2:$Q$151,Design!$A$2:$A$151, "-",0,1) -> - | F19: =_xlfn.XLOOKUP(F15,Design!$Q$2:$Q$151,Design!$A$2:$A$151, "-",0,1) -> - | G19: =_xlfn.XLOOKUP(G15,Design!$Q$2:$Q$151,Design!$A$2:$A$151, "-",0,1) -> - | H19: =_xlfn.XLOOKUP(H15,Design!$Q$2:$Q$151,Design!$A$2:$A$151, "-",0,1) -> - | I19: =_xlfn.XLOOKUP(I15,Design!$Q$2:$Q$151,Design!$A$2:$A$151, "-",0,1) -> - | J19: =_xlfn.XLOOKUP(J15,Design!$Q$2:$Q$151,Design!$A$2:$A$151, "-",0,1) -> - | ... N19: =_xlfn.XLOOKUP(N15,Design!$Q$2:$Q$151,Design!$A$2:$A$151, "-",0,1) -> -
B21: S2A Due Dates
B24: Todays Date | D24: =TODAY() -> 46275
C26: =TODAY() -> 46275 | D26: =WORKDAY(D24,1) -> 46276 | E26: =WORKDAY(D26,1) -> 46279 | F26: =WORKDAY(E26,1) -> 46280 | G26: =WORKDAY(F26,1) -> 46281 | H26: =WORKDAY(G26,1) -> 46282 | I26: =WORKDAY(H26,1) -> 46283 | J26: =WORKDAY(I26,1) -> 46286 | K26: =WORKDAY(J26,1) -> 46287 | L26: =WORKDAY(K26,1) -> 46288 | ... N26: =WORKDAY(M26,1) -> 46290
B27: Floor Plans | C27: =_xlfn.XLOOKUP(C26,Design!$J$2:$J$151,Design!$A$2:$A$151, " - ",0,1) -> - | D27: =_xlfn.XLOOKUP(D26,Design!$J$2:$J$151,Design!$A$2:$A$151, " - ",0,1) -> - | E27: =_xlfn.XLOOKUP(E26,Design!$J$2:$J$151,Design!$A$2:$A$151, " - ",0,1) -> - | F27: =_xlfn.XLOOKUP(F26,Design!$J$2:$J$151,Design!$A$2:$A$151, " - ",0,1) -> - | G27: =_xlfn.XLOOKUP(G26,Design!$J$2:$J$151,Design!$A$2:$A$151, " - ",0,1) -> - | H27: =_xlfn.XLOOKUP(H26,Design!$J$2:$J$151,Design!$A$2:$A$151, " - ",0,1) -> - | I27: =_xlfn.XLOOKUP(I26,Design!$J$2:$J$151,Design!$A$2:$A$151, " - ",0,1) -> - | J27: =_xlfn.XLOOKUP(J26,Design!$J$2:$J$151,Design!$A$2:$A$151, " - ",0,1) -> - | ... N27: =_xlfn.XLOOKUP(N26,Design!$J$2:$J$151,Design!$A$2:$A$151, " - ",0,1) -> -
B28: 50% Design | C28: =_xlfn.XLOOKUP(C26,Design!$L$2:$L$151,Design!$A$2:$A$151, " - ",0,1) -> - | D28: =_xlfn.XLOOKUP(D26,Design!$L$2:$L$151,Design!$A$2:$A$151, " - ",0,1) -> - | E28: =_xlfn.XLOOKUP(E26,Design!$L$2:$L$151,Design!$A$2:$A$151, " - ",0,1) -> - | F28: =_xlfn.XLOOKUP(F26,Design!$L$2:$L$151,Design!$A$2:$A$151, " - ",0,1) -> - | G28: =_xlfn.XLOOKUP(G26,Design!$L$2:$L$151,Design!$A$2:$A$151, " - ",0,1) -> - | H28: =_xlfn.XLOOKUP(H26,Design!$L$2:$L$151,Design!$A$2:$A$151, " - ",0,1) -> - | I28: =_xlfn.XLOOKUP(I26,Design!$L$2:$L$151,Design!$A$2:$A$151, " - ",0,1) -> - | J28: =_xlfn.XLOOKUP(J26,Design!$L$2:$L$151,Design!$A$2:$A$151, " - ",0,1) -> - | ... N28: =_xlfn.XLOOKUP(N26,Design!$L$2:$L$151,Design!$A$2:$A$151, " - ",0,1) -> -
B29: 100% IFR | C29: =_xlfn.XLOOKUP(C26,Design!$N$2:$N$151,Design!$A$2:$A$151, "-",0,1) -> - | D29: =_xlfn.XLOOKUP(D26,Design!$N$2:$N$151,Design!$A$2:$A$151, "-",0,1) -> - | E29: =_xlfn.XLOOKUP(E26,Design!$N$2:$N$151,Design!$A$2:$A$151, "-",0,1) -> - | F29: =_xlfn.XLOOKUP(F26,Design!$N$2:$N$151,Design!$A$2:$A$151, "-",0,1) -> - | G29: =_xlfn.XLOOKUP(G26,Design!$N$2:$N$151,Design!$A$2:$A$151, "-",0,1) -> - | H29: =_xlfn.XLOOKUP(H26,Design!$N$2:$N$151,Design!$A$2:$A$151, "-",0,1) -> - | I29: =_xlfn.XLOOKUP(I26,Design!$N$2:$N$151,Design!$A$2:$A$151, "-",0,1) -> - | J29: =_xlfn.XLOOKUP(J26,Design!$N$2:$N$151,Design!$A$2:$A$151, "-",0,1) -> - | ... N29: =_xlfn.XLOOKUP(N26,Design!$N$2:$N$151,Design!$A$2:$A$151, "-",0,1) -> -
B30: IFP | C30: =_xlfn.XLOOKUP(C26,Design!$P$2:$P$151,Design!$A$2:$A$151, "-",0,1) -> - | D30: =_xlfn.XLOOKUP(D26,Design!$P$2:$P$151,Design!$A$2:$A$151, "-",0,1) -> - | E30: =_xlfn.XLOOKUP(E26,Design!$P$2:$P$151,Design!$A$2:$A$151, "-",0,1) -> - | F30: =_xlfn.XLOOKUP(F26,Design!$P$2:$P$151,Design!$A$2:$A$151, "-",0,1) -> - | G30: =_xlfn.XLOOKUP(G26,Design!$P$2:$P$151,Design!$A$2:$A$151, "-",0,1) -> - | H30: =_xlfn.XLOOKUP(H26,Design!$P$2:$P$151,Design!$A$2:$A$151, "-",0,1) -> - | I30: =_xlfn.XLOOKUP(I26,Design!$P$2:$P$151,Design!$A$2:$A$151, "-",0,1) -> - | J30: =_xlfn.XLOOKUP(J26,Design!$P$2:$P$151,Design!$A$2:$A$151, "-",0,1) -> - | ... N30: =_xlfn.XLOOKUP(N26,Design!$P$2:$P$151,Design!$A$2:$A$151, "-",0,1) -> -
B31: IFC | C31: =_xlfn.XLOOKUP(C26,Design!$Q$2:$Q$151,Design!$A$2:$A$151, "-") -> - | D31: =_xlfn.XLOOKUP(D26,Design!$Q$2:$Q$151,Design!$A$2:$A$151, "-") -> - | E31: =_xlfn.XLOOKUP(E26,Design!$Q$2:$Q$151,Design!$A$2:$A$151, "-") -> - | F31: =_xlfn.XLOOKUP(F26,Design!$Q$2:$Q$151,Design!$A$2:$A$151, "-") -> - | G31: =_xlfn.XLOOKUP(G26,Design!$Q$2:$Q$151,Design!$A$2:$A$151, "-") -> - | H31: =_xlfn.XLOOKUP(H26,Design!$Q$2:$Q$151,Design!$A$2:$A$151, "-") -> - | I31: =_xlfn.XLOOKUP(I26,Design!$Q$2:$Q$151,Design!$A$2:$A$151, "-") -> - | J31: =_xlfn.XLOOKUP(J26,Design!$Q$2:$Q$151,Design!$A$2:$A$151, "-") -> - | ... N31: =_xlfn.XLOOKUP(N26,Design!$Q$2:$Q$151,Design!$A$2:$A$151, "-") -> -
B32: Iss Record | C32: =_xlfn.XLOOKUP(C26,Design!$U$2:$U$151,Design!$A$2:$A$151, "-") -> - | D32: =_xlfn.XLOOKUP(D26,Design!$U$2:$U$151,Design!$A$2:$A$151, "-") -> - | E32: =_xlfn.XLOOKUP(E26,Design!$U$2:$U$151,Design!$A$2:$A$151, "-") -> - | G32: =_xlfn.XLOOKUP(G26,Design!$U$2:$U$151,Design!$A$2:$A$151, "-") -> - | H32: =_xlfn.XLOOKUP(H26,Design!$U$2:$U$151,Design!$A$2:$A$151, "-") -> - | I32: =_xlfn.XLOOKUP(I26,Design!$U$2:$U$151,Design!$A$2:$A$151, "-") -> - | J32: =_xlfn.XLOOKUP(J26,Design!$U$2:$U$151,Design!$A$2:$A$151, "-") -> - | K32: =_xlfn.XLOOKUP(K26,Design!$U$2:$U$151,Design!$A$2:$A$151, "-") -> - | L32: =_xlfn.XLOOKUP(L26,Design!$U$2:$U$151,Design!$A$2:$A$151, "-") -> - | M32: =_xlfn.XLOOKUP(M26,Design!$U$2:$U$151,Design!$A$2:$A$151, "-") -> - | N32: =_xlfn.XLOOKUP(N26,Design!$U$2:$U$151,Design!$A$2:$A$151, "-") -> -
B35: Past Due: | C35: 1D | D35: 2D | E35: 3D | F35: 4D | G35: 5D | H35: 6D | I35: 7D | J35: 8D | K35: 9D | L35: 10D | M35: 11D | N35: 12D
C36: =_xlfn.XLOOKUP($C$15-1,Design!$Q$2:$Q$151,Design!$A$2:$A$151, "-",0,1) -> - | D36: =_xlfn.XLOOKUP($C$15-2,Design!$Q$2:$Q$151,Design!$A$2:$A$151, "-",0,1) -> - | E36: =_xlfn.XLOOKUP($C$15-3,Design!$Q$2:$Q$151,Design!$A$2:$A$151, "-",0,1) -> - | F36: =_xlfn.XLOOKUP($C$15-4,Design!$Q$2:$Q$151,Design!$A$2:$A$151, "-",0,1) -> - | G36: =_xlfn.XLOOKUP($C$15-5,Design!$Q$2:$Q$151,Design!$A$2:$A$151, "-",0,1) -> - | H36: =_xlfn.XLOOKUP($C$15-6,Design!$Q$2:$Q$151,Design!$A$2:$A$151, "-",0,1) -> - | I36: =_xlfn.XLOOKUP($C$15-7,Design!$Q$2:$Q$151,Design!$A$2:$A$151, "-",0,1) -> - | J36: =_xlfn.XLOOKUP($C$15-8,Design!$Q$2:$Q$151,Design!$A$2:$A$151, "-",0,1) -> - | K36: =_xlfn.XLOOKUP($C$15-9,Design!$Q$2:$Q$151,Design!$A$2:$A$151, "-",0,1) -> - | L36: =_xlfn.XLOOKUP($C$15-10,Design!$Q$2:$Q$151,Design!$A$2:$A$151, "-",0,1) -> - | M36: =_xlfn.XLOOKUP($C$15-11,Design!$Q$2:$Q$151,Design!$A$2:$A$151, "-",0,1) -> - | N36: =_xlfn.XLOOKUP($C$15-12,Design!$Q$2:$Q$151,Design!$A$2:$A$151, "-",0,1) -> -

Sheet Info Needed
A2: 50% Design
A3: Address or Lat/Long
A4: Approved Floorplans
A5: Headend Location
A6: Parent or Child Site?
A7: Greenfield site?
A8: Project Specific Notes
A10: 90/100% CAD Set
A11: Packaging Preferences
A12: CAD Titleblock with Client Logo Images (dwg & jpgs)
A13: CAD Floor Plans of the building and The Site Plan or Survey (dwg files)
A14: Cover Sheet if/when available (dwg or pdf)
... A29: Any redlines/instructions for changes

Sheet Design-formattingv2
A1: NAME | B1: LOCATION | C1: A/E | D1: Phase (Design or CA) | E1: AE-PM Name | F1: AE-PM Contact | G1: S2 PM | H1: Project Status | I1: Floorplans Received | J1: Floor Plans Needed | K1: 50% IFR - Notora | L1: 50% IFR - AE | M1: 100% IFR - Notora | N1: 100% IFR - AE | O1: IFP - Notora | P1: IFP - AE | Q1: IFC | R1: Project Start | S1: Submittal | T1: Substantial Completion | U1: Issue For Record | V1: Completion | W1: Commissioning | X1: Action Item Needed | Y1: Comments
A2: ATL06 | B2: Atlanta | C2: Highland Associates | D2: Design | E2: Christopher Ritchie | F2: critchie@ha-ny.com | H2: A | I2: Supposed to be 4/7/2023 | J2: =IFERROR(WORKDAY(Table145[[#This Row],[50% IFR - AE]],-15), " ") | K2: Complete | M2: No Notora | N2: 10/3/2023- Complete | O2: No Notora | P2: 10/24/2023-Complete | Q2: 2/12/2024-complete | X2: Need to track down: Floor Plans, AHJ (Authorities having jurisdiction contact), enforced code | Y2: Location: East Point GA Lat Long: 33*38'30"N, 84*30'59"W FloorPlans to be updated Friday the 7th
A3: ATL07 | H3: A | J3: 5/13/2024-complete | K3: 45435 | L3: 45436 | N3: 45468
A4: AVC02 | H4: A | J4: =IFERROR(WORKDAY(Table145[[#This Row],[50% IFR - AE]],-15), " ") | L4: 3/25/2024-Complete | N4: 4/29/2024-complete | P4: 45427 | V4: Need as-builts/testing for AVC01. Some weirdness w AVC01 | X4: DAS and Public safety Proposal needed.
A5: AVC17 | B5: SOUTH HILL, VA | C5: Highland Associates | D5: Design | E5: Hector Hernandez | F5: hhernandez@ha-ny.com | G5: Bram Wathen | H5: A | I5: 44981 | J5: =IFERROR(WORKDAY(Table145[[#This Row],[50% IFR - AE]],-15), " ") | K5: 3/8/2023 - complete | L5: 3/20/2023- complete | M5: 4/17/2023 - complete | N5: 4/24/2023 - complete | O5: 6/2/2023 - complete | P5: 6/5/2023 - complete | Q5: 8/3/2023-Complete | X5: Update the IFC Date | Y5: 3 Different Issues. Need to confrim if power supply for fiber optical master is required. Need ROIP specs, Site Heat map.
A6: AVC18 | B6: SOUTH HILL, VA | C6: Highland Associates | D6: Design | E6: Hector Hernandez | F6: hhernandez@ha-ny.com | G6: Bram Wathen | H6: A | I6: 44988 | J6: =IFERROR(WORKDAY(Table145[[#This Row],[50% IFR - AE]],-15), " ") | K6: 3/15/2023 - complete | L6: 3/20/2023 - complete | M6: 4/17/2023 - complete | N6: 4/24/2023 - complete | O6: 6/2/2023 - complete | P6: 6/5/2023 - complete | Q6: 8/3/2023-Complete | X6: Update the IFC Date | Y6: Review Drawings prior to IFP
A7: AVC43 | B7: SOUTH HILL, VA | C7: Swanson Rink | D7: Design | E7: Ryan Sims | F7: RSims@swansonrink.com | H7: C | I7: 44874 | J7: =IFERROR(WORKDAY(Table145[[#This Row],[50% IFR - AE]],-15), " ") | K7: Complete | L7: 11/21/2022 - Complete | M7: Complete | P7: Complete | X7: 2x2 cabinet
A8: CCO07 | H8: A | J8: =IFERROR(WORKDAY(Table145[[#This Row],[50% IFR - AE]],-15), " ") | K8: 8/23/2023 - complete | L8: 9/7/2023 - complete | M8: No Notora | N8: 10/19/2023-Complete | O8: No Notora | P8: 11/7/2023-Complete
A9: CHI05 | B9: Chicago | I9: 45065 | J9: =IFERROR(WORKDAY(Table145[[#This Row],[50% IFR - AE]],-15), " ") | K9: 5/26/2023 - complete | Q9: 45384 | U9: No Notora | Y9: We need NT proposal
A10: CHI11 | B10: Chicago | I10: X | J10: =IFERROR(WORKDAY(Table145[[#This Row],[50% IFR - AE]],-15), " ") | K10: 5/26/2023 - complete | P10: 3/11/2024-Complete | Y10: We need NT proposal
A11: CHI22 | B11: Chicago | H11: A | J11: =IFERROR(WORKDAY(Table145[[#This Row],[50% IFR - AE]],-15), " ") | P11: 1/11/2024-COMPLETE | Q11: 1/19/2024-complete | Y11: IFP DRB17 Print
A12: CLT04 | B12: North Carolina | C12: Olson | D12: Design | E12: David Barber | F12: dbarber@olsson.com | G12: Bram Wathen | H12: A | I12: 44957 | J12: =IFERROR(WORKDAY(Table145[[#This Row],[50% IFR - AE]],-15), " ") | K12: 2/16/2023 - complete | L12: 2/16/2023 - complete | M12: 4/12/2023 -complete | N12: 4/26/2023 - complete | O12: 2/20/2024-Complete | P12: 2/21/2024-Complete | X12: Title block updates. Request sent to Stephen 5/11 | Y12: Get address and find cell towers
A13: CLT10 | B13: North Carolina | C13: Olsson | D13: Design | E13: Meg Plank | F13: mplank@olsson.com | H13: A | I13: X | J13: =IFERROR(WORKDAY(Table145[[#This Row],[50% IFR - AE]],-15), " ") | K13: 6/30/2023 - Complete | L13: 7/06/2023 - Complete | M13: 8/25/2023 - complete | N13: 8/31/2023-Complete | O13: 2/20/2024-Complete | P13: 2/21/2024-Complete | X13: Site Plans & Floor Plans | Y13: Project Kick off June 1st.
A14: CLT11 | C14: Olson | D14: Design | E14: David Barber | F14: dbarber@olsson.com | G14: Bram Wathen | H14: P | J14: =IFERROR(WORKDAY(Table145[[#This Row],[50% IFR - AE]],-15), " ")
A15: CLT17 | C15: Olson | D15: Design | E15: David Barber | F15: dbarber@olsson.com | G15: Bram Wathen | H15: P | I15: X | J15: =IFERROR(WORKDAY(Table145[[#This Row],[50% IFR - AE]],-15), " ") | K15: 45240 | L15: 11/16/2023-complete | M15: 45280 | N15: 1/3/2024-Complete | P15: 2/14/2024-Complete | Y15: Not doing the CADs for this one
A16: CPQ03 | B16: BRAZIL | C16: Deerns | D16: Design | E16: Gabriel Pereira | F16: gabriel.pereira@deerns.com | H16: C | J16: =IFERROR(WORKDAY(Table145[[#This Row],[50% IFR - AE]],-15), " ") | Q16: 45215
A17: CPQ07 | B17: BRAZIL | C17: Deerns | D17: Design | E17: Gabriel Pereira | F17: gabriel.pereira@deerns.com | H17: C | I17: X | J17: =IFERROR(WORKDAY(Table145[[#This Row],[50% IFR - AE]],-15), " ") | K17: 2/17/2023 - complete | L17: 1/11/2023 - Complete | X17: Need updated IFR Date, if we're doing the CAD's | Y17: 1/25: emailed Kelwin asking for info
A18: CPQ08 | J18: =IFERROR(WORKDAY(Table145[[#This Row],[50% IFR - AE]],-15), " ") | L18: 1/8/2024-Complete
A19: CPQ11 | B19: BRAZIL | C19: Deerns | D19: Design | E19: Gabriel Pereira | F19: gabriel.pereira@deerns.com | H19: C | I19: X | J19: =IFERROR(WORKDAY(Table145[[#This Row],[50% IFR - AE]],-15), " ") | K19: Complete
A20: CYS17 | B20: Cheyanne | C20: Jacobs | D20: Design | E20: Kristin McCue | F20: Kristin.McCue@jacobs.com | H20: C | J20: =IFERROR(WORKDAY(Table145[[#This Row],[50% IFR - AE]],-15), " ") | M20: Complete | N20: 1/24/2023-complete | O20: complete | P20: complete | X20: IFP from WT | Y20: 2/6/2023: WT indicates a 2/13 delivery date. 2/6/2023: emailed WT requesting IFP update 1/24: recieved updated design fromWT, uploaded 1/20: recieved design from David. Emailed AE the drawing list and uploaded files to AE and S2 1/19: This is a 'WT' site, emailed Davide requesting design update 1/18: sent philip design pkg 4 email 1/13/23: emailed Kristen requesting update
A21: DFW20 | J21: =IFERROR(WORKDAY(Table145[[#This Row],[50% IFR - AE]],-15), " ") | Q21: 3/8/2024-complete
A22: DSM12 | B22: DES MOINES | C22: Burns & McDonnell | D22: Design | E22: Kylie Hornbeck | F22: khornbeck@burnsmcd.com | H22: C | J22: =IFERROR(WORKDAY(Table145[[#This Row],[50% IFR - AE]],-15), " ") | X22: Nick coordinating with AE
A23: DSM14 | B23: DES MOINES | C23: Burns & McDonnell | D23: Design | E23: Kylie Hornbeck | F23: khornbeck@burnsmcd.com | H23: C | J23: =IFERROR(WORKDAY(Table145[[#This Row],[50% IFR - AE]],-15), " ") | X23: Nick coordinating with AE
A24: DSM15 | B24: DES MOINES | C24: Burns & McDonnell | D24: Design | E24: Kylie Hornbeck | F24: khornbeck@burnsmcd.com | H24: C | J24: =IFERROR(WORKDAY(Table145[[#This Row],[50% IFR - AE]],-15), " ") | X24: Need Floorplans & Schedule - Nick to follow up with AE
A25: DSM40 | B25: DES MOINES | C25: Burns & McDonnell | D25: Design | E25: Kylie Hornbeck | F25: khornbeck@burnsmcd.com | H25: C | J25: =IFERROR(WORKDAY(Table145[[#This Row],[50% IFR - AE]],-15), " ") | Q25: 5/8/2024-Complete | X25: Nick coordinating with AE
A26: DSM41 | B26: DES MOINES | C26: Burns & McDonnell | D26: Design | E26: Kylie Hornbeck | F26: khornbeck@burnsmcd.com | H26: C | J26: =IFERROR(WORKDAY(Table145[[#This Row],[50% IFR - AE]],-15), " ") | X26: Nick coordinating with AE
A27: EAT04 | B27: WEANATCHEE, WA | C27: ESD | D27: Design | E27: Chad Mendell | F27: cmendell@esdglobal.com | H27: C | J27: =IFERROR(WORKDAY(Table145[[#This Row],[50% IFR - AE]],-15), " ") | K27: Complete | L27: 12/1/2022 - Complete | M27: Complete | N27: 1/12/2023 - Complete | O27: 1/19/23-complete | P27: 1/26/2023-complete | Q27: 5/31/2023-Complete | Y27: 2/6/23: IFC is TBD no update1/25: recieved updated design from Philip, uploaded to AE and S2 1/19: recieved updated design from Philip, uploaded to BIM and S2 1/19: uploaded specs, requested IFP design from Philip 1/18: sent IFP instructions to Notora
A28: EAT05 | B28: WEANATCHEE, WA | C28: ESD | D28: Bid | E28: Chad Mendell | F28: cmendell@esdglobal.com | H28: A | I28: 45033 | J28: =IFERROR(WORKDAY(Table145[[#This Row],[50% IFR - AE]],-15), " ") | K28: 5/3/2023 - complete | L28: 4/20/2023 - complete | M28: 5/19/2023 - complete | N28: 5/25/2023 - complete | O28: complete | P28: 6/13/2023 - complete | Q28: 3/5/2024-Complete | X28: Notora Internal review return 5/1-5/2 | Y28: May
A29: EAT06 | H29: A | J29: =IFERROR(WORKDAY(Table145[[#This Row],[50% IFR - AE]],-15), " ") | K29: 8/9/2023--Complete | L29: 8/1/2023-Complete | N29: 9/7/2023 - complete | P29: 9/26/2023-Complete
A30: EAT09 | H30: A | I30: 8/16/2023? | J30: =IFERROR(WORKDAY(Table145[[#This Row],[50% IFR - AE]],-15), " ") | N30: 9/7/2023 - complete | P30: 9/26/2023-Complete
A31: EAT12 | B31: WEANATCHEE, WA | C31: ESD | D31: Design | E31: Chad Mendell | F31: cmendell@esdglobal.com | H31: A | J31: =IFERROR(WORKDAY(Table145[[#This Row],[50% IFR - AE]],-15), " ") | K31: 2/20/2023-complete | L31: 2/23/2023-complete | M31: 3/20/2023 - complete | N31: 3/9/2023 - complete | O31: complete | P31: 4/6/2023 - complete | Q31: 3/21/2024 Complete | X31: Change notes in the Public Safety. Cover the L1 containment unless AHJ approves alternate means and methods. Pull box detail | Y31: 2/15: in internal review 2/15: requested update from Notora 2/3/23: floor plan delivered to Notora 2/1: Harold got floorplans today; 1/18: Design is resuming with meeting 1/30
A32: EAT13 | B32: WEANATCHEE, WA | C32: ESD | D32: Design | E32: Chad Mendell | F32: cmendell@esdglobal.com | H32: A | I32: X | J32: =IFERROR(WORKDAY(Table145[[#This Row],[50% IFR - AE]],-15), " ") | K32: 6/14/2023 - complete | L32: 6/15/2023 - complete | M32: 7/18/2023-Complete | N32: 7/20/2023-Complete | O32: 8/1/2023-Complete | P32: 8/2/2023-Complete | Q32: 4/9/2024-complete | Y32: Starting the week of 5/8
A33: EAT14 | B33: WEANATCHEE, WA | H33: A | I33: X | J33: =IFERROR(WORKDAY(Table145[[#This Row],[50% IFR - AE]],-15), " ") | K33: 9/27/2023 - complete | L33: 9/21/2023 - Complete | M33: 10/27/2023-complete | N33: 11/28/2023-Complete | P33: 12/14/2023 - Complete | Q33: 45427 | X33: Battery backups, near far, L1 containement?
A34: FTY01 | J34: =IFERROR(WORKDAY(Table145[[#This Row],[50% IFR - AE]],-15), " ") | Q34: 4/25/2024-Complete
A35: FTY02 | B35: GEORGIA | C35: Morrison Hershfield | D35: Bid | E35: Lee Percy | F35: LPercy@morrisonhershfield.com | J35: =IFERROR(WORKDAY(Table145[[#This Row],[50% IFR - AE]],-15), " ") -> 45139 | K35: 8/15/2023-Complete | L35: 45160 | M35: 9/8/2023 - complete | N35: 9/12/2023 - complete | O35: 10/10/2023 - Complete | P35: 10/12/2023- Complete | X35: Need to update the BOM to comba unit.
A36: FTY03 | J36: =IFERROR(WORKDAY(Table145[[#This Row],[50% IFR - AE]],-15), " ") | L36: 5/9/2024-Complete | N36: 45446 | P36: 45474
A37: IAD05 | J37: =IFERROR(WORKDAY(Table145[[#This Row],[50% IFR - AE]],-15), " ") | Q37: TBD
A38: IAD12 | B38: LEESBURG, VA | C38: Syska | D38: Design | E38: Liam Wall | F38: lwall@syska.com | H38: A | J38: =IFERROR(WORKDAY(Table145[[#This Row],[50% IFR - AE]],-15), " ") | K38: Complete | L38: 2/22/2023 - Complete | N38: 3/29/2023 - Complete | P38: 45042 | Q38: 45076
A39: IAD13 | B39: LEESBURG, VA | C39: Syska | D39: Design | E39: Liam Wall | F39: lwall@syska.com | H39: A | J39: =IFERROR(WORKDAY(Table145[[#This Row],[50% IFR - AE]],-15), " ") | K39: Complete | L39: Complete | M39: Complete | N39: 2/9/2023 - Complete | O39: Complete | P39: 3/24/2023 - Complete | Q39: 45050 | X39: Riser Info - no IFR yet
A40: IAD14 | B40: LEESBURG, VA | D40: Bid | E40: TBD | H40: A | J40: =IFERROR(WORKDAY(Table145[[#This Row],[50% IFR - AE]],-15), " ")
A41: LVL06 | B41: Drawing Review | D41: Design | E41: Fran Carlos | F41: fclaros@swansonrink.com | H41: A | I41: 44987 | J41: =IFERROR(WORKDAY(Table145[[#This Row],[50% IFR - AE]],-15), " ") | K41: 3/17/2023 - complete | L41: 3/21/2023 - complete | N41: 45041 | O41: 44931 | P41: 44931 | X41: 4/26/2023: Need to adjust to keep equipement in cells 1-3. See email. | Y41: Meet with Preston - make sure he updated prints with S2A changes
A42: LVL07 | H42: A | J42: =IFERROR(WORKDAY(Table145[[#This Row],[50% IFR - AE]],-15), " ") | K42: Complete | L42: 8/21/2023-Complete | M42: No Notora | N42: 9/29/2023--Complete | O42: No Notora | P42: 10/19/2023-Complete | Q42: 2/19/2024-Complete
A43: LVL11 | B43: BOYDTON, VA | C43: Swanson Rink | D43: Design | E43: Ryan Sims | F43: RSims@swansonrink.com | H43: C | J43: =IFERROR(WORKDAY(Table145[[#This Row],[50% IFR - AE]],-15), " ") | K43: Complete | L43: 1/23/2023 - Complete | M43: 2/20/2023 - Complete | N43: 2/27/2023 - Complete | P43: 45007 | Q43: 45061 | Y43: 2/1: Emailed James for desgin review & emailed Preson for titleblock, etc
A44: LVL12 | I44: X | J44: =IFERROR(WORKDAY(Table145[[#This Row],[50% IFR - AE]],-15), " ") | L44: 12/21/2023-Complete | M44: =IFERROR(WORKDAY(Table145[[#This Row],[100% IFR - AE]],-5), " ") | N44: 2/5/2024-Complete | P44: 45345 | X44: Need to provision for off-air as a backup if needed. Need antenna structure to support it.
A45: LVL13-14 | J45: =IFERROR(WORKDAY(Table145[[#This Row],[50% IFR - AE]],-15), " ") -> 45376 | K45: 3/28/2024-Complete | L45: 45397 | M45: 45425 | N45: 45426 | P45: 45453 | V45: Loop clark into dicusscion. We will go back to LVL08
A46: LYH03 | B46: BOYDTON, VA | C46: Highland Associates | D46: BID | E46: Hector Hernandez | F46: hhernandez@ha-ny.com | H46: C | J46: =IFERROR(WORKDAY(Table145[[#This Row],[50% IFR - AE]],-15), " ") | X46: Need Floorplans & Schedule
A47: LYH10 | B47: BOYDTON, VA | C47: Highland Associates | D47: Design | E47: Hector Hernandez | F47: hhernandez@ha-ny.com | G47: Bram Wathen | H47: P | J47: =IFERROR(WORKDAY(Table145[[#This Row],[50% IFR - AE]],-15), " ") | K47: Complete | L47: 11/29/2022 - Complete | M47: Complete | N47: complete | O47: Complete | P47: 45001 | Q47: 6/28/2023 - complete | X47: IFC Pushed to mid july--Will follow up later 04/28/2023 | Y47: 4/18 Specs updated and sent to Paul Duffy for upload. Need to upload to BIM360
A48: MNZ01 | B48: MANASSAS, VA | C48: Sysksa | D48: Design | E48: Christopher Lay | F48: clay@syska.com | H48: A | I48: X | J48: =IFERROR(WORKDAY(Table145[[#This Row],[50% IFR - AE]],-15), " ") | Y48: 1/26: emailed Chris asking for info
A49: MNZ03 | B49: MANASSAS, VA | C49: Sysksa | D49: Design | E49: Christopher Lay | F49: clay@syska.com | H49: A | J49: =IFERROR(WORKDAY(Table145[[#This Row],[50% IFR - AE]],-15), " ") | P49: 3/3/2023 - Complete | Q49: Mid June
A50: MNZ04 | J50: =IFERROR(WORKDAY(Table145[[#This Row],[50% IFR - AE]],-15), " ") | L50: 4/23/2024-Complete | N50: 45456 | P50: 45476
A51: MNZ05 | J51: =IFERROR(WORKDAY(Table145[[#This Row],[50% IFR - AE]],-15), " ") -> 45414 | L51: 45435 | N51: 45484
A52: MWH08 | B52: Quincy | H52: A | I52: X | J52: =IFERROR(WORKDAY(Table145[[#This Row],[50% IFR - AE]],-15), " ") | L52: 1/19/2024-Complete | M52: =IFERROR(WORKDAY(Table145[[#This Row],[100% IFR - AE]],-5), " ") | N52: 3/24/2024-complete
A53: PHX14 | J53: =IFERROR(WORKDAY(Table145[[#This Row],[50% IFR - AE]],-15), " ")
A54: PHX16 | B54: PHOENIX, AZ | I54: X | J54: =IFERROR(WORKDAY(Table145[[#This Row],[50% IFR - AE]],-15), " ")
A55: PHX17 | B55: PHOENIX, AZ | I55: X | J55: =IFERROR(WORKDAY(Table145[[#This Row],[50% IFR - AE]],-15), " ")
A56: PHX15 | B56: PHOENIX, AZ | I56: X | J56: =IFERROR(WORKDAY(Table145[[#This Row],[50% IFR - AE]],-15), " ") -> 45440 | K56: Rough Date | L56: 45461
A57: PHX61 | J57: =IFERROR(WORKDAY(Table145[[#This Row],[50% IFR - AE]],-15), " ") | K57: 11/9/2023-Complete | N57: 11/16/2023-Complete
A58: PHX71 | B58: PHOENIX, AZ | C58: Jacobs | D58: Design | E58: Blake Giles | F58: Blake.Giles@jacobs.com | H58: C | I58: X | J58: =IFERROR(WORKDAY(Table145[[#This Row],[50% IFR - AE]],-15), " ") | X58: Repackaging Site
A59: PHX72 | B59: PHOENIX, AZ | C59: Jacobs | D59: Design | E59: Blake Giles | F59: Blake.Giles@jacobs.com | H59: A | J59: =IFERROR(WORKDAY(Table145[[#This Row],[50% IFR - AE]],-15), " ") -> 44985 | K59: Complete | L59: 45006 | P59: 45089 | X59: QA Form, SPEC, Review A/E Sumittal | Y59: IFP Pushed back to 5/23
A60: PHX73 | B60: PHOENIX, AZ | J60: =IFERROR(WORKDAY(Table145[[#This Row],[50% IFR - AE]],-15), " ") -> 45141 | K60: 8/11/2023 - complete | L60: 45162 | M60: No Notora | N60: 45190 | O60: No Notora | P60: 10/17/2023-Complete
A61: PHX74 | B61: PHOENIX, AZ | H61: A | I61: X | J61: =IFERROR(WORKDAY(Table145[[#This Row],[50% IFR - AE]],-15), " ") | K61: 10/20/2023-Complete | L61: 11/9/2023-Complete | M61: SPEC Needed | N61: 45268 | O61: No Notora | P61: 45301
A62: PHX81 | B62: PHOENIX, AZ | C62: Jacobs | D62: Design | E62: Blake Giles | F62: Blake.Giles@jacobs.com | H62: C | J62: =IFERROR(WORKDAY(Table145[[#This Row],[50% IFR - AE]],-15), " ") | K62: Complete | L62: 11/10/2022 - Complete | M62: Complete | N62: 12/9/2022 - Complete | O62: 1/25/2023-complete | P62: 1/30/2023-complete | Q62: 3/11/2024-Complete | V62: No Notora | X62: Notora Needs IFC Date | Y62: 1/26: recieved package from WT, uploaded. 1/20: emailed David at WT requesting package 1/19: specs sent to PM
A63: PHX82 | B63: PHOENIX, AZ | D63: Design | G63: Bram Wathen | H63: A | J63: =IFERROR(WORKDAY(Table145[[#This Row],[50% IFR - AE]],-15), " ") -> 45022 | L63: 45043 | M63: 45079 | N63: 45083 | P63: 45106 | X63: 4/18 Harold to Review Design. SPECS due June 1 | Y63: We need to review 50% set
A64: PHX83 | B64: PHOENIX, AZ | J64: =IFERROR(WORKDAY(Table145[[#This Row],[50% IFR - AE]],-15), " ")
A65: SAT14 | J65: =IFERROR(WORKDAY(Table145[[#This Row],[50% IFR - AE]],-15), " ") | Q65: 45428
A66: SAT15 | B66: SAN ANTONIO, TX | C66: Page Southerland Page Inc. | D66: Design | E66: Lauren Alexander | F66: lalexander@pagethink.com | H66: A | I66: X | J66: =IFERROR(WORKDAY(Table145[[#This Row],[50% IFR - AE]],-15), " ") | K66: Complete | L66: Complete | M66: Complete | N66: 12/14/2022 - Complete | O66: No NT | P66: 45428 | Q66: 45019 | X66: IFC date determined after permitting
A67: SAT17 | I67: X | J67: =IFERROR(WORKDAY(Table145[[#This Row],[50% IFR - AE]],-15), " ") | L67: 3/27/2024-Complete | M67: =IFERROR(WORKDAY(Table145[[#This Row],[100% IFR - AE]],-5), " ") | N67: 5/9/2024-Complete | P67: 45449
A68: SAT16 | I68: X | J68: =IFERROR(WORKDAY(Table145[[#This Row],[50% IFR - AE]],-15), " ") | K68: 10/26/2023 - complete | L68: 11/29/2023-Complete | N68: 1/9/2024-Complete | P68: 2/15/2024-Complete
A69: SAT40 | B69: SAN ANTONIO, TX | C69: Page Southerland Page Inc. | D69: Design | E69: Lauren Alexander | F69: lalexander@pagethink.com | H69: A | J69: =IFERROR(WORKDAY(Table145[[#This Row],[50% IFR - AE]],-15), " ") | K69: Complete | L69: 11/30/2022 - Complete | M69: Complete | N69: 1/20/2023 - Complete | O69: 2/15/2023 - Complete | P69: 44960 | Q69: 8/2/2023--Complete | X69: Notora Needs Updated IFP Titleblock
A70: SAT80/81 | B70: SAN ANTONIO, TX | C70: Page Southerland Page Inc. | D70: Design | E70: Alan McClung | F70: amcclung@pagethink.com | H70: A | J70: =IFERROR(WORKDAY(Table145[[#This Row],[50% IFR - AE]],-15), " ") | K70: Complete | L70: Complete | M70: Complete | N70: 7/11/2023--Complete | X70: Notora Needs Floorplans & IFC Dates
A71: SAT82 | I71: X | J71: =IFERROR(WORKDAY(Table145[[#This Row],[50% IFR - AE]],-15), " ") | K71: 10/31/2023 - complete | L71: 12/4/2023-Complete | N71: 1/16/2024-Complete | P71: 2/6/2024-Complete | Q71: 44980
A72: SAT90 | I72: X | J72: =IFERROR(WORKDAY(Table145[[#This Row],[50% IFR - AE]],-15), " ") | P72: 2/15/2024-Complete
A73: SAT89 | B73: SAN ANTONIO, TX | H73: A | I73: X | J73: =IFERROR(WORKDAY(Table145[[#This Row],[50% IFR - AE]],-15), " ") | K73: 10/25/2023 - complete | L73: 11/15/2023-Complete | M73: Stephen To deliver | N73: 1/4/2024-Complete | P73: 2/15/2024-Complete
A74: SJC02 | B74: SAN JOSE, CA | C74: Jacobs | D74: Design | E74: Kristin McCue | F74: Kristin.McCue@jacobs.com | H74: A | J74: =IFERROR(WORKDAY(Table145[[#This Row],[50% IFR - AE]],-15), " ") | K74: Complete | L74: Complete | M74: 9/8/2023 - complete | N74: 9/14/2023 - complete | O74: 10/20/2023-Complete | P74: 45458 | Y74: Project is on hold while "they" are working through the IFP comments
A75: SJC04 | B75: SAN JOSE, CA | C75: Jacobs | D75: Bid | E75: Kristin McCue | F75: Kristin.McCue@jacobs.com | H75: P | J75: =IFERROR(WORKDAY(Table145[[#This Row],[50% IFR - AE]],-15), " ") -> 45470 | L75: 45491 | N75: 45547
A76: YQB01/02 | B76: QUEBEC CITY | G76: Bram Wathen | H76: A | I76: X | J76: =IFERROR(WORKDAY(Table145[[#This Row],[50% IFR - AE]],-15), " ") | N76: 7/11/2023-Complete | O76: 8/7/2023 - Complete | P76: 10/4/2023 - complete | Q76: 2/27/2024-complete
A77: YQB04 | B77: QUEBEC CITY | G77: Bram Wathen | H77: A | I77: X | J77: =IFERROR(WORKDAY(Table145[[#This Row],[50% IFR - AE]],-15), " ") | K77: 3/3/2023 - complete | L77: 3/3/2023 - complete | M77: 3/16/2023- complete | N77: 3/20/2023 - complete | O77: 6/9/2023 - complete | P77: 6/15/2023 - complete | Q77: 11/15/2023-complete
A78: YQB06 | B78: QUEBEC CITY | H78: A | I78: X | J78: =IFERROR(WORKDAY(Table145[[#This Row],[50% IFR - AE]],-15), " ") | K78: 5/1/2023 - complete | L78: 4/24/2023 - complete | M78: 6/22/2023--Complete | N78: 6/27/2023--Complete | O78: No Notora | P78: 9/25/2023 - Complete | Q78: 2/2/2024-Complete | X78: Site Plans email sent.
A79: YQB11 | B79: QUEBEC CITY | H79: A | I79: X | J79: =IFERROR(WORKDAY(Table145[[#This Row],[50% IFR - AE]],-15), " ") | K79: 5/8/2023 - complete | L79: 5/12/2023 - complete | M79: 7/1/2023 - complete | N79: 7/25/2023--Complete | O79: 45198 | P79: 12/12/2023-Complete | Q79: 4/9/2024-Complete
A80: YTO10 | B80: Toronto | D80: Bid | E80: Saeed Akbari | F80: SAkbari@morrisonhershfield.com | H80: A | J80: =IFERROR(WORKDAY(Table145[[#This Row],[50% IFR - AE]],-15), " ")
A81: YTO11 | B81: Toronto | C81: Morrison Hershfield | D81: Design | E81: Saeed Akbari | F81: SAkbari@morrisonhershfield.com | H81: A | I81: X | J81: =IFERROR(WORKDAY(Table145[[#This Row],[50% IFR - AE]],-15), " ") | K81: Complete | L81: 9/26/2022 - Complete | M81: Complete | N81: 2/3/2023 - Complete | O81: Complete | P81: 8/8/2023 - Complete | Q81: 45338 | V81: Need to update note & Site plan | X81: Just the Drawings-Update Dates (7-10) | Y81: We will not be submitting a 50% design (or 100% draft as they call it); once we get comments back from Microsoft on YTO40, then they will have us make the same changes to YTO11 and then we will submit YTO11
A82: YTO14 | B82: Toronto | C82: Morrison Hershfield | D82: Design | E82: Saeed Akbari | F82: SAkbari@morrisonhershfield.com | G82: Bram Wathen | H82: A | I82: X | J82: =IFERROR(WORKDAY(Table145[[#This Row],[50% IFR - AE]],-15), " ") | K82: 5/3/2023 - complete | L82: 8/26/2023- Complete | M82: 6/13/2023 - complete | N82: tbd | Q82: TBD | V82: Need to update note & Site plan | X82: Set up meeting w Jim + Harold to discuss the Colo 5 Elec 3 Riser room for fiber. | Y82: Guard house is the same as YTO11 & YTO40. Talk to Mianna for updated plans. 100 % changed to October 16
A83: YTO40 | B83: Toronto | C83: Morrison Hershfield | D83: Design | E83: Saeed Akbari | F83: SAkbari@morrisonhershfield.com | H83: A | I83: X | J83: =IFERROR(WORKDAY(Table145[[#This Row],[50% IFR - AE]],-15), " ") | K83: Complete | L83: Complete | M83: Complete | N83: 1/5/2023 - Complete | O83: 2/14/2023 - Completed | P83: 45435 | Q83: TBD | V83: Need to update antenna note & Site plan | X83: Need IFC Dates | Y83: AE should receive comments back from Microsoft on 1/16 and then we will have 5 days to make changes and issue 100% design
J84: =IFERROR(WORKDAY(Table145[[#This Row],[50% IFR - AE]],-15), " ")
J85: =IFERROR(WORKDAY(Table145[[#This Row],[50% IFR - AE]],-15), " ")
J86: =IFERROR(WORKDAY(Table145[[#This Row],[50% IFR - AE]],-15), " ")
J87: =IFERROR(WORKDAY(Table145[[#This Row],[50% IFR - AE]],-15), " ")
J88: =IFERROR(WORKDAY(Table145[[#This Row],[50% IFR - AE]],-15), " ")
J89: =IFERROR(WORKDAY(Table145[[#This Row],[50% IFR - AE]],-15), " ")
J90: =IFERROR(WORKDAY(Table145[[#This Row],[50% IFR - AE]],-15), " ")
J91: =IFERROR(WORKDAY(Table145[[#This Row],[50% IFR - AE]],-15), " ")
J92: =IFERROR(WORKDAY(Table145[[#This Row],[50% IFR - AE]],-15), " ")
J93: =IFERROR(WORKDAY(Table145[[#This Row],[50% IFR - AE]],-15), " ")
J94: =IFERROR(WORKDAY(Table145[[#This Row],[50% IFR - AE]],-15), " ")
J95: =IFERROR(WORKDAY(Table145[[#This Row],[50% IFR - AE]],-15), " ")
... J134: =IFERROR(WORKDAY(Table145[[#This Row],[50% IFR - AE]],-15), " ")

Sheet Design-formattingv1
A1: NAME | B1: LOCATION | C1: A/E | D1: Phase (Design or CA) | E1: AE-PM Name | F1: AE-PM Contact | G1: S2 PM | H1: Project Status | I1: Floorplans Received | J1: Floor Plans Needed | K1: 50% IFR - Notora | L1: 50% IFR - AE | M1: 100% IFR - Notora | N1: 100% IFR - AE | O1: IFP - Notora | P1: IFP - AE | Q1: IFC | R1: Project Start | S1: Submittal | T1: Substantial Completion | U1: Issue For Record | V1: Completion | W1: Commissioning | X1: Action Item Needed | Y1: Comments
A2: ATL06 | B2: Atlanta | C2: Highland Associates | D2: Design | E2: Christopher Ritchie | F2: critchie@ha-ny.com | H2: A | I2: Supposed to be 4/7/2023 | J2: =IFERROR(WORKDAY(Table14[[#This Row],[50% IFR - AE]],-15), " ") | K2: Complete | M2: No Notora | N2: 10/3/2023- Complete | O2: No Notora | P2: 10/24/2023-Complete | Q2: 2/12/2024-complete | X2: Need to track down: Floor Plans, AHJ (Authorities having jurisdiction contact), enforced code | Y2: Location: East Point GA Lat Long: 33*38'30"N, 84*30'59"W FloorPlans to be updated Friday the 7th
A3: ATL07 | H3: A | J3: 5/13/2024-complete | K3: 45435 | L3: 45436 | N3: 45468
A4: AVC02 | H4: A | J4: =IFERROR(WORKDAY(Table14[[#This Row],[50% IFR - AE]],-15), " ") | L4: 3/25/2024-Complete | N4: 4/29/2024-complete | P4: 45427 | V4: Need as-builts/testing for AVC01. Some weirdness w AVC01 | X4: DAS and Public safety Proposal needed.
A5: AVC17 | B5: SOUTH HILL, VA | C5: Highland Associates | D5: Design | E5: Hector Hernandez | F5: hhernandez@ha-ny.com | G5: Bram Wathen | H5: A | I5: 44981 | J5: =IFERROR(WORKDAY(Table14[[#This Row],[50% IFR - AE]],-15), " ") | K5: 3/8/2023 - complete | L5: 3/20/2023- complete | M5: 4/17/2023 - complete | N5: 4/24/2023 - complete | O5: 6/2/2023 - complete | P5: 6/5/2023 - complete | Q5: 8/3/2023-Complete | X5: Update the IFC Date | Y5: 3 Different Issues. Need to confrim if power supply for fiber optical master is required. Need ROIP specs, Site Heat map.
A6: AVC18 | B6: SOUTH HILL, VA | C6: Highland Associates | D6: Design | E6: Hector Hernandez | F6: hhernandez@ha-ny.com | G6: Bram Wathen | H6: A | I6: 44988 | J6: =IFERROR(WORKDAY(Table14[[#This Row],[50% IFR - AE]],-15), " ") | K6: 3/15/2023 - complete | L6: 3/20/2023 - complete | M6: 4/17/2023 - complete | N6: 4/24/2023 - complete | O6: 6/2/2023 - complete | P6: 6/5/2023 - complete | Q6: 8/3/2023-Complete | X6: Update the IFC Date | Y6: Review Drawings prior to IFP
A7: AVC43 | B7: SOUTH HILL, VA | C7: Swanson Rink | D7: Design | E7: Ryan Sims | F7: RSims@swansonrink.com | H7: C | I7: 44874 | J7: =IFERROR(WORKDAY(Table14[[#This Row],[50% IFR - AE]],-15), " ") | K7: Complete | L7: 11/21/2022 - Complete | M7: Complete | P7: Complete | X7: 2x2 cabinet
A8: CCO07 | H8: A | J8: =IFERROR(WORKDAY(Table14[[#This Row],[50% IFR - AE]],-15), " ") | K8: 8/23/2023 - complete | L8: 9/7/2023 - complete | M8: No Notora | N8: 10/19/2023-Complete | O8: No Notora | P8: 11/7/2023-Complete
A9: CHI05 | B9: Chicago | I9: 45065 | J9: =IFERROR(WORKDAY(Table14[[#This Row],[50% IFR - AE]],-15), " ") | K9: 5/26/2023 - complete | Q9: 45384 | U9: No Notora | Y9: We need NT proposal
A10: CHI11 | B10: Chicago | I10: X | J10: =IFERROR(WORKDAY(Table14[[#This Row],[50% IFR - AE]],-15), " ") | K10: 5/26/2023 - complete | P10: 3/11/2024-Complete | Y10: We need NT proposal
A11: CHI22 | B11: Chicago | H11: A | J11: =IFERROR(WORKDAY(Table14[[#This Row],[50% IFR - AE]],-15), " ") | P11: 1/11/2024-COMPLETE | Q11: 1/19/2024-complete | Y11: IFP DRB17 Print
A12: CLT04 | B12: North Carolina | C12: Olson | D12: Design | E12: David Barber | F12: dbarber@olsson.com | G12: Bram Wathen | H12: A | I12: 44957 | J12: =IFERROR(WORKDAY(Table14[[#This Row],[50% IFR - AE]],-15), " ") | K12: 2/16/2023 - complete | L12: 2/16/2023 - complete | M12: 4/12/2023 -complete | N12: 4/26/2023 - complete | O12: 2/20/2024-Complete | P12: 2/21/2024-Complete | X12: Title block updates. Request sent to Stephen 5/11 | Y12: Get address and find cell towers
A13: CLT10 | B13: North Carolina | C13: Olsson | D13: Design | E13: Meg Plank | F13: mplank@olsson.com | H13: A | I13: X | J13: =IFERROR(WORKDAY(Table14[[#This Row],[50% IFR - AE]],-15), " ") | K13: 6/30/2023 - Complete | L13: 7/06/2023 - Complete | M13: 8/25/2023 - complete | N13: 8/31/2023-Complete | O13: 2/20/2024-Complete | P13: 2/21/2024-Complete | X13: Site Plans & Floor Plans | Y13: Project Kick off June 1st.
A14: CLT11 | C14: Olson | D14: Design | E14: David Barber | F14: dbarber@olsson.com | G14: Bram Wathen | H14: P | J14: =IFERROR(WORKDAY(Table14[[#This Row],[50% IFR - AE]],-15), " ")
A15: CLT17 | C15: Olson | D15: Design | E15: David Barber | F15: dbarber@olsson.com | G15: Bram Wathen | H15: P | I15: X | J15: =IFERROR(WORKDAY(Table14[[#This Row],[50% IFR - AE]],-15), " ") | K15: 45240 | L15: 11/16/2023-complete | M15: 45280 | N15: 1/3/2024-Complete | P15: 2/14/2024-Complete | Y15: Not doing the CADs for this one
A16: CPQ03 | B16: BRAZIL | C16: Deerns | D16: Design | E16: Gabriel Pereira | F16: gabriel.pereira@deerns.com | H16: C | J16: =IFERROR(WORKDAY(Table14[[#This Row],[50% IFR - AE]],-15), " ") | Q16: 45215
A17: CPQ07 | B17: BRAZIL | C17: Deerns | D17: Design | E17: Gabriel Pereira | F17: gabriel.pereira@deerns.com | H17: C | I17: X | J17: =IFERROR(WORKDAY(Table14[[#This Row],[50% IFR - AE]],-15), " ") | K17: 2/17/2023 - complete | L17: 1/11/2023 - Complete | X17: Need updated IFR Date, if we're doing the CAD's | Y17: 1/25: emailed Kelwin asking for info
A18: CPQ08 | J18: =IFERROR(WORKDAY(Table14[[#This Row],[50% IFR - AE]],-15), " ") | L18: 1/8/2024-Complete
A19: CPQ11 | B19: BRAZIL | C19: Deerns | D19: Design | E19: Gabriel Pereira | F19: gabriel.pereira@deerns.com | H19: C | I19: X | J19: =IFERROR(WORKDAY(Table14[[#This Row],[50% IFR - AE]],-15), " ") | K19: Complete
A20: CYS17 | B20: Cheyanne | C20: Jacobs | D20: Design | E20: Kristin McCue | F20: Kristin.McCue@jacobs.com | H20: C | J20: =IFERROR(WORKDAY(Table14[[#This Row],[50% IFR - AE]],-15), " ") | M20: Complete | N20: 1/24/2023-complete | O20: complete | P20: complete | X20: IFP from WT | Y20: 2/6/2023: WT indicates a 2/13 delivery date. 2/6/2023: emailed WT requesting IFP update 1/24: recieved updated design fromWT, uploaded 1/20: recieved design from David. Emailed AE the drawing list and uploaded files to AE and S2 1/19: This is a 'WT' site, emailed Davide requesting design update 1/18: sent philip design pkg 4 email 1/13/23: emailed Kristen requesting update
A21: DFW20 | J21: =IFERROR(WORKDAY(Table14[[#This Row],[50% IFR - AE]],-15), " ") | Q21: 3/8/2024-complete
A22: DSM12 | B22: DES MOINES | C22: Burns & McDonnell | D22: Design | E22: Kylie Hornbeck | F22: khornbeck@burnsmcd.com | H22: C | J22: =IFERROR(WORKDAY(Table14[[#This Row],[50% IFR - AE]],-15), " ") | X22: Nick coordinating with AE
A23: DSM14 | B23: DES MOINES | C23: Burns & McDonnell | D23: Design | E23: Kylie Hornbeck | F23: khornbeck@burnsmcd.com | H23: C | J23: =IFERROR(WORKDAY(Table14[[#This Row],[50% IFR - AE]],-15), " ") | X23: Nick coordinating with AE
A24: DSM15 | B24: DES MOINES | C24: Burns & McDonnell | D24: Design | E24: Kylie Hornbeck | F24: khornbeck@burnsmcd.com | H24: C | J24: =IFERROR(WORKDAY(Table14[[#This Row],[50% IFR - AE]],-15), " ") | X24: Need Floorplans & Schedule - Nick to follow up with AE
A25: DSM40 | B25: DES MOINES | C25: Burns & McDonnell | D25: Design | E25: Kylie Hornbeck | F25: khornbeck@burnsmcd.com | H25: C | J25: =IFERROR(WORKDAY(Table14[[#This Row],[50% IFR - AE]],-15), " ") | Q25: 5/8/2024-Complete | X25: Nick coordinating with AE
A26: DSM41 | B26: DES MOINES | C26: Burns & McDonnell | D26: Design | E26: Kylie Hornbeck | F26: khornbeck@burnsmcd.com | H26: C | J26: =IFERROR(WORKDAY(Table14[[#This Row],[50% IFR - AE]],-15), " ") | X26: Nick coordinating with AE
A27: EAT04 | B27: WEANATCHEE, WA | C27: ESD | D27: Design | E27: Chad Mendell | F27: cmendell@esdglobal.com | H27: C | J27: =IFERROR(WORKDAY(Table14[[#This Row],[50% IFR - AE]],-15), " ") | K27: Complete | L27: 12/1/2022 - Complete | M27: Complete | N27: 1/12/2023 - Complete | O27: 1/19/23-complete | P27: 1/26/2023-complete | Q27: 5/31/2023-Complete | Y27: 2/6/23: IFC is TBD no update1/25: recieved updated design from Philip, uploaded to AE and S2 1/19: recieved updated design from Philip, uploaded to BIM and S2 1/19: uploaded specs, requested IFP design from Philip 1/18: sent IFP instructions to Notora
A28: EAT05 | B28: WEANATCHEE, WA | C28: ESD | D28: Bid | E28: Chad Mendell | F28: cmendell@esdglobal.com | H28: A | I28: 45033 | J28: =IFERROR(WORKDAY(Table14[[#This Row],[50% IFR - AE]],-15), " ") | K28: 5/3/2023 - complete | L28: 4/20/2023 - complete | M28: 5/19/2023 - complete | N28: 5/25/2023 - complete | O28: complete | P28: 6/13/2023 - complete | Q28: 3/5/2024-Complete | X28: Notora Internal review return 5/1-5/2 | Y28: May
A29: EAT06 | H29: A | J29: =IFERROR(WORKDAY(Table14[[#This Row],[50% IFR - AE]],-15), " ") | K29: 8/9/2023--Complete | L29: 8/1/2023-Complete | N29: 9/7/2023 - complete | P29: 9/26/2023-Complete
A30: EAT09 | H30: A | I30: 8/16/2023? | J30: =IFERROR(WORKDAY(Table14[[#This Row],[50% IFR - AE]],-15), " ") | N30: 9/7/2023 - complete | P30: 9/26/2023-Complete
A31: EAT12 | B31: WEANATCHEE, WA | C31: ESD | D31: Design | E31: Chad Mendell | F31: cmendell@esdglobal.com | H31: A | J31: =IFERROR(WORKDAY(Table14[[#This Row],[50% IFR - AE]],-15), " ") | K31: 2/20/2023-complete | L31: 2/23/2023-complete | M31: 3/20/2023 - complete | N31: 3/9/2023 - complete | O31: complete | P31: 4/6/2023 - complete | Q31: 3/21/2024 Complete | X31: Change notes in the Public Safety. Cover the L1 containment unless AHJ approves alternate means and methods. Pull box detail | Y31: 2/15: in internal review 2/15: requested update from Notora 2/3/23: floor plan delivered to Notora 2/1: Harold got floorplans today; 1/18: Design is resuming with meeting 1/30
A32: EAT13 | B32: WEANATCHEE, WA | C32: ESD | D32: Design | E32: Chad Mendell | F32: cmendell@esdglobal.com | H32: A | I32: X | J32: =IFERROR(WORKDAY(Table14[[#This Row],[50% IFR - AE]],-15), " ") | K32: 6/14/2023 - complete | L32: 6/15/2023 - complete | M32: 7/18/2023-Complete | N32: 7/20/2023-Complete | O32: 8/1/2023-Complete | P32: 8/2/2023-Complete | Q32: 4/9/2024-complete | Y32: Starting the week of 5/8
A33: EAT14 | B33: WEANATCHEE, WA | H33: A | I33: X | J33: =IFERROR(WORKDAY(Table14[[#This Row],[50% IFR - AE]],-15), " ") | K33: 9/27/2023 - complete | L33: 9/21/2023 - Complete | M33: 10/27/2023-complete | N33: 11/28/2023-Complete | P33: 12/14/2023 - Complete | Q33: 45427 | X33: Battery backups, near far, L1 containement?
A34: FTY01 | J34: =IFERROR(WORKDAY(Table14[[#This Row],[50% IFR - AE]],-15), " ") | Q34: 4/25/2024-Complete
A35: FTY02 | B35: GEORGIA | C35: Morrison Hershfield | D35: Bid | E35: Lee Percy | F35: LPercy@morrisonhershfield.com | J35: =IFERROR(WORKDAY(Table14[[#This Row],[50% IFR - AE]],-15), " ") -> 45139 | K35: 8/15/2023-Complete | L35: 45160 | M35: 9/8/2023 - complete | N35: 9/12/2023 - complete | O35: 10/10/2023 - Complete | P35: 10/12/2023- Complete | X35: Need to update the BOM to comba unit.
A36: FTY03 | J36: =IFERROR(WORKDAY(Table14[[#This Row],[50% IFR - AE]],-15), " ") | L36: 5/9/2024-Complete | N36: 45446 | P36: 45474
A37: IAD05 | J37: =IFERROR(WORKDAY(Table14[[#This Row],[50% IFR - AE]],-15), " ") | Q37: TBD
A38: IAD12 | B38: LEESBURG, VA | C38: Syska | D38: Design | E38: Liam Wall | F38: lwall@syska.com | H38: A | J38: =IFERROR(WORKDAY(Table14[[#This Row],[50% IFR - AE]],-15), " ") | K38: Complete | L38: 2/22/2023 - Complete | N38: 3/29/2023 - Complete | P38: 45042 | Q38: 45076
A39: IAD13 | B39: LEESBURG, VA | C39: Syska | D39: Design | E39: Liam Wall | F39: lwall@syska.com | H39: A | J39: =IFERROR(WORKDAY(Table14[[#This Row],[50% IFR - AE]],-15), " ") | K39: Complete | L39: Complete | M39: Complete | N39: 2/9/2023 - Complete | O39: Complete | P39: 3/24/2023 - Complete | Q39: 45050 | X39: Riser Info - no IFR yet
A40: IAD14 | B40: LEESBURG, VA | D40: Bid | E40: TBD | H40: A | J40: =IFERROR(WORKDAY(Table14[[#This Row],[50% IFR - AE]],-15), " ")
A41: LVL06 | B41: Drawing Review | D41: Design | E41: Fran Carlos | F41: fclaros@swansonrink.com | H41: A | I41: 44987 | J41: =IFERROR(WORKDAY(Table14[[#This Row],[50% IFR - AE]],-15), " ") | K41: 3/17/2023 - complete | L41: 3/21/2023 - complete | N41: 45041 | O41: 44931 | P41: 44931 | X41: 4/26/2023: Need to adjust to keep equipement in cells 1-3. See email. | Y41: Meet with Preston - make sure he updated prints with S2A changes
A42: LVL07 | H42: A | J42: =IFERROR(WORKDAY(Table14[[#This Row],[50% IFR - AE]],-15), " ") | K42: Complete | L42: 8/21/2023-Complete | M42: No Notora | N42: 9/29/2023--Complete | O42: No Notora | P42: 10/19/2023-Complete | Q42: 2/19/2024-Complete
A43: LVL11 | B43: BOYDTON, VA | C43: Swanson Rink | D43: Design | E43: Ryan Sims | F43: RSims@swansonrink.com | H43: C | J43: =IFERROR(WORKDAY(Table14[[#This Row],[50% IFR - AE]],-15), " ") | K43: Complete | L43: 1/23/2023 - Complete | M43: 2/20/2023 - Complete | N43: 2/27/2023 - Complete | P43: 45007 | Q43: 45061 | Y43: 2/1: Emailed James for desgin review & emailed Preson for titleblock, etc
A44: LVL12 | I44: X | J44: =IFERROR(WORKDAY(Table14[[#This Row],[50% IFR - AE]],-15), " ") | L44: 12/21/2023-Complete | M44: =IFERROR(WORKDAY(Table14[[#This Row],[100% IFR - AE]],-5), " ") | N44: 2/5/2024-Complete | P44: 45345 | X44: Need to provision for off-air as a backup if needed. Need antenna structure to support it.
A45: LVL13-14 | J45: =IFERROR(WORKDAY(Table14[[#This Row],[50% IFR - AE]],-15), " ") -> 45376 | K45: 3/28/2024-Complete | L45: 45397 | M45: 45425 | N45: 45426 | P45: 45453 | V45: Loop clark into dicusscion. We will go back to LVL08
A46: LYH03 | B46: BOYDTON, VA | C46: Highland Associates | D46: BID | E46: Hector Hernandez | F46: hhernandez@ha-ny.com | H46: C | J46: =IFERROR(WORKDAY(Table14[[#This Row],[50% IFR - AE]],-15), " ") | X46: Need Floorplans & Schedule
A47: LYH10 | B47: BOYDTON, VA | C47: Highland Associates | D47: Design | E47: Hector Hernandez | F47: hhernandez@ha-ny.com | G47: Bram Wathen | H47: P | J47: =IFERROR(WORKDAY(Table14[[#This Row],[50% IFR - AE]],-15), " ") | K47: Complete | L47: 11/29/2022 - Complete | M47: Complete | N47: complete | O47: Complete | P47: 45001 | Q47: 6/28/2023 - complete | X47: IFC Pushed to mid july--Will follow up later 04/28/2023 | Y47: 4/18 Specs updated and sent to Paul Duffy for upload. Need to upload to BIM360
A48: MNZ01 | B48: MANASSAS, VA | C48: Sysksa | D48: Design | E48: Christopher Lay | F48: clay@syska.com | H48: A | I48: X | J48: =IFERROR(WORKDAY(Table14[[#This Row],[50% IFR - AE]],-15), " ") | Y48: 1/26: emailed Chris asking for info
A49: MNZ03 | B49: MANASSAS, VA | C49: Sysksa | D49: Design | E49: Christopher Lay | F49: clay@syska.com | H49: A | J49: =IFERROR(WORKDAY(Table14[[#This Row],[50% IFR - AE]],-15), " ") | P49: 3/3/2023 - Complete | Q49: Mid June
A50: MNZ04 | J50: =IFERROR(WORKDAY(Table14[[#This Row],[50% IFR - AE]],-15), " ") | L50: 4/23/2024-Complete | N50: 45456 | P50: 45476
A51: MNZ05 | J51: =IFERROR(WORKDAY(Table14[[#This Row],[50% IFR - AE]],-15), " ") -> 45414 | L51: 45435 | N51: 45484
A52: MWH08 | B52: Quincy | H52: A | I52: X | J52: =IFERROR(WORKDAY(Table14[[#This Row],[50% IFR - AE]],-15), " ") | L52: 1/19/2024-Complete | M52: =IFERROR(WORKDAY(Table14[[#This Row],[100% IFR - AE]],-5), " ") | N52: 3/24/2024-complete
A53: PHX14 | J53: =IFERROR(WORKDAY(Table14[[#This Row],[50% IFR - AE]],-15), " ")
A54: PHX16 | B54: PHOENIX, AZ | I54: X | J54: =IFERROR(WORKDAY(Table14[[#This Row],[50% IFR - AE]],-15), " ")
A55: PHX17 | B55: PHOENIX, AZ | I55: X | J55: =IFERROR(WORKDAY(Table14[[#This Row],[50% IFR - AE]],-15), " ")
A56: PHX15 | B56: PHOENIX, AZ | I56: X | J56: =IFERROR(WORKDAY(Table14[[#This Row],[50% IFR - AE]],-15), " ") -> 45440 | K56: Rough Date | L56: 45461
A57: PHX61 | J57: =IFERROR(WORKDAY(Table14[[#This Row],[50% IFR - AE]],-15), " ") | K57: 11/9/2023-Complete | N57: 11/16/2023-Complete
A58: PHX71 | B58: PHOENIX, AZ | C58: Jacobs | D58: Design | E58: Blake Giles | F58: Blake.Giles@jacobs.com | H58: C | I58: X | J58: =IFERROR(WORKDAY(Table14[[#This Row],[50% IFR - AE]],-15), " ") | X58: Repackaging Site
A59: PHX72 | B59: PHOENIX, AZ | C59: Jacobs | D59: Design | E59: Blake Giles | F59: Blake.Giles@jacobs.com | H59: A | J59: =IFERROR(WORKDAY(Table14[[#This Row],[50% IFR - AE]],-15), " ") -> 44985 | K59: Complete | L59: 45006 | P59: 45089 | X59: QA Form, SPEC, Review A/E Sumittal | Y59: IFP Pushed back to 5/23
A60: PHX73 | B60: PHOENIX, AZ | J60: =IFERROR(WORKDAY(Table14[[#This Row],[50% IFR - AE]],-15), " ") -> 45141 | K60: 8/11/2023 - complete | L60: 45162 | M60: No Notora | N60: 45190 | O60: No Notora | P60: 10/17/2023-Complete
A61: PHX74 | B61: PHOENIX, AZ | H61: A | I61: X | J61: =IFERROR(WORKDAY(Table14[[#This Row],[50% IFR - AE]],-15), " ") | K61: 10/20/2023-Complete | L61: 11/9/2023-Complete | M61: SPEC Needed | N61: 45268 | O61: No Notora | P61: 45301
A62: PHX81 | B62: PHOENIX, AZ | C62: Jacobs | D62: Design | E62: Blake Giles | F62: Blake.Giles@jacobs.com | H62: C | J62: =IFERROR(WORKDAY(Table14[[#This Row],[50% IFR - AE]],-15), " ") | K62: Complete | L62: 11/10/2022 - Complete | M62: Complete | N62: 12/9/2022 - Complete | O62: 1/25/2023-complete | P62: 1/30/2023-complete | Q62: 3/11/2024-Complete | V62: No Notora | X62: Notora Needs IFC Date | Y62: 1/26: recieved package from WT, uploaded. 1/20: emailed David at WT requesting package 1/19: specs sent to PM
A63: PHX82 | B63: PHOENIX, AZ | D63: Design | G63: Bram Wathen | H63: A | J63: =IFERROR(WORKDAY(Table14[[#This Row],[50% IFR - AE]],-15), " ") -> 45022 | L63: 45043 | M63: 45079 | N63: 45083 | P63: 45106 | X63: 4/18 Harold to Review Design. SPECS due June 1 | Y63: We need to review 50% set
A64: PHX83 | B64: PHOENIX, AZ | J64: =IFERROR(WORKDAY(Table14[[#This Row],[50% IFR - AE]],-15), " ")
A65: SAT14 | J65: =IFERROR(WORKDAY(Table14[[#This Row],[50% IFR - AE]],-15), " ") | Q65: 45428
A66: SAT15 | B66: SAN ANTONIO, TX | C66: Page Southerland Page Inc. | D66: Design | E66: Lauren Alexander | F66: lalexander@pagethink.com | H66: A | I66: X | J66: =IFERROR(WORKDAY(Table14[[#This Row],[50% IFR - AE]],-15), " ") | K66: Complete | L66: Complete | M66: Complete | N66: 12/14/2022 - Complete | O66: No NT | P66: 45428 | Q66: 45019 | X66: IFC date determined after permitting
A67: SAT17 | I67: X | J67: =IFERROR(WORKDAY(Table14[[#This Row],[50% IFR - AE]],-15), " ") | L67: 3/27/2024-Complete | M67: =IFERROR(WORKDAY(Table14[[#This Row],[100% IFR - AE]],-5), " ") | N67: 5/9/2024-Complete | P67: 45449
A68: SAT16 | I68: X | J68: =IFERROR(WORKDAY(Table14[[#This Row],[50% IFR - AE]],-15), " ") | K68: 10/26/2023 - complete | L68: 11/29/2023-Complete | N68: 1/9/2024-Complete | P68: 2/15/2024-Complete
A69: SAT40 | B69: SAN ANTONIO, TX | C69: Page Southerland Page Inc. | D69: Design | E69: Lauren Alexander | F69: lalexander@pagethink.com | H69: A | J69: =IFERROR(WORKDAY(Table14[[#This Row],[50% IFR - AE]],-15), " ") | K69: Complete | L69: 11/30/2022 - Complete | M69: Complete | N69: 1/20/2023 - Complete | O69: 2/15/2023 - Complete | P69: 44960 | Q69: 8/2/2023--Complete | X69: Notora Needs Updated IFP Titleblock
A70: SAT80/81 | B70: SAN ANTONIO, TX | C70: Page Southerland Page Inc. | D70: Design | E70: Alan McClung | F70: amcclung@pagethink.com | H70: A | J70: =IFERROR(WORKDAY(Table14[[#This Row],[50% IFR - AE]],-15), " ") | K70: Complete | L70: Complete | M70: Complete | N70: 7/11/2023--Complete | X70: Notora Needs Floorplans & IFC Dates
A71: SAT82 | I71: X | J71: =IFERROR(WORKDAY(Table14[[#This Row],[50% IFR - AE]],-15), " ") | K71: 10/31/2023 - complete | L71: 12/4/2023-Complete | N71: 1/16/2024-Complete | P71: 2/6/2024-Complete | Q71: 44980
A72: SAT90 | I72: X | J72: =IFERROR(WORKDAY(Table14[[#This Row],[50% IFR - AE]],-15), " ") | P72: 2/15/2024-Complete
A73: SAT89 | B73: SAN ANTONIO, TX | H73: A | I73: X | J73: =IFERROR(WORKDAY(Table14[[#This Row],[50% IFR - AE]],-15), " ") | K73: 10/25/2023 - complete | L73: 11/15/2023-Complete | M73: Stephen To deliver | N73: 1/4/2024-Complete | P73: 2/15/2024-Complete
A74: SJC02 | B74: SAN JOSE, CA | C74: Jacobs | D74: Design | E74: Kristin McCue | F74: Kristin.McCue@jacobs.com | H74: A | J74: =IFERROR(WORKDAY(Table14[[#This Row],[50% IFR - AE]],-15), " ") | K74: Complete | L74: Complete | M74: 9/8/2023 - complete | N74: 9/14/2023 - complete | O74: 10/20/2023-Complete | P74: 45458 | Y74: Project is on hold while "they" are working through the IFP comments
A75: SJC04 | B75: SAN JOSE, CA | C75: Jacobs | D75: Bid | E75: Kristin McCue | F75: Kristin.McCue@jacobs.com | H75: P | J75: =IFERROR(WORKDAY(Table14[[#This Row],[50% IFR - AE]],-15), " ") -> 45470 | L75: 45491 | N75: 45547
A76: YQB01/02 | B76: QUEBEC CITY | G76: Bram Wathen | H76: A | I76: X | J76: =IFERROR(WORKDAY(Table14[[#This Row],[50% IFR - AE]],-15), " ") | N76: 7/11/2023-Complete | O76: 8/7/2023 - Complete | P76: 10/4/2023 - complete | Q76: 2/27/2024-complete
A77: YQB04 | B77: QUEBEC CITY | G77: Bram Wathen | H77: A | I77: X | J77: =IFERROR(WORKDAY(Table14[[#This Row],[50% IFR - AE]],-15), " ") | K77: 3/3/2023 - complete | L77: 3/3/2023 - complete | M77: 3/16/2023- complete | N77: 3/20/2023 - complete | O77: 6/9/2023 - complete | P77: 6/15/2023 - complete | Q77: 11/15/2023-complete
A78: YQB06 | B78: QUEBEC CITY | H78: A | I78: X | J78: =IFERROR(WORKDAY(Table14[[#This Row],[50% IFR - AE]],-15), " ") | K78: 5/1/2023 - complete | L78: 4/24/2023 - complete | M78: 6/22/2023--Complete | N78: 6/27/2023--Complete | O78: No Notora | P78: 9/25/2023 - Complete | Q78: 2/2/2024-Complete | X78: Site Plans email sent.
A79: YQB11 | B79: QUEBEC CITY | H79: A | I79: X | J79: =IFERROR(WORKDAY(Table14[[#This Row],[50% IFR - AE]],-15), " ") | K79: 5/8/2023 - complete | L79: 5/12/2023 - complete | M79: 7/1/2023 - complete | N79: 7/25/2023--Complete | O79: 45198 | P79: 12/12/2023-Complete | Q79: 4/9/2024-Complete
A80: YTO10 | B80: Toronto | D80: Bid | E80: Saeed Akbari | F80: SAkbari@morrisonhershfield.com | H80: A | J80: =IFERROR(WORKDAY(Table14[[#This Row],[50% IFR - AE]],-15), " ")
A81: YTO11 | B81: Toronto | C81: Morrison Hershfield | D81: Design | E81: Saeed Akbari | F81: SAkbari@morrisonhershfield.com | H81: A | I81: X | J81: =IFERROR(WORKDAY(Table14[[#This Row],[50% IFR - AE]],-15), " ") | K81: Complete | L81: 9/26/2022 - Complete | M81: Complete | N81: 2/3/2023 - Complete | O81: Complete | P81: 8/8/2023 - Complete | Q81: 45338 | V81: Need to update note & Site plan | X81: Just the Drawings-Update Dates (7-10) | Y81: We will not be submitting a 50% design (or 100% draft as they call it); once we get comments back from Microsoft on YTO40, then they will have us make the same changes to YTO11 and then we will submit YTO11
A82: YTO14 | B82: Toronto | C82: Morrison Hershfield | D82: Design | E82: Saeed Akbari | F82: SAkbari@morrisonhershfield.com | G82: Bram Wathen | H82: A | I82: X | J82: =IFERROR(WORKDAY(Table14[[#This Row],[50% IFR - AE]],-15), " ") | K82: 5/3/2023 - complete | L82: 8/26/2023- Complete | M82: 6/13/2023 - complete | N82: tbd | Q82: TBD | V82: Need to update note & Site plan | X82: Set up meeting w Jim + Harold to discuss the Colo 5 Elec 3 Riser room for fiber. | Y82: Guard house is the same as YTO11 & YTO40. Talk to Mianna for updated plans. 100 % changed to October 16
A83: YTO40 | B83: Toronto | C83: Morrison Hershfield | D83: Design | E83: Saeed Akbari | F83: SAkbari@morrisonhershfield.com | H83: A | I83: X | J83: =IFERROR(WORKDAY(Table14[[#This Row],[50% IFR - AE]],-15), " ") | K83: Complete | L83: Complete | M83: Complete | N83: 1/5/2023 - Complete | O83: 2/14/2023 - Completed | P83: 45435 | Q83: TBD | V83: Need to update antenna note & Site plan | X83: Need IFC Dates | Y83: AE should receive comments back from Microsoft on 1/16 and then we will have 5 days to make changes and issue 100% design
J84: =IFERROR(WORKDAY(Table14[[#This Row],[50% IFR - AE]],-15), " ")
J85: =IFERROR(WORKDAY(Table14[[#This Row],[50% IFR - AE]],-15), " ")
J86: =IFERROR(WORKDAY(Table14[[#This Row],[50% IFR - AE]],-15), " ")
J87: =IFERROR(WORKDAY(Table14[[#This Row],[50% IFR - AE]],-15), " ")
J88: =IFERROR(WORKDAY(Table14[[#This Row],[50% IFR - AE]],-15), " ")
J89: =IFERROR(WORKDAY(Table14[[#This Row],[50% IFR - AE]],-15), " ")
J90: =IFERROR(WORKDAY(Table14[[#This Row],[50% IFR - AE]],-15), " ")
J91: =IFERROR(WORKDAY(Table14[[#This Row],[50% IFR - AE]],-15), " ")
J92: =IFERROR(WORKDAY(Table14[[#This Row],[50% IFR - AE]],-15), " ")
J93: =IFERROR(WORKDAY(Table14[[#This Row],[50% IFR - AE]],-15), " ")
J94: =IFERROR(WORKDAY(Table14[[#This Row],[50% IFR - AE]],-15), " ")
J95: =IFERROR(WORKDAY(Table14[[#This Row],[50% IFR - AE]],-15), " ")
... J134: =IFERROR(WORKDAY(Table14[[#This Row],[50% IFR - AE]],-15), " ")

Sheet Design
A1: NAME | B1: LOCATION | C1: A/E | D1: Phase (Design or CA) | E1: AE-PM Name | F1: AE-PM Contact | G1: S2 PM | H1: Project Status | I1: Floorplans Received | J1: Floor Plans Needed | K1: 50% IFR - Notora | L1: 50% IFR - AE | M1: 100% IFR - Notora | N1: 100% IFR - AE | O1: IFP - Notora | P1: IFP - AE | Q1: IFC | R1: Project Start | S1: Submittal | T1: Substantial Completion | U1: Issue For Record | V1: Completion | W1: Commissioning | X1: Action Item Needed | Y1: Comments
A2: ATL06 | B2: Atlanta | C2: Highland Associates | D2: Design | E2: Christopher Ritchie | F2: critchie@ha-ny.com | H2: C | I2: Supposed to be 4/7/2023 | J2: =IFERROR(WORKDAY(Table1[[#This Row],[50% IFR - AE]],-15), " ") | K2: Complete | M2: No Notora | N2: 10/3/2023- Complete | O2: No Notora | P2: 10/24/2023-Complete | Q2: 2/12/2024-complete | X2: Need to track down: Floor Plans, AHJ (Authorities having jurisdiction contact), enforced code | Y2: Location: East Point GA Lat Long: 33*38'30"N, 84*30'59"W FloorPlans to be updated Friday the 7th
A3: ATL07 | H3: C | J3: 5/13/2024-complete | K3: 5/23/2024-complete | L3: 5/24/2024-complete | Y3: Work completed, assigned to another contractor
A4: AVC01-DRB13 | B4: SOUTH HILL, VA | H4: C | J4: no | M4: 1/3/2025-complete | N4: 4/24/2025-Complete | P4: 1/24/2025-complete | Q4: 1/28/2025-complete
A5: AVC02 | B5: SOUTH HILL, VA | H5: C | J5: =IFERROR(WORKDAY(Table1[[#This Row],[50% IFR - AE]],-15), " ") | L5: 3/25/2024-Complete | N5: 4/29/2024-complete | P5: 5/15/2024-complete | Q5: No S2A - DayWireless | V5: Need as-builts/testing for AVC01. Some weirdness w AVC01 | X5: DAS and Public safety Proposal needed. | Y5: Given to DWS. Highland associates
A6: AVC09-DRB10 | B6: SOUTH HILL, VA | H6: C | J6: no | M6: 12/31/2024-Complete | N6: 4/25/2025- Complete | P6: 1/24/2025-complete | Q6: 1/28/2025-complete
A7: AVC11 | B7: SOUTH HILL, VA | C7: Highland Associates | D7: Design | E7: Paul Duffy (Bim Manager) | F7: pduffy@ha-ny.com | H7: C | J7: 6/26/24-complete | L7: 7/16/2024-Complete | N7: 8/21/2024-Complete | P7: 9/10/2024-complete | Q7: 1/16/2025-completed | X7: Add note to drawings: Carrier coordination must occur at the beginning of the project. As soon as they are awarded contract. | Y7: 8/29: Bram emailed NT: next AVC11 Issuance (IFP) we will need to add a few items. See email thread.
A8: AVC17 | B8: SOUTH HILL, VA | C8: Highland Associates | D8: Design | E8: Hector Hernandez | F8: hhernandez@ha-ny.com | G8: Bram Wathen | H8: C | I8: 2/24/2023 - complete | J8: =IFERROR(WORKDAY(Table1[[#This Row],[50% IFR - AE]],-15), " ") | K8: 3/8/2023 - complete | L8: 3/20/2023- complete | M8: 4/17/2023 - complete | N8: 4/24/2023 - complete | O8: 6/2/2023 - complete | P8: 6/5/2023 - complete | Q8: 8/3/2023-Complete | X8: Update the IFC Date | Y8: 3 Different Issues. Need to confrim if power supply for fiber optical master is required. Need ROIP specs, Site Heat map.
A9: AVC18 | B9: SOUTH HILL, VA | C9: Highland Associates | D9: Design | E9: Hector Hernandez | F9: hhernandez@ha-ny.com | G9: Bram Wathen | H9: C | I9: 3/3/2023 - complete | J9: =IFERROR(WORKDAY(Table1[[#This Row],[50% IFR - AE]],-15), " ") | K9: 3/15/2023 - complete | L9: 3/20/2023 - complete | M9: 4/17/2023 - complete | N9: 4/24/2023 - complete | O9: 6/2/2023 - complete | P9: 6/5/2023 - complete | Q9: 8/3/2023-Complete | X9: Update the IFC Date | Y9: Review Drawings prior to IFP
A10: AVC17/18-DRB | B10: SOUTH HILL, VA | C10: Highland Associates | D10: Design | E10: Hector Hernandez | F10: hhernandez@ha-ny.com | G10: Bram Wathen | H10: A | J10: =IFERROR(WORKDAY(Table1[[#This Row],[50% IFR - AE]],-15), " ") | K10: 11/25/2024-complete | L10: 12/3/2024-complete | N10: 4/17/2025-complete | O10: 12/13/2024-complete | Q10: 12/18/2024-Complete | X10: 5/6: Waiting on Commscope for ROM. Proposal received from Andrews 4/30 Waiting on OneCell BOM pricing - Wesco Note-need benchmark | Y10: 5/6: Waiting on Commscope for ROM. Proposal received from Andrews 4/30 Waiting on OneCell BOM pricing - Wesco Note-need benchmark
A11: AVC19 | B11: SOUTH HILL, VA | C11: Highland Associates | D11: Design | E11: Hector Hernandez | F11: hhernandez@ha-ny.com | G11: Bram Wathen | H11: C | J11: 12/16/24-complete | K11: 1/13/2025-complete | L11: 1/22/2025-complete | M11: 3/11/2025-cancelled | N11: 3/12/2025-cancelled | P11: 3/25/2024-cancelled
A12: AVC20 | B12: SOUTH HILL, VA | C12: Highland Associates | D12: Design | E12: Hector Hernandez | F12: hhernandez@ha-ny.com | G12: Bram Wathen | H12: C | J12: 2/26/25-complete | K12: 3/10/2025-cancelled | L12: 3/12/2025-cancelled
A13: AVC21 | B13: SOUTH HILL, VA | C13: Highland Associates | D13: Design | E13: Hector Hernandez | F13: hhernandez@ha-ny.com | G13: Bram Wathen | H13: C | J13: cancelled | K13: 4/21/2025-cancelled | L13: 4/24/2025-cancelled
A14: AVC43 | B14: SOUTH HILL, VA | C14: Swanson Rink | D14: Design | E14: Ryan Sims | F14: RSims@swansonrink.com | H14: C | I14: 44874 | J14: =IFERROR(WORKDAY(Table1[[#This Row],[50% IFR - AE]],-15), " ") | K14: Complete | L14: 11/21/2022 - Complete | M14: Complete | P14: Complete | X14: 2x2 cabinet
A15: AVC43_DRB07 | B15: SOUTH HILL, VA | C15: Swanson Rink | D15: Design | E15: Ryan Sims | F15: RSims@swansonrink.com | H15: C | J15: no | M15: 12/31/2024-complete | N15: 4/25/2025-Complete | P15: 1/24/2025-complete | Q15: 1/27/2025-complete
A16: BN_Campus | B16: BOYDTON,VA | H16: C | J16: =IFERROR(WORKDAY(Table1[[#This Row],[50% IFR - AE]],-15), " ") | O16: 4/28/2025-complete | P16: 4/4/2025-complete | X16: BW – schedule meeting for Thursday 5/7 KP invoice after delivered.
A17: BN7-8Rev | B17: BOYDTON,VA | H17: C | J17: =IFERROR(WORKDAY(Table1[[#This Row],[50% IFR - AE]],-15), " ") | O17: 5/1/2025-complete | X17: BW – schedule meeting for Thursday 5/7 KP invoice after delivered.
A18: CCO06DRB13 | H18: C | J18: =IFERROR(WORKDAY(Table1[[#This Row],[50% IFR - AE]],-15), " ") | M18: 5/1/2025-completed | N18: 5/6/2025-Completed | Q18: 5/8/2025-complete
A19: CCO07 | B19: PALMETTO, GA | H19: C | J19: =IFERROR(WORKDAY(Table1[[#This Row],[50% IFR - AE]],-15), " ") | K19: 8/23/2023 - complete | L19: 9/7/2023 - complete | M19: No Notora | N19: 10/19/2023-Complete | O19: No Notora | P19: 11/7/2023-Complete
A20: CCO07DCN07 | B20: PALMETTO, GA | F20: Steve.Baum@jacob.com | H20: C | J20: =IFERROR(WORKDAY(Table1[[#This Row],[50% IFR - AE]],-15), " ") | O20: 5/23/2025-complete | P20: 5/23/2025-Complete | Q20: 6/6/25-complete
A21: CCO08 | B21: PALMETTO, GA | C21: Jacobs | D21: Design | E21: Michael Mcloone | F21: Michael.Mcloone@jacobs.com | H21: C | I21: 7/10/2024-Complete | J21: 7/10/2024-Complete | K21: 7/19/2024-Complete | L21: 7/29/2024-Complete | M21: 8/23/24-complete | N21: 9/3/2024-Complete | O21: 9/16/2024-complete | P21: 9/18/2024-complete | Q21: TBD | V21: Launch(Admin&Colo1) & PKG3-6 Fitout. Separate packages | X21: 8/8/24: NT requests 50%s by 8/13 in order to make the 8/22 date for 100%'s. 8/6/24 HS – agree on a standard PSDAS approach – 4 or 3 antennas per COLO, 1 or 2 FBDAs per DC - no opinion from S2A side other than we want a uniform approach across all our projects. Verify Centerline calculated, not guessed at, the potential of near far. One option to calculate: Steps to Calculate Determine the Power Levels: Measure the power levels of the signals from both the near and far transmitters (radios). Calculate Path Loss: Use the path loss formula to determine how much the signal strength decreases over distance. The path loss ( L ) can be calculated using: L=10⋅n⋅log10​(d)+C where ( n ) is the path loss exponent, ( d ) is the distance, and ( C ) is a constant. Evaluate Interference: Assess the interference caused by the stronger signal on the weaker one. This can be done using the Signal-to-Interference Ratio (SIR): SIR= ​Pfar​​/ Pnear , where ( P_{\text{far}} ) is the power of the far signal and ( P_{\text{near}} ) is the power of the near signal.
A22: CCO08DCN | B22: PALMETTO, GA | H22: A | J22: =IFERROR(WORKDAY(Table1[[#This Row],[50% IFR - AE]],-15), " ") | K22: 5/12/2025-complete | O22: 7/17/25-complete | P22: 8/5/2025-complete | X22: 7/28: IFP due date changed to 8/5 per email from BW. 7/21: Draft IFP delivered to A/E, final due 8/11.
A23: CHI05 | B23: Chicago | H23: C | I23: 5/19/2023 - complete | J23: =IFERROR(WORKDAY(Table1[[#This Row],[50% IFR - AE]],-15), " ") | K23: 5/26/2023 - complete | Q23: 4/2/2024-complete | U23: No Notora | Y23: We need NT proposal
A24: CHI11 | B24: Chicago | H24: C | I24: X | J24: =IFERROR(WORKDAY(Table1[[#This Row],[50% IFR - AE]],-15), " ") | K24: 5/26/2023 - complete | P24: 3/11/2024-Complete | Y24: We need NT proposal
A25: CHI22 | B25: Chicago | H25: C | J25: =IFERROR(WORKDAY(Table1[[#This Row],[50% IFR - AE]],-15), " ") | P25: 1/11/2024-COMPLETE | Q25: 1/19/2024-complete | Y25: IFP DRB17 Print
A26: CLT04 | B26: North Carolina | C26: Olson | D26: Design | E26: David Barber | F26: dbarber@olsson.com | G26: Bram Wathen | H26: C | I26: 1/31/2023 - complete | J26: =IFERROR(WORKDAY(Table1[[#This Row],[50% IFR - AE]],-15), " ") | K26: 2/16/2023 - complete | L26: 2/16/2023 - complete | M26: 4/12/2023 -complete | N26: 4/26/2023 - complete | O26: 2/20/2024-Complete | P26: 2/21/2024-Complete | Q26: 1/3/2025-complete | X26: Title block updates. Request sent to Stephen 5/11 | Y26: Get address and find cell towers
A27: CLT05 | B27: North Carolina | H27: C | J27: 1/8/25-complete | K27: 1/17/2025-completed | L27: 1/21/2025-Complete | M27: 2/10/2025-complete | N27: 2/13/2025-Complete | Y27: 9/17/24: Unclear if S2A got contract or not.
A28: CLT10 | B28: North Carolina | C28: Olsson | D28: Design | E28: Meg Plank | F28: mplank@olsson.com | H28: C | I28: X | J28: =IFERROR(WORKDAY(Table1[[#This Row],[50% IFR - AE]],-15), " ") | K28: 6/30/2023 - Complete | L28: 7/06/2023 - Complete | M28: 8/25/2023 - complete | N28: 8/31/2023-Complete | O28: 2/20/2024-Complete | P28: 2/21/2024-Complete | Q28: 1/3/2025-complete | X28: Site Plans & Floor Plans | Y28: Project Kick off June 1st.
A29: CLT11 | B29: North Carolina | H29: C | J29: 1/23/25-complete | K29: 2/3/2025-complete | L29: 2/4/2025-Complete | M29: 3/14/2025-cancelled | N29: 3/18/2025-cancelled | P29: 4/8/2025-cancelled
A30: CLT17 | B30: North Carolina | C30: Olson | D30: Design | E30: David Barber | F30: dbarber@olsson.com | G30: Bram Wathen | H30: C | I30: X | J30: =IFERROR(WORKDAY(Table1[[#This Row],[50% IFR - AE]],-15), " ") | K30: 11/10/2023 - complete | L30: 11/16/2023-complete | M30: 12/20/2023 - complete | N30: 1/3/2024-Complete | P30: 2/14/2024-Complete | Q30: 1/3/2025-complete | Y30: Not doing the CADs for this one
A31: CLT18 | B31: North Carolina | H31: C | J31: 2/17/25-completed | K31: 2/25/2025-completed | L31: 2/27/2025-complete | M31: 4/11/2025-cancelled | N31: 4/15/2025-cancelled | P31: 5/6/2025-cancelled
A32: CPQ03 | B32: BRAZIL | C32: Deerns | D32: Design | E32: Gabriel Pereira | F32: gabriel.pereira@deerns.com | H32: C | J32: =IFERROR(WORKDAY(Table1[[#This Row],[50% IFR - AE]],-15), " ") | Q32: 10/16/2023-complete
A33: CPQ04 | B33: BRAZIL | H33: C | J33: 9/13/2024-complete | K33: 9/19/24-complete | L33: 9/24/2024-complete | M33: 10/7/2024-complete | N33: 10/14/2024-complete | Y33: 8/29/24: added to list. project coming up.
A34: CPQ07 | B34: BRAZIL | C34: Deerns | D34: Design | E34: Gabriel Pereira | F34: gabriel.pereira@deerns.com | H34: C | I34: X | J34: =IFERROR(WORKDAY(Table1[[#This Row],[50% IFR - AE]],-15), " ") | K34: 2/17/2023 - complete | L34: 1/11/2023 - Complete | X34: Need updated IFR Date, if we're doing the CAD's | Y34: 1/25: emailed Kelwin asking for info
A35: CPQ08 | B35: BRAZIL | H35: C | J35: =IFERROR(WORKDAY(Table1[[#This Row],[50% IFR - AE]],-15), " ") | L35: 1/8/2024-Complete
A36: CPQ11 | B36: BRAZIL | C36: Deerns | D36: Design | E36: Gabriel Pereira | F36: gabriel.pereira@deerns.com | H36: C | I36: X | J36: =IFERROR(WORKDAY(Table1[[#This Row],[50% IFR - AE]],-15), " ") | K36: Complete
A37: CYS13 | B37: Cheyanne | H37: C | J37: =IFERROR(WORKDAY(Table1[[#This Row],[50% IFR - AE]],-15), " ") | U37: 9/10/2024-completed | X37: 7/29/24: Bram follow up with Kristin McCue for details/confirmed schedule | Y37: 7/17/24: CYS13 Record Drawings (Admin and COLOs 1 through 5) to close out the project. The latest federated model is available in Navisworks and all disciplines should have final approved redlines (with the exception of Mechanical, where we are tracking down some last info). Please begin working on Record Drawings with the idea to submit as early as possible in August (date TBC once we receive final Mech info). The client has asked us to submit these as soon as possible, so we’re being asked to advance what we can.
A38: CYS17 | B38: Cheyanne | C38: Jacobs | D38: Design | E38: Kristin McCue | F38: Kristin.McCue@jacobs.com | H38: A | J38: =IFERROR(WORKDAY(Table1[[#This Row],[50% IFR - AE]],-15), " ") | M38: Complete | N38: 1/24/2023-complete | O38: complete | P38: complete | U38: 7/11/2025-complete | X38: 6/10/25: Redlines expected end of June(?) | Y38: 2/6/2023: WT indicates a 2/13 delivery date. 2/6/2023: emailed WT requesting IFP update 1/24: recieved updated design fromWT, uploaded 1/20: recieved design from David. Emailed AE the drawing list and uploaded files to AE and S2 1/19: This is a 'WT' site, emailed Davide requesting design update 1/18: sent philip design pkg 4 email 1/13/23: emailed Kristen requesting update
A39: DFW20 | B39: Irving, TX | H39: C | J39: =IFERROR(WORKDAY(Table1[[#This Row],[50% IFR - AE]],-15), " ") | Q39: 3/8/2024-complete
A40: DSM12 | B40: DES MOINES | C40: Burns & McDonnell | D40: Design | E40: Kylie Hornbeck | F40: khornbeck@burnsmcd.com | H40: C | J40: =IFERROR(WORKDAY(Table1[[#This Row],[50% IFR - AE]],-15), " ") | X40: Nick coordinating with AE
A41: DSM14 | B41: DES MOINES | C41: Burns & McDonnell | D41: Design | E41: Kylie Hornbeck | F41: khornbeck@burnsmcd.com | H41: C | J41: =IFERROR(WORKDAY(Table1[[#This Row],[50% IFR - AE]],-15), " ") | X41: Nick coordinating with AE
A42: DSM15 | B42: DES MOINES | C42: Burns & McDonnell | D42: Design | E42: Kylie Hornbeck | F42: khornbeck@burnsmcd.com | H42: C | J42: =IFERROR(WORKDAY(Table1[[#This Row],[50% IFR - AE]],-15), " ") | X42: Need Floorplans & Schedule - Nick to follow up with AE
A43: DSM40 | B43: DES MOINES | C43: Burns & McDonnell | D43: Design | E43: Kylie Hornbeck | F43: khornbeck@burnsmcd.com | H43: C | J43: =IFERROR(WORKDAY(Table1[[#This Row],[50% IFR - AE]],-15), " ") | Q43: 5/8/2024-Complete | U43: 9/4/2024-Complete | X43: Nick coordinating with AE
A44: DSM41 | B44: DES MOINES | C44: Burns & McDonnell | D44: Design | E44: Kylie Hornbeck | F44: khornbeck@burnsmcd.com | H44: C | J44: =IFERROR(WORKDAY(Table1[[#This Row],[50% IFR - AE]],-15), " ") | X44: Nick coordinating with AE
A45: DSM44 | B45: DES MOINES | C45: Burns & McDonnell | D45: Design | E45: Andrew Kalaani | F45: akalaani@burnsmcd.com | H45: A | J45: =IFERROR(WORKDAY(Table1[[#This Row],[50% IFR - AE]],-15), " ") | K45: N/A | L45: N/A | M45: No NT | N45: 9/18/2024-Complete | O45: No NT | P45: 10/7/2024-Complete | X45: 8/5/24: HS – we will want to look at the campus layout as part of the evaluation. | Y45: No Notora. S2A engaged to review designs.
A46: EAT04 | B46: WENATCHEE, WA | C46: ESD | D46: Design | E46: Chad Mendell | F46: cmendell@esdglobal.com | H46: C | J46: =IFERROR(WORKDAY(Table1[[#This Row],[50% IFR - AE]],-15), " ") | K46: Complete | L46: 12/1/2022 - Complete | M46: Complete | N46: 1/12/2023 - Complete | O46: 1/19/23-complete | P46: 1/26/2023-complete | Q46: 5/31/2023-Complete | Y46: 2/6/23: IFC is TBD no update1/25: recieved updated design from Philip, uploaded to AE and S2 1/19: recieved updated design from Philip, uploaded to BIM and S2 1/19: uploaded specs, requested IFP design from Philip 1/18: sent IFP instructions to Notora
A47: EAT05 | B47: WENATCHEE, WA | C47: ESD | D47: Bid | E47: Chad Mendell | F47: cmendell@esdglobal.com | H47: C | I47: 4/17/2023 - complete | J47: =IFERROR(WORKDAY(Table1[[#This Row],[50% IFR - AE]],-15), " ") | K47: 5/3/2023 - complete | L47: 4/20/2023 - complete | M47: 5/19/2023 - complete | N47: 5/25/2023 - complete | O47: complete | P47: 6/13/2023 - complete | Q47: 3/5/2024-Complete | X47: Notora Internal review return 5/1-5/2 | Y47: May
A48: EAT06 | B48: WENATCHEE, WA | H48: C | J48: =IFERROR(WORKDAY(Table1[[#This Row],[50% IFR - AE]],-15), " ") | K48: 8/9/2023--Complete | L48: 8/1/2023-Complete | N48: 9/7/2023 - complete | P48: 9/26/2023-Complete | Q48: 9/24/2024-complete
A49: EAT09 | B49: WENATCHEE, WA | H49: C | I49: 8/16/2023 - complete | J49: =IFERROR(WORKDAY(Table1[[#This Row],[50% IFR - AE]],-15), " ") | N49: 9/7/2023 - complete | P49: 9/26/2023-Complete | Q49: 9/24/2024-complete
A50: EAT06-09Revision | B50: WENATCHEE, WA | C50: Stantec | E50: Michael Clements | F50: Michael.Clements@stantec.com | H50: A | I50: 45804 | J50: YES | L50: 8/29/2025?
A51: EAT12 | B51: WENATCHEE, WA | C51: ESD | D51: Design | E51: Chad Mendell | F51: cmendell@esdglobal.com | H51: C | J51: =IFERROR(WORKDAY(Table1[[#This Row],[50% IFR - AE]],-15), " ") | K51: 2/20/2023-complete | L51: 2/23/2023-complete | M51: 3/20/2023 - complete | N51: 3/9/2023 - complete | O51: complete | P51: 4/6/2023 - complete | Q51: 3/21/2024 Complete | X51: Change notes in the Public Safety. Cover the L1 containment unless AHJ approves alternate means and methods. Pull box detail | Y51: 2/15: in internal review 2/15: requested update from Notora 2/3/23: floor plan delivered to Notora 2/1: Harold got floorplans today; 1/18: Design is resuming with meeting 1/30
A52: EAT12Revision | H52: A | J52: =IFERROR(WORKDAY(Table1[[#This Row],[50% IFR - AE]],-15), " ") | X52: Per Call 5/6: Survey scheduled for Friday. Waiting on DW benchmark; waiting on Stantec approval. Covered by CA.
A53: EAT13 | B53: WENATCHEE, WA | C53: ESD | D53: Design | E53: Chad Mendell | F53: cmendell@esdglobal.com | H53: C | I53: X | J53: =IFERROR(WORKDAY(Table1[[#This Row],[50% IFR - AE]],-15), " ") | K53: 6/14/2023 - complete | L53: 6/15/2023 - complete | M53: 7/18/2023-Complete | N53: 7/20/2023-Complete | O53: 8/1/2023-Complete | P53: 8/2/2023-Complete | Q53: 4/9/2024-complete | Y53: Starting the week of 5/8
A54: EAT14 | B54: WENATCHEE, WA | H54: C | I54: X | J54: =IFERROR(WORKDAY(Table1[[#This Row],[50% IFR - AE]],-15), " ") | K54: 9/27/2023 - complete | L54: 9/21/2023 - Complete | M54: 10/27/2023-complete | N54: 11/28/2023-Complete | P54: 12/14/2023 - Complete | Q54: 9/3/2024-Complete | X54: Battery backups, near far, L1 containement?
A55: FTY01 | B55: Douglassville, GA | H55: C | J55: =IFERROR(WORKDAY(Table1[[#This Row],[50% IFR - AE]],-15), " ") | Q55: 4/25/2024-Complete
A56: FTY02 | B56: GEORGIA | C56: Morrison Hershfield | D56: Bid | E56: Lee Percy | F56: LPercy@morrisonhershfield.com | H56: C | J56: =IFERROR(WORKDAY(Table1[[#This Row],[50% IFR - AE]],-15), " ") | K56: 8/15/2023-Complete | L56: 8/22/2023 - complete | M56: 9/8/2023 - complete | N56: 9/12/2023 - complete | O56: 10/10/2023 - Complete | P56: 10/12/2023- Complete | Q56: 5/23/2024-complete | X56: Need to update the BOM to comba unit.
A57: FTY03 | B57: Atlanta, GA | H57: C | J57: =IFERROR(WORKDAY(Table1[[#This Row],[50% IFR - AE]],-15), " ") | L57: 5/9/2024-Complete | N57: 6/6/2024-Complete | P57: 7/1/2024-Complete
A58: FTY04 | B58: Atlanta, GA | H58: C | J58: 7/22/24-complete | K58: 8/5/2024-complete | L58: 8/5/2024-complete | M58: 8/28/2024-Complete | N58: 9/5/2024-Complete | O58: 9/24/2024-complete | P58: 9/27/2024-Complete | X58: 8/5/24: HS – LINX has installed a ONECELL – we need to make sure that the FTY04 design captures fiber requirements. | Y58: 8/23: NT target delivery 8/26.
A59: IAD04DRB | B59: LEESBURG, VA | H59: A | J59: =IFERROR(WORKDAY(Table1[[#This Row],[50% IFR - AE]],-15), " ") | Q59: 6/27/2025-complete
A60: IAD05 | B60: LEESBURG, VA | H60: C | J60: =IFERROR(WORKDAY(Table1[[#This Row],[50% IFR - AE]],-15), " ") | P60: No Notora | Q60: 5/20/2024-complete | X60: Bram requesting CAD contact @ sysksa
A61: IAD11 | B61: LEESBURG, VA | H61: C | J61: =IFERROR(WORKDAY(Table1[[#This Row],[50% IFR - AE]],-15), " ") | N61: 7/8/2025-complete | U61: 10/18/2024-completed | X61: Bram to do AS Builds
A62: IAD12 | B62: LEESBURG, VA | C62: Syska | D62: Design | E62: Liam Wall | F62: lwall@syska.com | H62: C | J62: =IFERROR(WORKDAY(Table1[[#This Row],[50% IFR - AE]],-15), " ") | K62: Complete | L62: 2/22/2023 - Complete | N62: 3/29/2023 - Complete | P62: 4/26/2023-complete | Q62: 5/30/2023-complete
A63: IAD11DRB-DCN08 | B63: LEESBURG, VA | H63: A | J63: complete | L63: 7/2/2025-complete | M63: 7/14/2025-complete | N63: 7/18/2025-complete
A64: IAD12-13Descope | B64: LEESBURG, VA | H64: A | K64: 5/7/2025-complete | O64: 5/23/25-complete | Q64: 5/23/2025-complete
A65: IAD12-13-DCN06 | J65: =IFERROR(WORKDAY(Table1[[#This Row],[50% IFR - AE]],-15), " ")
A66: IAD13 | B66: LEESBURG, VA | C66: Syska | D66: Design | E66: Liam Wall | F66: lwall@syska.com | H66: C | J66: =IFERROR(WORKDAY(Table1[[#This Row],[50% IFR - AE]],-15), " ") | K66: Complete | L66: Complete | M66: Complete | N66: 2/9/2023 - Complete | O66: Complete | P66: 3/24/2023 - Complete | Q66: 5/4/2023-complete | X66: Riser Info - no IFR yet
A67: IAD14 | B67: LEESBURG, VA | D67: Bid | E67: TBD | H67: C | J67: =IFERROR(WORKDAY(Table1[[#This Row],[50% IFR - AE]],-15), " ")
A68: LVL01-07-DRB | B68: BOYDTON, VA | H68: C | J68: =IFERROR(WORKDAY(Table1[[#This Row],[50% IFR - AE]],-15), " ") | M68: 12/31/2024-complete | N68: 1/13/2025-complete | P68: 1/24/2025-complete | Q68: 1/27/2025-complete
A69: LVL05 | B69: BOYDTON, VA | H69: C | J69: =IFERROR(WORKDAY(Table1[[#This Row],[50% IFR - AE]],-15), " ") | U69: 5/14/2025-complete
A70: LVL06 | B70: BOYDTON, VA | D70: Design | E70: Fran Carlos | F70: fclaros@swansonrink.com | H70: C | I70: 3/2/2023 - complete | J70: =IFERROR(WORKDAY(Table1[[#This Row],[50% IFR - AE]],-15), " ") | K70: 3/17/2023 - complete | L70: 3/21/2023 - complete | N70: 4/25/2023 - complete | O70: 1/5/2023 - complete | P70: 1/5/2023 - complete | X70: 4/26/2023: Need to adjust to keep equipement in cells 1-3. See email. | Y70: Meet with Preston - make sure he updated prints with S2A changes
A71: LVL06_EXT | H71: C | J71: =IFERROR(WORKDAY(Table1[[#This Row],[50% IFR - AE]],-15), " ") | N71: 4/25/2025-complte
A72: LVL07 | B72: BOYDTON, VA | H72: C | J72: =IFERROR(WORKDAY(Table1[[#This Row],[50% IFR - AE]],-15), " ") | K72: Complete | L72: 8/21/2023-Complete | M72: No Notora | N72: 9/29/2023--Complete | O72: No Notora | P72: 10/19/2023-Complete | Q72: 2/19/2024-Complete | U72: 7/28/2025-complete
A73: LVL07DRB03 | B73: BOYDTON, VA | H73: A | J73: =IFERROR(WORKDAY(Table1[[#This Row],[50% IFR - AE]],-15), " ")
A74: LVL08-14-DRB | B74: BOYDTON, VA | H74: C | J74: =IFERROR(WORKDAY(Table1[[#This Row],[50% IFR - AE]],-15), " ") | M74: 12/31/2024-complete | N74: 1/13/2025-complete | P74: 1/24/2025-complete | Q74: 1/27/2025-complete | U74: 7/28/25?
A75: LVL09_RecordSets | B75: BOYDTON, VA | H75: A | J75: =IFERROR(WORKDAY(Table1[[#This Row],[50% IFR - AE]],-15), " ") | U75: 7/28/2025-complete | X75: drawing list due 7/15.
A76: LVL11 | B76: BOYDTON, VA | C76: Swanson Rink | D76: Design | E76: Ryan Sims | F76: RSims@swansonrink.com | H76: C | J76: =IFERROR(WORKDAY(Table1[[#This Row],[50% IFR - AE]],-15), " ") | K76: Complete | L76: 1/23/2023 - Complete | M76: 2/20/2023 - Complete | N76: 2/27/2023 - Complete | P76: 3/22/2023-complete | Q76: 5/15/2023-complete | Y76: 2/1: Emailed James for desgin review & emailed Preson for titleblock, etc
A77: LVL12 | B77: BOYDTON, VA | H77: C | I77: X | J77: =IFERROR(WORKDAY(Table1[[#This Row],[50% IFR - AE]],-15), " ") | L77: 12/21/2023-Complete | M77: =IFERROR(WORKDAY(Table1[[#This Row],[100% IFR - AE]],-5), " ") | N77: 2/5/2024-Complete | P77: 2/23/2024-complete | Q77: 6/28/2024-Complete | X77: Need to provision for off-air as a backup if needed. Need antenna structure to support it.
A78: LVL11Rev | B78: BOYDTON, VA | H78: C | L78: 4/16/2025-Complete
A79: LVL12DRB01 | B79: BOYDTON, VA | H79: C | J79: =IFERROR(WORKDAY(Table1[[#This Row],[50% IFR - AE]],-15), " ") | M79: 1/27/2025-complete | N79: 4/15/2025 - Complete | O79: 2/14/2025-complete | P79: 5/6/2025-complete | Q79: 45881
A80: LVL13-14 | B80: BOYDTON, VA | H80: C | J80: =IFERROR(WORKDAY(Table1[[#This Row],[50% IFR - AE]],-15), " ") | K80: 3/28/2024-Complete | L80: 4/15/2024-Complete | M80: 5/13/2024-complete | N80: 5/14/2024-complete | P80: 6/5/2024-Complete | Q80: 9/09/2024-Complete | V80: Loop clark into dicusscion. We will go back to LVL08 | Y80: 12/19/24: per email, 13 & 14 construction are cancelled and 12 will be a stand alone data center.
A81: LYH03 | B81: BOYDTON, VA | C81: Highland Associates | D81: BID | E81: Hector Hernandez | F81: hhernandez@ha-ny.com | H81: C | J81: =IFERROR(WORKDAY(Table1[[#This Row],[50% IFR - AE]],-15), " ") | X81: 7/29/24: S2A not awarded bid. See email from HS.
A82: LYH10 | B82: BOYDTON, VA | C82: Highland Associates | D82: Design | E82: Hector Hernandez | F82: hhernandez@ha-ny.com | G82: Bram Wathen | H82: C | J82: =IFERROR(WORKDAY(Table1[[#This Row],[50% IFR - AE]],-15), " ") | K82: Complete | L82: 11/29/2022 - Complete | M82: Complete | N82: complete | O82: Complete | P82: 3/16/2023-complete | Q82: 10/31/2024-Complete | X82: IFC Pushed to mid july--Will follow up later 04/28/2023 | Y82: 4/18 Specs updated and sent to Paul Duffy for upload. Need to upload to BIM360
A83: LYH10_DRB | H83: C | J83: =IFERROR(WORKDAY(Table1[[#This Row],[50% IFR - AE]],-15), " ") | M83: 4/25/2025-Complete | N83: 4/25/2025-Complete
A84: MNZ01 | B84: MANASSAS, VA | C84: Sysksa | D84: Design | E84: Christopher Lay | F84: clay@syska.com | H84: C | I84: X | J84: =IFERROR(WORKDAY(Table1[[#This Row],[50% IFR - AE]],-15), " ") | Y84: 1/26: emailed Chris asking for info
A85: MNZ03 | B85: MANASSAS, VA | C85: Sysksa | D85: Design | E85: Christopher Lay | F85: clay@syska.com | H85: C | J85: =IFERROR(WORKDAY(Table1[[#This Row],[50% IFR - AE]],-15), " ") | P85: 3/3/2023 - Complete | Q85: mid june-Complete
A86: MNZ03DRB | B86: MANASSAS, VA | H86: A | J86: =IFERROR(WORKDAY(Table1[[#This Row],[50% IFR - AE]],-15), " ") | Q86: 6/6/25-complete
A87: MNZ04 | B87: MANASSAS, VA | C87: Syska | D87: Design | E87: Christopher Lay | F87: clay@syska.com | H87: C | J87: =IFERROR(WORKDAY(Table1[[#This Row],[50% IFR - AE]],-15), " ") | L87: 4/23/2024-Complete | N87: 6/18/2024-Complete | O87: 7/15/2024-complete | P87: 7/16/2024-complete
A88: MNZ05 | B88: MANASSAS, VA | C88: Syska | D88: Design | E88: Christopher Lay | F88: clay@syska.com | H88: C | J88: =IFERROR(WORKDAY(Table1[[#This Row],[50% IFR - AE]],-15), " ") | L88: 5/30/2024-complete | N88: 7/11/2024-Complete
A89: MWH08 | B89: Quincy, WA | H89: C | I89: X | J89: =IFERROR(WORKDAY(Table1[[#This Row],[50% IFR - AE]],-15), " ") | L89: 1/19/2024-Complete | M89: =IFERROR(WORKDAY(Table1[[#This Row],[100% IFR - AE]],-5), " ") | N89: 3/24/2024-complete
A90: PHX12 | B90: PHOENIX, AZ | H90: A | J90: =IFERROR(WORKDAY(Table1[[#This Row],[50% IFR - AE]],-15), " ") | U90: TBD
A91: PHX14 | B91: PHOENIX, AZ | H91: ? | J91: =IFERROR(WORKDAY(Table1[[#This Row],[50% IFR - AE]],-15), " ")
A92: PHX16 | B92: PHOENIX, AZ | H92: ? | I92: X | J92: =IFERROR(WORKDAY(Table1[[#This Row],[50% IFR - AE]],-15), " ")
A93: PHX17 | B93: PHOENIX, AZ | H93: ? | I93: X | J93: =IFERROR(WORKDAY(Table1[[#This Row],[50% IFR - AE]],-15), " ")
A94: PHX15 | B94: PHOENIX, AZ | H94: C | I94: X | K94: Rough Date | L94: 6/19/2024-Complete | M94: 7/25/2024-complete | N94: 7/26/2024-complete | O94: 8/23/2024-complete | P94: 8/28/2024-Complete | Q94: 3/31/2025-completed
A95: PHX61 | B95: PHOENIX, AZ | H95: C | J95: =IFERROR(WORKDAY(Table1[[#This Row],[50% IFR - AE]],-15), " ") | K95: 11/9/2023-Complete | N95: 11/16/2023-Complete
A96: PHX71 | B96: PHOENIX, AZ | C96: Jacobs | D96: Design | E96: Andrea Frazier-Sanchez | F96: Andrea.FrazierSanchez@jacobs.com | H96: A | I96: X | J96: =IFERROR(WORKDAY(Table1[[#This Row],[50% IFR - AE]],-15), " ") | U96: TBD | X96: Repackaging Site
A97: PHX72 | B97: PHOENIX, AZ | C97: Jacobs | D97: Design | E97: Andrea Frazier-Sanchez | F97: Andrea.FrazierSanchez@jacobs.com | H97: C | J97: =IFERROR(WORKDAY(Table1[[#This Row],[50% IFR - AE]],-15), " ") | K97: Complete | L97: 3/21/2023 - complete | P97: 6/12/2023 - complete | Q97: 6/13/2024-complete | X97: QA Form, SPEC, Review A/E Sumittal | Y97: IFP Pushed back to 5/23
A98: PHX72DRB08 | H98: C | J98: 4/28/2025-complete | M98: 5/5/2025 - Complete | N98: 5/2/2025-complete | Q98: 6/9/2025-complete
A99: PHX82DRB11 | H99: C | J99: =IFERROR(WORKDAY(Table1[[#This Row],[50% IFR - AE]],-15), " ") | M99: Complete | N99: 5/2/2025-complete | Q99: 6/9/2025-complete
A100: PHX72-Rescope | H100: A | J100: =IFERROR(WORKDAY(Table1[[#This Row],[50% IFR - AE]],-15), " ")
...

Sheet Site Visit Schedule
A1: Site | B1: Status | C1: S2 Advisors | D1: Date | E1: Test Data Received/Location | F1: Confirmed/Not Confirmed | G1: Notes
A2: ATL06 | B2: Complete | C2: Bram | D2: 45986 | F2: Confirmed
A3: CC006 | B3: Complete | C3: Bram | D3: 45986 | F3: Confirmed
A4: CHI05 | B4: Complete | C4: Harold | D4: Late April | E4: After March 20th | F4: Not Confirmed | G4: 4/13: Katie asked Harold for specific dates 3/17: See the upcoming timeline for CHI05 DAS Commissioning: - March 10th & 11th – Day Wireless will be onsite to repair the current DAS antenna run and fix any open issues with the systems functionality - March 12th & 13th – Day Wireless will be onsite to complete the commissioning of COLO 2-5 DAS system - March 20th – Walsh plans to have all DAS testing and documentation sent into the AE for review and approval CHI05 is turned over and actively operating under MSFT Ops. Following the submission of test reports, your team can review and you are more than welcome to come to site for a final walk (most likely week of March 30th, from our discussion).3/6: Walsh DAS contractor says DAS repairs are happening on the 10th, then CX-ing a couple days after. They expect to get test data to S2A by the 20th. 2/18: We have not heard anything further from the CHI05 Contractor beyond the attached. We understand S2A’s recommendation to hold off on DAS/PS/RoIP Record Drawings at this time. 1/16: AK said there is a Verizon issue. HS asked for submittals and a site visit. 1/5: Waiting to hear back from Andrew Kreb. Back in office today. CHI05 campus turned over on 12/16
A5: YTO11 | B5: Completed | C5: Harold | D5: 46002 | F5: Confirmed | G5: Same visit: CHI05, YTO11 - 8am (7:30am safety meeting) if possible, the preference is to have you take the site safety training which happens at 7:30AM, this will allow you permanent site access and also allow you access to YTO40 in the future, site safety training is approximately 1 hour long. fill out the QR code per the second email when convenient.
A6: YQB04 | B6: Completed | C6: Harold | D6: 46006 | F6: Confirmed | G6: Meet at the site at 8am
A7: AVC43 | B7: Completed | C7: Bram | D7: 46008 | F7: Confirmed | G7: Same visit: IAD05, MNZ03, AVC43
A8: IAD05 | B8: Completed | C8: Bram | D8: 12/15-12/19 | F8: Confirmed | G8: Same visit: IAD05, MNZ03, AVC43
A9: MNZ03 | B9: Completed | C9: Bram | D9: 12/15-12/19 | F9: Confirmed | G9: Same visit: IAD05, MNZ03, AVC43
A10: EAT04 | B10: On Hold | C10: Harold | D10: Week of March 2-6? | F10: Not Confirmed | G10: 2/18: I don’t believe we have been awarded the EAT04 install yet, so this hasn’t been schedule. I’ve forwarded your email on to our account manage who will have better visibility into current status.1/5: No RFIs or submittals. Site not ready, BW to chat with Michael about EAT04 and 12.
A11: EAT12 | B11: Completed | C11: Harold | D11: Week of March 2-6? | F11: Not Confirmed | G11: 2/20: PSDAS Cx in progress - ETA finish: 3/2-3/6 Cell DAS Cx in progress - ETA finish: 3/2-3/6 2/18: Katie reached out to Grant Potter about status of the passive layer testing. punch walk COLO 3 and COLO 4 during the EAT12 punch walk
A12: SAT14 | B12: Not Needed | C12: Harold | D12: Early January | F12: Not Confirmed | G12: 1/5: Katie reached out to David L. and Jerry B.
A13: SAT40 | B13: On Hold | C13: Harold | D13: Early January | F13: Not Confirmed | G13: 2/18: MSFT has not approved the CO. 1/5: Katie reached out to Kevin Shirley "Still waiting for MSFT to provide our dedicated fiber circuit for ISP connection" Kevin will update S2A when ready.
A14: CHI11 | B14: Complete | C14: Harold | D14: Late April | E14: 3/2, CHI11_Test Data (SP folder) | F14: Not Confirmed | G14: 4/13: Katie asked Harold for specific dates 3/17: Ron Swiercz sent full closeout package 3/3: Bram to review test data 2/26: Katie met with DAS contractor. He is sending the test data reports from the subcontractor to S2A. 2/11: Katie sent an email to Sultan Katrangi asking for update. Issues with the functionality of the DAS/Public safety systems at CHI10 which are preventing completion of CHI11 systems.
A15: CCO07 | B15: Not Needed | C15: TBD | D15: Mid-January | F15: Not Confirmed | G15: 1/13: HS response to Steve: Until DAS scopes are fully installed and tested, a site visit would be premature. At this time we are not going to schedule a visit 1/5: Katie reached out to Steve Baum. "The last word I had from S2 Advisors (possibly from Bram) was that no on site view was practical until the system was operational. If we need to have someone on site for a punch walk, we are planning on being on site the week of Jan 19 with Electrical/Mechanical being the first two days, Architectural, Security and LSS the last two days. Either group has room for S2 to join."
A16: YTO11/YTO40 | B16: Complete | C16: Harold | D16: July 23rd YTO11: Time: 8:30AM – Location project trailers YTO40: Time: 12:30PM – Location project trailers | F16: Confirmed | G16: 7/8: Harold will go to YTO11 first and then YTO40 6/26: Harold to complete DCAT form 6/16: Bell has completed installation and is ready for a site visit. Folders will be populated with test data at the end of the week. 6/10: Bell is currently on site and has not completed their scope as of today. ED will confirm with Bell and send us a heads up of when the work will be complete and ready for a site review, could be late June – stay tuned. 4/27: Expected site ready for a visit in early June. In anticipation of your eventual site visit to close out the Bell scope of work please see attached and fill out so we can get you security access into the turned over space. You can see my information filled out as a template, let me know if you have any questions or concerns, thanks.1/19: I’ve been told that the carrier (bell) has not proceeded with any work, and that they have not given any timeline on commencement. 1/5: Peter asked, "is the Bell Installation complete and should S2A be preparing to come out soon"
A17: PHX81 | B17: Rescheduled | C17: Bram | D17: March 23rd, 2026 | F17: Confirmed | G17: 3/3: Brian Gailfus sent pre-site visit instructions 2/18: Katie reached out to Sebastian Arias for DAS test and commissioning data. 1/26: Said this will most likely occur in March during leads meeting. 1/26: HP has pushed PHX82 punch to mid-February. More to come. I still haven’t heard if DAS testing will be complete. Let’s discuss in the leads meeting next Monday. 1/23: Waiting for Brian Gailfus to confirm second week of February. 1/12: Brian Gailfus: HP is asking to finish up PHX81 punch walks for Telecom, DAS/RoIP and Security.
A18: PHX82 | B18: On Hold | C18: Bram | D18: TBD (as of 3/17) | F18: Not Confirmed | G18: 2/20: Jesse B. said: PHX82 is still under construction at this time. Aiming to have Admin/COLO1/COLO2 install finished by mid to late March. 2/18: Visit the same time as PHX81? 1/26: Said this will most likely occur in March during leads meeting. 1/26: HP has pushed PHX82 punch to mid-February. More to come. I still haven’t heard if DAS testing will be complete. Let’s discuss in the leads meeting next Monday. 1/23: Waiting for Brian Gailfus to confirm second week of February. 1/12: Brian Gailfus said in the PHX81/82 leads meeting PHX82 would be ready for a site visit in early Feb
A19: PHX72 | B19: On Hold | C19: Bram | D19: March 25th, 2026 (can reschedule to March 24th) | E19: Receiving test data 3/17 | F19: Confirmed | G19: 3/6: Commissioning and the testing is supposed to be completed by March 16th. If so, that should be enough time to submit and review the needed information. Since zBeta schedules are as full as the rest of us, I recommend that we keep the March 25th date 2/20: Do not yet have test data. Ideally same trip at PHX81 and PHX82
A20: SAT80/81 | B20: On Hold | C20: Harold | D20: Mid June | E20: ProCore Portal | F20: Not Confirmed | G20: 6/10: Jesse replied: we have been on hold due to the VHF donor cable pathway out of the building, its not ready. 6/10: Katie followed up with Jesse B for test reports 4/27: the last time you all had representation on site for an Inspection was on 4/4/25 and at that time, SAT80 Admin & Colo1 were looked at. We have turned over to MS Colo2 and will be turning over Colo3 today. If you all need to get into the “Turned Over” areas then you all need to submit the names of the folks who will be going in the building under a DCAT, an MSOW may need to be submitted as well. Whoever goes in will also need to go through a MS Security Orientation. 4/23: E2 sent test data for SAT80/81 4/22: Katie reached out for GC contract 3/4: S2A needs to hold on a site visit until Mid to late April – that’s when E2Opitics will have completed the PSDAS.
A21: SAT15 | B21: Completed | C21: Harold | D21: 3/30-4/13 | E21: 3/2, SAT15_Test Data (SP folder) | F21: Not Confirmed | G21: 4/8: No longer needed. BW said we can sign off with accurate test results. 3/7: I can probably include COLO 4 as well in this walk, but early April is what we need to shoot for COLO 3. 3/4: Asking for next week
A22: SAT14 | B22: On Hold | C22: Harold | G22: 3/17: Asking for 3/23
A23: SAT14 | B23: Not Needed | C23: TBD | D23: Last week of May | E23: Requested | F23: Not Confirmed | G23: 4/27: Rene Palencia said: I just spoke with our superintendent and we are aiming to be ready for a walk the last week of May. 4/22: Katie reached out to Rene for DAS/ROIP test data report progress
A25: LYH10 / AVC43 / AVC01 / AVC09 | B25: Open | C25: Harold | F25: Not Confirmed | G25: BIR to use change order to look at public safety
A26: SAT40 | B26: Open | C26: Harold | F26: Not Confirmed | G26: 9/8: Katie reached out to KS for update. 6/16: Katie reached out to Kevin Shirley for ISP update
A27: FTY02 | B27: Open | C27: Bram | F27: Not Confirmed
A28: PHX72 | B28: Complete | C28: Harold | D28: July 7th | F28: Confirmed | G28: 6/22: Test report submittals complete
A29: YQB06 | B29: Complete | C29: Harold | D29: August 10th | F29: Confirmed | G29: 7/6: Vincent will also be there if technical questions arise.
A30: CCO07 | B30: On Hold | C30: Harold | F30: Not Confirmed | G30: 7/30: Check if Cx-ing is done
A31: CCO06 | B31: Open | C31: Bram | D31: Week of (or after) Sept 21 | F31: Not Confirmed | G31: 8/26: Currently cx is tracking for completion by 9/14. If these dates change. AHJ would would follow the next week 9/21. 7/14: Installation and Cx-ing should be done 17-21 Aug
A32: ATL06 | B32: On Hold | F32: Not Confirmed | G32: 7/30: Go to again? COLO turn-ups?
A33: IAD12-13 | B33: On Hold | F33: Not Confirmed | G33: 7/30: Check on status
A34: SAT80/81 | B34: Open | F34: Not Confirmed | G34: 9/8: Emailed Jesse Brierly for PSDAS update
A35: MNZ03 | B35: Open | C35: Bram | D35: End of Sept | F35: Not Confirmed

Sheet 2026 Meeting Schedule
B1: Monday | E1: Tuesday | H1: Wednesday | K1: Thursday | N1: Friday
B2: HS | C2: BW | D2: KC | E2: HS | F2: BW | G2: KC | H2: HS | I2: BW | J2: KC | K2: HS | L2: BW | M2: KC | N2: HS | O2: BW | P2: KC
A3: 7AM
A4: 7:30AM
A5: 8AM
A6: 8:30AM
A7: 9AM | D7: QRO01 EXP Mtg
A8: 9:30AM
A9: 10AM | B9: QRO01 Design Meeting | G9: AVC17/18 RFI/SUB Review | H9: Verizon MSFT Weekly Touchpoint | K9: MSFT OneCell Andrew Meeting
A10: 10:30AM
A11: 11AM | B11: SJC02 - RFI MTG | D11: CCO7CA Leads Mtg | M11: YQB04 Weekly Meeting
A12: 11:30AM | K12: S2 Weekly CL Call
A13: 12PM | D13: PHX80 Leads Mtg
A14: 12:30PM
A15: 1PM | D15: CCO08CA Leads Mtg
A16: 1:30PM
A17: 2PM | G17: EAT12 OAC Mtg
A18: 2:30PM | E18: Weekly Touch Base
A19: 3PM
A20: 3:30PM
A21: 4PM
A22: 4:30PM
A23: 5PM

Sheet Delivereable_Tracker
A1: Projects | B1: Priority/Status | C1: Scope | D1: AE Due Date | E1: CL Due Date | F1: S2A/CL Due Date | G1: Status | H1: AE Contract | I1: CL Contract
A2: CPQ11 | B2: 5.Completed | C2: Add in Colo 4 to ibwaves | D2: 45905 | F2: 45908 | G2: 9/25: HS responded that he has issued the deliverables. | H2: 9/25: Contract amendment received. | I2: OpenPO
A3: CCO07 | B3: 5.Completed | C3: Set Up Call with DAS team - submitting permits | D3: Completed | F3: Completed | G3: 7/31: Based on RFI #265 for CCO07 | H3: CA | I3: NA
A4: CCO08 | B4: 5.Completed | C4: Descoped colos 3-5. ERRCS design/BOM | D4: 7/21/2025-complete | F4: 7/16-complete | G4: 7/14: Final IFP 8/11 6/23: Draft IFP due 7/21. CL work needs to be reviewed against MS scope and confirm all is descoped. | H4: NTP | I4: OpenPO
A5: IAD13 | B5: 5.Completed | C5: IFC Issuance | D5: 8/6/25-completed | F5: NA | G5: 7/23: A/E emailed schedule. No CL | H5: CA | I5: NA - Bram to do CAD work
A6: QRO06 | B6: 5.Completed | C6: QRO06 EXP 100% IFR Submittal Print | D6: 8/7/25-completed | F6: NA | G6: 8/7: BW delivered files. | H6: CA | I6: NA - Bram to do CAD work
A7: SAT PROJECTS | B7: 5.Completed | C7: Lessons Learned Logs required for SAT 14, 15, 40, 80/81 Projects | D7: Complete 7/29 | F7: NA | G7: 7/28: BW - note complete. Not planning on taking any action until PM pushes the issue. | H7: NA | I7: NA
A8: LVL12 | B8: 5.Completed | C8: LVL12 DRB01 REV 1 IFC | D8: 8/15/2025-Completed | F8: 8/11/2025-Completed | H8: LVL12-14DS | I8: OpenPO
A9: BOYDTON AREA? | B9: 5.Completed | C9: T-Mobile/At&T contracts | D9: TBD | F9: TBD | G9: Sounds like TMO will be included. Communicate with Andrews for TMO addition.
A10: CCO08 | B10: 5.Completed | C10: PSDAS Updates to reflect City of Palmetto comments - includes CADS | D10: 7/21/2025-complete | F10: Complete | G10: 7/17: A little bit of rework needed. Trey working on it. 7/16: Cads delivered. 7/14: Final IFP 8/11 draft ifp 7/21. CL working on incorporating in comments. 7/10: iBwaves delivered. S2A to review and then give CL OK to proceed with CADS. | H10: NTP | I10: OpenPO
A11: CCO08 | B11: 5.Completed | C11: Final IFP | D11: 8/11/25-completed July | F11: Completed | G11: 7/25: Draft IFP was delivered 8/5 | H11: CCO08DS | I11: NA
A12: IAD12-13CA | B12: 5.Completed | C12: submit anticipated monthly hours for the CA associated with descoping only, September forward. | D12: 45912 | F12: 45912 | G12: 9/24: See email from See email from Chris Kruger about pausing all work on descoping. Chris Kruger 9/10 with spreadsheet link. | H12: CA | I12: NA
A13: CCO08 | B13: 5.Completed | C13: DCN08 IFP Reprint PS Update to remove COLOs 3-5 | D13: 9/29/2025-completed | F13: 9/24/2025-completed | G13: 9/29/2025: CCO08 IFC Complete 9/25: Stephen Wright is submitting this afternoon. 9/22: Stephen Wright working on CAD drawings. 8/26: HS working on budget, same as CCO06. CL will be engaged, waiting on quote. | H13: CCO08DS? (confirm we have enough budget) | I13: OpenPO
A14: LVL12-14 | B14: 5.Completed | C14: 100% IFR (lesson learned from LVL12 and update to IFC 2021)10/14: Update floor plan layout and public safety code update | D14: 45966 | F14: 10/27-Completed | G14: 11/04: Katie to mark status completed once invoice is sent to AE 10/27: S2A received Cline work. 10/24: BW gave Stephen go ahead to start updating the CDs 10/23: CL sent over design for BW to review. Then Stephen will begin work. 10/17: CL will get started on this design revision late next week 10/8: Updated to reflect 75 calendar days for AHJ review. IFC: 3/4/26 – Pending DEQ approval 9/30: HS to review public safety to make sure compliant with Virgina state code 8/25: Proposal discussed 8 hours, no CL, BW to work | H14: LVL12-14DS | I14: OpenPO
A15: PHX72 | B15: 5.Completed | C15: Reverse of descope work done in May | D15: 10/31-Completed | F15: 10/31-Completed | G15: 11/04: Katie to mark status completed once invoice is sent to AE 10/30: BW set clouded drawings and revisions to Jacobs to cont. in Revit. 10/29: 10/29: BW to send clouded sets and mark-ups to Jacobs telecomm by EOD 10/29. 10/28: BW to talk with Carrie 10/29, morning 10/27: HS completed the change tracker for PHX72 and PHX82 full buildout 10/22: Project back to life. CL to do CAD drawings. (CL did original drawings) 10/21:NTP Received 10/14: BW Confirm budget and scope 9/30: Sent proposal end of august, BW follow up with Jacobs 8/28: CL estimate received for CADS only | H15: TBD | I15: NA
A16: LVL07 | B16: 5.Completed | C16: LVL07 RFI 96.3/96.4 - Issue Drawings | D16: 45866 | F16: NA | G16: 7/30: BW completed | H16: CA | I16: NA
A17: LVL08 | B17: 5.Completed | C17: Consolidate LVL09,10,11 into LVL08 Drawings | D17: 45867 | F17: 7/23-complete | G17: 7/30: BW delivered as part of LVL09 Record Set | H17: Bill to LVL10CA | I17: OpenPO
A18: LVL09 | B18: 5.Completed | C18: Record Set | D18: 45867 | F18: Complete | G18: 7/30: BW delivered. A/E confirmed receipt | H18: CA | I18: OpenPO
A19: QRO06 | B19: 5.Completed | C19: Descope-COMM /ROIP Design Revisions/CADS | D19: 7/18/25-complete | F19: Complete | G19: 6/23: Redline drawings sent to S2A; issue record set by 7/22. | H19: CA | I19: N/A
A20: CYS17 | B20: 5.Completed | C20: Issue for Record Set DWG-R1 Record | 7/15/2025 | D20: Complete | F20: Complete | G20: 7/10: CL due date 7/10 confirmed on weekly call. | H20: CA | I20: OpenPO
A21: PHX72 | B21: 5.Completed | C21: PHX72 Descope IFC submission | D21: 7/17/2025-complete | F21: Complete | G21: 7/10: CL delivered files to S2A | H21: CA | I21: OpenPO
A22: IAD11DCN08 | B22: 5.Completed | C22: DRB - New Headend Mod - 100% IFR | D22: 7/18/25-complete | F22: Complete | G22: 7/15: CL delivered files. In S2A court to hand off to A/E | H22: NTP | I22: OpenPO
A23: CCO08 | B23: 5.Completed | C23: IFP Reprint Package for Bidding | D23: 8/14/2025-Completed | F23: 8/14/2025-Completed | G23: 8/14: CL to deliver IFP set. | H23: CCO08DS
A24: CCO08 | B24: 5.Completed | C24: CCO08 Design | PKG06-R1 IFP | 8/7/2025 | D24: 8/5/25-completed | F24: NA | G24: 7/28: Added to list. No CL | H24: CCO08DS | I24: NA
A25: PHX82 | B25: 5.Completed | C25: Reverse of descope work done in May | D25: 45960 | F25: TBD | G25: 11/04: Katie to mark status completed once invoice is sent to AE 10/30: BW set clouded drawings and revisions to Jacobs to cont. in Revit. 10/29: BW to send clouded sets and mark-ups to Jacobs telecomm by EOD 10/29. 10/28: BW to talk with Carrie 10/29, morning 10/27: HS completed the change tracker for PHX72 and PHX82 full buildout 10/22: Project back to life. CL to do CAD drawings. (CL did not do original drawings and has questions) 10/21: NTP Received 10/14: BW Confirm budget and scope 9/30: Sent proposal end of august, BW follow up with Jacobs 8/28: CL estimate received for CADS only | H25: TBD | I25: NA
A26: QRO02 | B26: 5.Completed | C26: Descope-COMM /ROIP Design Revisions/CADS | D26: Cancelled | F26: Cancelled | G26: 7/14: HS confirmed no further aciton. 6/16: HS touch base with Alma. | H26: TBD | I26: ?
A27: IAD11DCN08 | B27: 5.Completed | C27: DRB - New Headend Mod - 50% IFR | D27: Complete | F27: Complete | G27: 6/23: CL files delivered - S2A to hand off to A/E. Bill proposal 100% complete after 7/18 deliverable. | H27: TBD | I27: OpenPO
A28: PHX82 | B28: 5.Completed | C28: CAD drawing date/title updates | D28: Complete | F28: Complete | G28: 7/16: Proposal was billed 100% complete already. No further invoicing for these efforts at this time. 7/7: we need CAD files - BW did not upload to OneDrive? We only have PDFs on file. 7/2: Need invoice from CL for the CAD updates - apply toward Open PO | H28: CA | I28: OpenPO
A29: BN Campus | B29: 5.Completed | C29: BN Campus Design Revisions | D29: TBD | F29: Complete | G29: 6/4: Invoice sent.
A30: BN Campus | B30: 5.Completed | C30: BN7/BN8 Updates | D30: TBD | F30: Complete | G30: invoice to be submitted via BN Campus
A31: BN Campus | B31: 5.Completed | C31: LVL08DRB - Spidercloud/OneCell | D31: TBD | F31: Complete | G31: invoice to be submitted via BN Campus
A32: CCO06 | B32: 5.Completed | C32: DRB13 – PSDAS & CAD updates. | D32: TBD | F32: Complete | G32: 5/13: Kp confirming hours/rate to bill - emailed HS. - completed client invoiced May. | H32: TBD
A33: CCO07DCN07 | B33: 5.Completed | C33: PSDAS updates | D33: TBD | F33: Complete | G33: 6/10: Revisions/updates requested from A/E. invoice sent July. | H33: CCO07CA | I33: completed
A34: EAT03 | B34: 5.Completed | C34: Colo 4 did not pass AHJ test | D34: TBD | F34: Complete | G34: invoiced in July. 6/23,6/16: Waiting for data from contractor. 5/22: HS requested solution from CL for colo 4 to present to GC - apply towards retainer PO. | H34: CA | I34: OpenPO
A35: EAT12 | B35: 5.Completed | C35: Moving PS Antenna | D35: TBD | F35: Complete | G35: invoiced July cycle. 6/10: Trey provided updated response as requested from HS | H35: CA | I35: OpenPO
A36: IAD05DRB10 | B36: 5.Completed | C36: Headend Mod to IAD04 | D36: TBD | F36: Complete | G36: 6/23: CL files delivered - S2A to hand off to A/E. Billed in July | H36: NTP | I36: OpenPO
A37: IAD12-13 | B37: 5.Completed | C37: Descoped Colos 3-5. Update design for ERRCS only. | D37: TBD | F37: Complete | G37: 5/22: BW handed off files to client. | H37: CA | I37: Confirmed
A38: LVL04-05 | B38: 5.Completed | C38: Record Set | D38: TBD | F38: Complete | G38: 5/13: KP forwarded A/E email to BW | H38: NA | I38: NA
A39: LVL09/10 | B39: 5.Completed | C39: ibwaves updates to reflect new dedicated signal source in LVL08 | D39: TBD | F39: Complete | G39: 6/20: BW approved CL work to apply to retainer PO. - convert hours and bill A/E CA contract. | H39: CA | I39: OpenPO
A40: MNZ03 | B40: 5.Completed | C40: DRB04 - New Headend Mod | D40: TBD | F40: Complete | G40: delivered early June | H40: TBD | I40: OpenPO
A41: PHX72/82DRB | B41: 5.Completed | C41: PHX72 and 82 Descope IFC packages | D41: TBD | F41: Complete | G41: 6/5: Packaging info received | H41: CA - contracts to be amended. | I41: Proposal received
A42: QRO01 | B42: 5.Completed | C42: Descope-COMM /ROIP Design Revisions/CADS | D42: TBD | F42: Complete | G42: 6/24: BW requested info / way to deliver files to Fernando. | H42: CA | I42: NA
A43: YQB01 | B43: 5.Completed | C43: Descope-Stand Alone Package for Admin+Colo 1. Design revision-minimal coverage in Colos 2-5 | D43: TBD | F43: Complete | G43: Follow up: after IFC – contact contractor to have updated ibWave sent via RFI. | H43: CA before IFC deliverables. Then Design PO | I43: N/A
A44: YQB04 | B44: 5.Completed | C44: Descope-Stand Alone Package for Admin+Colo 1. Design revision-minimal coverage in Colos 2-5 | D44: TBD | F44: Complete | G44: Follow up: after IFC – contact contractor to have updated ibWave sent via RFI. | H44: CA before IFC deliverables. Then Design PO | I44: Delivered-Invoiced
... A48: YTO40 | B48: 5.Completed | C48: IFC print due 5/1. | D48: TBD | F48: Complete | G48: 5/5: Stephen handling. | H48: CA | I48: Delivered
A49: YTO40DRB07 | B49: 5.Completed | C49: DRB-07 Descoping Page-Turn (ROIP, Security, & Structural) | D49: TBD | F49: Complete | H49: CA | I49: Contract
A50: QRO06 | B50: 5.Completed | C50: QRO06 EXP 100% IFR Q-Print | D50: 45868 | F50: NA | G50: 7/30: BW delivered | H50: CA | I50: NA - Bram to do CAD work
A51: YTO11 | B51: 5.Completed | C51: YTO11- DRB-09 - COLO 3 Fit-out (Package 2) - Issued for Review | D51: 9/12/2025-completed | F51: completed | G51: 09/12: BW uploaded docs | H51: CA | I51: YES - Stephen to submit $500 invoice via CL
A52: QRO06 | B52: 5.Completed | C52: QRO06 EXP IFC Q-Print | D52: 10/1/2025-Completed | F52: TBD | G52: 9/30: BW to do a print in BB. 7/14: Logged on project task list. | H52: CA | I52: TBD
A53: EAT06-09 | B53: 5.Completed | C53: Redesign to Fremont - 50% IFR 8/29/25 - Invoice to 60% | D53: 46036 | F53: 46010 | G53: 1/16: Invoice to 60% 1/5: CL (Trey) sent revised designs back to Harold. 12/22: Harold gave feedback to CL 12/9: S2A received floor plans. Trey to use these plans for Microsoft EAT06. CL will begin the model later this week and the design next week. 11/25: Floor plans are still in production, there is some that was associated with the 30% but I think we are still a few weeks away from all the floor plans being available. 11/24: KC asked for update on floor plans 11/17: 30% was pushed to 11/21. So we are actively working on the deliverable this week and will start on the 60% next week. 10/30: Design still on track to start the week of Nov 17-21st 10/29: Katie reached out to Chad Mendall at Stantec 10/28: Katie to reach out to check project status 10/10: S2A will not be starting their work during the 30% design phase. The 30% IFR started this Tuesday, 10/7, and will last six weeks. 10/9: Waiting on floor plans. 10/2: HS sent the revised DCN-01 proposal for EAT06 only. 10/1: Chad Mendal - Correction Needed. The second DCN for the full design will just be for the 2-Story 5-Colo EAT06 building (2.5 Colos over 2.5 Colos). Your DCN is indicating EAT09, so I will need you to amend your DCN to remove any reference to EAT09. 9/30: HS to resubmit pricing 9/30 7/30: Kick off did not happen 8/4 - TBD, 8/14: BW asked to take off list | H53: TBD - contract revision pending | I53: PO from October for $6,750.00
A54: YQB Projects | B54: 5.Completed | C54: Create S2A Org Chart | D54: 11/21/2025-Completed | F54: NA | G54: 11/4: First draft sent to HS for review KC to create S2A org chart | H54: ? | I54: NA
A55: LVL12-14 | B55: 5.Completed | C55: LVL13 BOD Updates & Colo Shifts | D55: 11/14/2025-Completed | G55: 11/17: BW asked CL to implement comments from the A.E/MSFT regarding the LVL13 set | H55: LVL12-14CA | I55: OpenPO
A56: PHX82 | B56: 5.Completed | C56: PHX82 CA Construction DRB13 IFP (COLO 3-5 full scope) | D56: 11/18-Completed | F56: NA | G56: 11/18: BW to send in QA form after reviewing designs. 11/17: Ball in Jacobs court. BW to send in QA form after reviewing drawings. | H56: PHX82CA | I56: NA
A57: LVL12-14 | B57: 5.Completed | C57: LVL13 100% IFR Production Deadline: 11/21 – Delivery Due to SRI for QC and posting | D57: 11/21/2025-Completed | F57: 45981 | G57: 11/24: BW to send the DAS drawings and model for the 11/25 deliverable. Please also complete the drawing list, answer all related BIM 360 issues and confirm that the deviations log is up to date. Bram forwarded print instructions to Stephen so he can print the final set. | H57: LVL12-14CA | I57: OpenPO
A58: PHX12 | B58: 5.Completed | C58: Record Drawings | D58: 1/29/2026-Completed | F58: NA | G58: 1/26: BW sent markups to Bart Spencer of Jacobs to update the Revit files. 1/23: Carrie Wright gave access to IFC and asked Jacobs team to implement S2A markups. Stephen engagsed as backup in case we need to redo the CADs. 12/11: Howard Way sent the as-builts 12/9. Katie to complete as-builts with assistance from Bram. 12/3: Howard Way will let the Team know when all Contractor As-builts have been received and approved, to begin Record Drawing preparation. 12/1: BW reached out to Howard Way and Brandon Gilyard. 10/30: S2 Advisors still needs to receive and approve the PHX12 COLOs 2-5 ERRCs as-builts. The General Contractor has not yet submitted all as-builts for the PHX12 Project to begin Record Drawing preparation. 5/13: A/E to schedule call with S2A to review drawings once they are ready. | H58: CA | I58: TBD
A59: PHX71 | B59: 3.In Queue | C59: Redlines/Record Drawings | D59: TBD | F59: Complete | G59: 10/30: Andrea gave update that installation and testing are completed. Did not give carrier agreement update. 09/15: BW emailed Andrea requesting status update. 5/27: CADS delivered from Stephen. Submission date to A/E TBD. Andrea Frazier-Sanches to advise, 9/22 - BW has reached out for direction on how to submit deliverables, has not received direction. | H59: CA | I59: Contract
A60: YTO11 | B60: 5.Completed | C60: YTO11 - IFC Refresh for Package 3 & 4 (COLOs 2 and 3) | D60: Complete-10/03/25 | F60: Complete-10/03/2025 | G60: 11/04: Did CL bill for work on this deliverable? Once confirmed, move to Completed. 9/25: Stephen Wright is working on this. 6/27: A/E requests estimate of hours and timeline to complete. | H60: CA | I60: N/A
A61: IAD12 | B61: 5.Completed | C61: IFC Issuance | D61: TBD | F61: TBD | G61: 9/3: BW advised to close. No action needed.8/12: IFC date TBD, AE update ETA week of 8/18 | H61: CA | I61: NA - Bram to do CAD work
A62: LVL07DRB03 | B62: 5.Completed | C62: IFR Issance | D62: 9/9/2025-completed | F62: 45910 | G62: 9/9: BW email to Mira confirming delivery for afternoon 9/10. BW forwarded email thread confirming CA contract to be billed for effort. | H62: CA | I62: NA - Bram doing the work.
A63: YTO40DCN03 | B63: 5.Completed | C63: DCN03 Colo 3,4,5 De-Scoping Efforts | D63: TBD | F63: Complete | G63: 6/23: CL given approval to proceed. | H63: CA | I63: N/A
A64: LVL06 | B64: 5.Completed | C64: LVL06 - as-builts | D64: 10/2/2025-Completed | F64: N/A | G64: 9/30: BW to send markups. 9/22: SwansonRink to do CAD drawings, BW to confirm 9/19: S2A to verify that we have redlines | H64: CA | I64: N/A
A65: SJC02 | B65: 5.Completed | C65: SJC02 - IFP REV4 | D65: 10/8/2025-Completed | F65: Complete, need to print | G65: 11/04: Is this new work, or is this covered by the $6,810 that was billed to completion in September? 10/7: Jacobs sent the upload folder 9/22: Stephen Wright to incorp ROIP revisions and CAD package, 9/19: S2A to reivew the status of the drawings | H65: DS | I65: OpenPo
A66: SAT89 | B66: 5.Completed | C66: SAT89 S2 Advisors CA Contract | D66: N/A | F66: 45926 | G66: 10/7: WSP sent contract. HS to sign contract. 10/6: WSP updated COI insurance amounts to reflect S2A coverage. Still waiting on corrected contract. 10/2: WSP to correct SAT89 & 90 CA contract. Waiting on approval of COI insurance coverage. 9/24: Contract needed to complete RFIs. KC reached out to Garr DiSalvo. Garr is traveling this week. | H66: N/A | I66: N/A
A67: AVC43 | B67: 5.Completed | C67: Benchmark Data Email Thread- Ask GC for a BM status report | D67: N/A | F67: N/A | G67: 10/2: BW has LYH10 BM status report but still waiting on AVC43. 9/24: BW to ask GC for BM status report | H67: N/A | I67: N/A
A68: LYH10 | B68: 5.Completed | C68: Benchmark Data Email Thread- Ask GC for a BM status report | D68: N/A | F68: N/A | G68: 9/24: BW to ask GC for BM status report | H68: N/A | I68: N/A
A69: BOYDTON AREA | B69: 5.Completed | C69: Send access requirements | D69: N/A | F69: N/A | G69: 9/25: Refer to email chain with Joshua Moore 9/25 | H69: N/A | I69: N/A
A70: BOYDTON AREA | B70: 5.Completed | C70: Update hardware quotes so MSFT can process PO | D70: N/A | F70: N/A | G70: 9/25: BW refer to email chain with Clark Martin | H70: N/A | I70: N/A
A71: YTO11 | B71: 5.Completed | C71: YTO11 - DCN-11 - Package 4 & Specification Refresh (COLO 5 Fit-Out) | D71: TBD | F71: TBD | G71: 11/13: Wayne confirmed 80 hours for each discipline, DAS and ROIP equal to $36,320 10/28: HS sent in hours request for 60 hours 10/22: Hours estimate request from Stantec. BW estimates it will take of 15 hours to review, print, and attend meetings.
A72: CLT04/10/17 | B72: 5.Completed | C72: FInalize contracts and insurance coverage amounts | D72: TBD | F72: TBD | G72: 10/30: Megan sent clarification on contract amounts. 10/29: KC reached out to Megan and asked for clarity on contract amounts and insurance coverage. | H72: CA | I72: TBD
A73: PHX72 | B73: 5.Completed | C73: DRB14 (not 13) Full Buildout | D73: 11/5/2025-Completed | F73: NA | G73: 10/31: Mahima requests QA firms to make the IFP submission on 11/5. BW: Wait until Jacobs confirms the drawing updates are completed. | H73: PHX72CA
A74: LVL12-14 | B74: 5.Completed | C74: 100% IFR (lesson learned from LVL12 and update to IFC 2021) | D74: 11/5/2025-Completed | F74: 45966 | G74: 11/7: Mira said drawings looked good. 11/5: BW to send spec section # 275019 on Monday, 11/10 11/5: Comments from ML: (SW to work on this) - We are missing spec 275019. Please provide. - Please update the PS DAS drawing list. - Please update the TB on all drawing sets & re-upload. 11/4: Waiting to hear back confirmation from Mira Lammers if changes are needed/QA form completion | H74: LVL12-14DS | I74: OpenPO
A75: SAT89 | B75: 5.Completed | C75: Vertical Construction IFC | D75: 11/7/2025-Completed | F75: 45967 | G75: 11/7: Still need to update CAD title blocks and upload to WSP Sharepoint. SW uploading updated files to SAT89 project folder. Waiting on access from Garr to upload to AE folder. | H75: SAT89CA | I75: OpenPO
A76: PHX72 | B76: 5.Completed | C76: PHX72 CA COLOS 3-5 Restart of CA | D76: 45975 | F76: NA | G76: 11/12: Harold send hours to Andrea. Waiting on AFS response. Andrea Frazier-Sanchez asks HS that he adjust the time and relook at the proposal. Looking at a total of 50 weeks. She asks if HS can return proposal by 11/14. | H76: PHX72CA | I76: NA
A77: PHX82 | B77: 5.Completed | C77: PHX82 CA Construction DRB13 IFP (COLO 3-5 full scope) | D77: 45978 | F77: 45975 | G77: 11/17: Ball in Jacobs court. BW to send in QA form after reviewing drawings. 11/13: Send in QA form 11/12: BW sent markups and instructions. In Jacobs court now.Jacobs is doing the CAD and S2A is doing the QAQC. We will be re-issuing all drawings from PKG04-06 in this package. All drawings have been marked as REF. We will also need to issue and changes to revert scope back from the descope DRB10-IFC. | H77: PHX82CA | I77: OpenPO
A78: PHX13/14 | B78: 5.Completed | C78: 11/6 Site Visit Reports | D78: 11/10/2025-Completed | F78: NA | G78: HS to complete reports 11/12 or 11/13 | H78: PHX13CA
A79: SAT14 | B79: 3.In Queue | C79: SAT14/15 RFQ Clarifications | D79: ? | F79: ? | G79: 12/1: Stuck in MSFT approval 11/17: BW to follow-up 11/13: SW asked for original CADS. CL sent proposals. Need to know scope, if a DS contract is coming, when project will start. | H79: ? | I79: Proposal received
A80: SAT15 | B80: 3.In Queue | C80: SAT14/15 RFQ Clarifications | D80: ? | F80: ? | G80: 12/1: Stuck in MSFT approval 11/17: BW to follow-up 11/13: SW asked for original CADS. CL sent proposals. Need to know scope, if a DS contract is coming, when project will start. | H80: ? | I80: Proposal received
A81: LVL12-14 | B81: 5.Completed | C81: Issue #2400 was assigned to you | D81: 11/18/2025-Completed | F81: NA | G81: Matt Benson assigned BW issue #2400. | H81: LVL12-14DS | I81: NA
A82: CHI11 | B82: 5.Completed | C82: Troubleshooting for CHI10 DAS headend issue | D82: NA | F82: NA | G82: 12/3: S2A to provide a high level technical review of proposal.
A83: LVL12-14 | B83: 5.Completed | C83: LVL13 Redesign IFB Delivery Guidelines | D83: 12/18/2025-Completed | F83: NA | G83: 12/12: IFB is postponed and will likely be at the end of January. 12/3: Bram to print set | H83: LVL12-14DS
A84: SJC02 | B84: 5.Completed | C84: SJC02 Building CA Proposal | D84: 46007 | F84: NA | G84: 12/12: Updates pricing
A85: IAD12-13 | B85: 5.Completed | C85: Design DCN for IAD12&13 Restart | D85: 2/5/2026-Completed | F85: 46056 | G85: 2/10: Bram, was this uploaded successfully on 2/5? 2/1: This note shall be placed on all drawings: “DRB06 drawings shall supersede DRB04 documents. Any items previously installed under DRB04 shall be re-installed per the DRB06 documents” . 1/30: Stephen to deliver 2/3 1/23: Stephen working on CAD floorplans 1/16: Reliant on IAD11. Contractor who installs IAD11 signal source must install IAD12/13 expansion/commissioning. Whoever installs the headend in 11 owns it, they need to introduce any changes to the carriers. 1/5: Propose moving to a DSS 1/5: Same direction. MSFT may have additional items that may come up but for now get drawings back to point when descope was announced. 12/22: Katie asked for deliverables schedule. 12/18: Stephen to work on CADs. 12/16: Work with Matt McCarthy and Jack O'Brien to determine if reverting models to March of 25 is the best approach or just undoing Descope items from the current set.Please commence to get your drawing sets back to the point when descope was announced. (Approx. 3/25) Please be sure to include any changes made for QA/QC purposes and any SME comments that are to stay in the final build. | H85: IAD12-13DS | I85: Open PO
A86: CLT04 | B86: 5.Completed | C86: DRAFT DRB01 Drawings | D86: 1/8/2026-complete | F86: 1/7/2026-complete | G86: 1/5: CL (Stephen) confirmed 1/8 delivery date and asked to set up time with Bram today or tomorrow. 12/24: Please upload CLT04 Draft DRB01 Drawings HERE by EOD 1/8/2026. Please make sure all changes have been clouded and the ​DRB01 Narrative​ has been completed for your discipline. Due for DAS/ROIP: -BOM Updates -Rack elevation and requirement update -Update to ISP circuits | H86: CLT04CA | I86: CLT04CA
A87: CLT04 | B87: 5.Completed | C87: FINAL DRB01 Drawings | D87: 1/16/2026-Completed | F87: ? | G87: 1/16 CADs/Drawings are complete. We are waiting on any MSFT comments. Bill to MSFT on Friday. 1/5: Meg Plank sent delivery instructions and folder 12/24: Please upload CLT04 Draft DRB01 Drawings HERE by EOD 1/8/2026. Please make sure all changes have been clouded and the ​DRB01 Narrative​ has been completed for your discipline. Due for DAS/ROIP: -BOM Updates -Rack elevation and requirement update -Update to ISP circuits | H87: CLT04CA | I87: CLT04CA
A88: LVL11 | B88: 5.Completed | C88: LVL11 Record Sets | D88: 1/20/2025-Completed | G88: This isn’t due until 1/20 12/29: CAD exports for backgrounds need to be shared with the team (1/13) | H88: LVL11CA
A89: YTO40 | B89: 5.Completed | C89: Updated IFC print/refresh: DCN-11/DRB-13 - Packages 2, 3 & 4 with Specifications Refresh (COLOs 3, 4 & 5 Fit-Out) | D89: 1/9/2026-complete | F89: NA | G89: 1/6: No major changes | H89: YTO40CA
A90: LVL12-14 | B90: 5.Completed | C90: LVL13 Redesign Issue for MSFT Review Delivery | D90: 46064 | F90: NA | G90: 2/11: Bram will update title block in BlueBeam. 1/30: The SME’s would like to have a formal review period before IFC is released for LVL13. We only need to issue launch and buildout drawing packages, but at the point of issue, these backages should be complete and essentially ready for IFC. There will be no admin QC for this deliverable. Please complete and engineering QC and admin QC of your drawings before delivery. | H90: LVL12-14DS
A91: SAT89 | B91: 5.Completed | C91: Vertical Construction of SAT89 Slides | D91: 1/8/2026-complete | G91: Recycle slides that Bram sent Clark | H91: SAT89
A92: FYT01/02 | B92: 5.Completed | C92: Combine FTY01/02 iBwaves | D92: 1/23/26-completed | F92: 1/23/26-completed | G92: 1/23: Trey sent the link to the combined FTY01/02 design for Verizon to review. 1/20: AE approved CL revision. CL waiting for Benchmark reports. 1/12: CL is requesting $2000 for revision | H92: FTY01? | I92: Open PO
A93: FTY03 | B93: 5.Completed | C93: FTY03 DRAFT IFC QC | D93: 2/6/2026-Completed | F93: NA | G93: 2/10: Bram, was this uploaded successfully on 2/6? 2/3: Bram working on this week 1/30: Bram to submit. Still waiting on title block instructions. 1/29: Stephen to update TB. Add note to title page about rebroadcast agreements must be amended by the owner of the sisnal source equipment (Linx). No other contractor is permitted to work on signal source except for the owner. 1/26: Katie + Bram to meet to discuss 1/15: Assigned to Katie. | H93: FTY03DS additional funds, see 1/29 email | I93: NA
A94: CLT10 | B94: 5.Completed | C94: CLT10 DRB01 QC Sets | D94: 46080 | F94: NA | G94: Email from Meg Plank 2/10: Please upload CLT10 DRB01 QC Sets HERE by EOD 2/27/2026. | H94: CLT10CA | I94: Open PO
A95: CLT04 | B95: 5.Completed | C95: FINAL DRB01 Drawings | D95: 1/21/2026-completed | F95: NA | G95: Please upload CLT04 Final DRB01 Drawings ​​HERE​​​​​​ by EOD 1/21/2026. Please make sure all changes have been clouded and the ​​​DRB01 Narrative​​​ has been completed for your discipline. | H95: CLT04CA | I95: NA
A96: CLT17 | B96: 5.Completed | C96: CLT17 DRB01 IFC | D96: 46086 | F96: NA | G96: 3/2: Set is complete, waiting on comments from MSFT 3/2: Confirmation from Meg Plank: Please have drawings and CAD files uploaded by EOD 3/5. 2/25: As a reminder, please upload the CLT17 DRB01 IFC drawings and specs (if needed) HERE by EOD 3/5/26. 2/10: Please update the revision block accordingly and make sure all changes are clouded! Please also make sure the ​​​CLT17 DRB01 Narrative.docx​​ has been updated for your discipline! Please upload CLT17 DRB01 QC Sets ​HERE​ by EOD 2/13/26. | H96: CLT17CA | I96: Open PO
A97: CLT10 | B97: 5.Completed | C97: CLT10 DRB01 IFC | D97: 3/19/2026-completed | F97: ? | G97: 2/10: Please upload CLT10 DRB01 IFC Drawings ​ HERE EOD 3/12/26. Please update the revision block accordingly and make sure all changes are clouded! Only revised sheets need to be issued! Please also make sure ​the ​CLT10 DRB01 Narrative.docx​ has been updated for your discipline! | H97: CLT10CA | I97: Open PO
A98: FTY03 | B98: 3.In Queue | C98: FTY03 DRAFT IFC QC | D98: 46070 | F98: NA | G98: 2/11: Resubmit for the 2/17 submission | H98: FTY03CA | I98: NA
A99: EAT06 | B99: 5.Completed | C99: New 2-Story Design Fremont | D99: 2/6/2026-Completed | F99: NA | G99: Bram, can I mark this as completed and invoice? 2/5: QA-QC process contines with Stantec 2/3: Stephen delivered QA-QC set. Bram to submit. | H99: EAT06CA | I99: EAT06 contract
A100: LVL10 | B100: 5.Completed | C100: Record Docs | D100: 46076 | F100: TBD | G100: 1/30: ML sent delivery guidelines. Please note, record docs need to be updated to include all RFIs and the received As-builts. | H100: LVL10CA
A101: CLT17 | B101: 5.Completed | C101: CLT17 DRB01 IFR - Submit to PM | D101: 46072 | F101: ? | G101: 2/10: Please upload CLT17 DRB01 Drawings ​​HERE​​​​​ by EOD 2/19/26. Please update the revision block accordingly and make sure all changes are clouded! Only revised sheets need to be issued! | H101: CLT17CA | I101: Open PO
A102: CLT17 | B102: 5.Completed | C102: CLT17 DRB01 IFC | D102: 46079 | F102: ? | G102: 2/10: Please upload CLT17 DRB01 IFC Drawings HERE by EOD 2/26/26. Please update the revision block accordingly and ensure all changes are clouded. Only the revised sheets need to be issued. These sets will need to be signed and sealed. Please also make sure ​the ​​​CLT17 DRB01 Narrative.docx​​ has been updated for your discipline! | H102: CLT17CA | I102: Open PO
A103: Cherry Creek Garage | B103: 3.In Queue | C103: ? | D103: ? | F103: ? | G103: ? | I103: $14,250 in proposal for CAD drawings and iBwave designs
...

Sheet RFI_Submitals
A1: Notes: | B1: Morrison Hershfield (Stantec) | C1: requests a follow up email when answering. Said BlueBeam doesn't always send a notification when something is answered.
B2: SAT Projects: | C2: FOLLOW PAGE GUIDELINES!!! - And add 'S2A' to the file name when responding.
B3: Swanson Rink | C3: Send a follow up email confirming responded to in BB. LVL / AVC, etc.
B4: YTO40CA | C4: Refer to YTO40CA guidelines PDF.
A5: Added | B5: Project | C5: Description | D5: Due | E5: Status | F5: Completed Date | G5: Comments
A6: 45314 | B6: MNZ03 | C6: RFI266.1 Voltage types for ROIP | D6: 45684 | E6: Completed | G6: BW completed 1/27
A7: 45485 | B7: AVC01 | C7: AVC01: Action Required for Submittal (#663.0: MC Dean - DAS COLO 3 As-Builts) | D7: 45492 | E7: Completed 7/23 | G7: 7/23: Hector Hernandez sent reminder
A8: 45485 | B8: AVC43 | C8: AVC43 due 7/12: AVC 43 RFI 27.012.0 - FCR PDAS Cabinet Location - 22-60846 - due 7/12. | D8: 45485 | E8: Completed
A9: 45485 | B9: IAD03 | C9: 275019-22.1 - NTI, IAD03 DAS Closeout | D9: 45496 | E9: Completed-7/19
A10: 45485 | B10: IAD11 | C10: IAD11 due 7/16: 275019-13.1 - RoIP, Cellular, & Public Safety DAS Final Closeout Package | D10: 45489 | E10: Completed
A11: 45485 | B11: LVL11 | C11: LVL11 due 7/22: LVL11-273241-007-R0 - (ComNet) - PSDAS System Des - 22-60853 | D11: 45495 | E11: Completed
A12: 45485 | B12: PHX13 CA | C12: PHX13 CA - D3127062 - Submittal 273241-001 - DAS System - due 7/23 | D12: 45496 | E12: Completed 7/21
A13: 45485 | B13: PHX13 CA | C13: PHX13 CA - D3127062 - Submittal 275019-002-00 - DAS System - due 7/23 | D13: 45496 | E13: Completed 7/21
A14: 45485 | B14: QRO06? | C14: QRO06? Due ?. Email from 7/9 at 12pm - 'LOTE 10 - Issue #7433' | D14: ? | E14: Completed
A15: 45485 | B15: SAT40 | C15: RFI #00136. PS DAS potential changes. Has this been picked up? | D15: 45484 | E15: Completed - 7/22 | G15: Bram Responded 7/22
A16: 45485 | B16: SAT40 | C16: SAT40 overdue? Submittal SUM-01389 | D16: ? | E16: Completed
A17: 45495 | B17: CYS13 | C17: D3128083 - Submittal 273241-028-00 - ROIP CLOSEOUT PACKAGE | D17: 45499 | E17: Completed-7/23
A18: 45495 | B18: SAT80 | C18: RFI#20827 ERRCS frequences-in progress. | D18: ? | E18: Completed | G18: 7/31 HS indicated he completed this one.
A19: 45496 | B19: AVC01 | C19: 647.1 MC Dean - COLO 3 DAS Warranty R1 | D19: 45503 | E19: Completed 7/23 | G19: 7/23: Hector Hernandez sent reminder
A20: 45496 | B20: SAT15 | C20: RFI# 0350 TeamLinx - Signal Source Options | D20: 45498 | E20: Complete-7/23 | G20: Harold completed 7/23.
A21: 45499 | B21: IAD04 | C21: 21-004233 - IAD04 Loudoun County VA - Submittal Forwarded: 275019-2.0 - PS-DAS SD | D21: 45506 | E21: Complete-7/26 | G21: HS Note: need the Syska electrical team to confirm that they called for a dedicated electrical circuit for the PSDAS equipment
A22: 45502 | B22: SAT40 | C22: RFI-00136-R1 - PS DAS Potential Changes - Microsoft SAT40 Design | D22: 45504 | E22: Complete-7/30 | G22: Bram responded
A23: 45503 | B23: IAD04 | C23: 21-004233 - IAD04 Loudoun County VA - RFI Forwarded: RFI 00551 - FCR Extra Rack R5 | D23: 45503 | E23: Complete
A24: 45503 | B24: PHX61 | C24: PHX2-DC1 Mercury Fit-Out: New RFI 171 (DAS Design Deficiencies *HOT*) | D24: 45510 | E24: Completed | G24: Completed by bram 7/30
A25: 45503 | B25: PHX71 | C25: RFI #513 - DAS / Telecom - DAS Wall Rack conflict with air quality equipment has been reopened. | D25: 45481 | E25: Completed | G25: Not for S2A
A26: 45504 | B26: IAD04 | C26: 21-004233 - IAD04 Loudoun County VA - RFI Forwarded: RFI 00555 - COLO Aisle Door 1100.1A Magnetic Holder | D26: 45506 | E26: Completed | G26: Not for S2A
A27: 45505 | B27: LVL09 | C27: LVL09-273241-008-R0 - (IES) - COLO2 and 3 - DAS a - 21-60832 | D27: 45519 | E27: Completed 8/15,8/22
A28: 45509 | B28: MNZ03 | C28: 051200-19.0 - Shop Drawings - Phase 5 & 6 - Stair 3 Antenna Wall - mounting questions | D28: ? | E28: Complete
A29: 45510 | B29: AVC17-18 | C29: MSFT - AVC17/18: New RFI 47 (PDAS Locations) | D29: 45513 | E29: Completed 8/14
A30: 45510 | B30: DFW20 | C30: Submittal #27 32 41-1 Revision 0: ROIP Design Package - Radio over IP | D30: 45517 | E30: Completed | G30: HS requested S2A to be removed.
A31: 45510 | B31: DFW20 | C31: Submittal #27 50 15-1 Revision 0: DAS Design Package - DAS Cabling | D31: 45517 | E31: Completed | G31: Moved back to open status 8/13.
A32: 45510 | B32: IAD03 | C32: 273241-30.1 - NTI, IAD03 RoIP Closeout | D32: 45517 | E32: Completed - 8/8 BW
A33: 45510 | B33: SAT15 | C33: RFI 0319 - TeamLinx - RoIP E-House Coverage - MS SAT15 Design | D33: 45512 | E33: Completed - 8/8 BW
A34: 45513 | B34: LVL09 | C34: LVL09-273241-009-R0 - (IES) - ROIP As-Builts Draw - 21-60832 | D34: 45527 | E34: Completed
A35: 45516 | B35: IAD04 | C35: IAD04 Loudoun County VA 275019-1.1 - Cellular DAS SD | D35: 45523 | E35: Complete 8/13
A36: 45516 | B36: LVL11 | C36: RFI#00278 DAS Verizon RBA | D36: 45518 | E36: Completed 8/14
A37: 45517 | B37: SAT14CA | C37: 275019-012 - Comm Systems DAS - Cell DAS As-Builts - CLAB - MS SAT14 CA | D37: 45512 | E37: Completed
A38: 45518 | B38: LVL10 | C38: LVL10-270519-004-R1 - (ComNet) - PSDAS System Equ - 22-60848 | D38: 45528 | E38: Completed
A39: 45519 | B39: AVC09 | C39: AVC09 eFemto integration question regarding corp account login | D39: ASAP | E39: Completed 8/19
A40: 45519 | B40: SAT14CA | C40: RFI 1236 - Teamlinx - ERRCS Remote COLO1- Relocation - MS SAT14 CA | D40: 45520 | E40: Completed
A41: 45520 | B41: AVC43 | C41: AVC43 Submittal 27 50 19-2.0 - IES PS DAS Submitt - 22-60846 - Submittal # 272073-04 | D41: 45524 | E41: Completed 8/19
A42: 45520 | B42: AVC43 | C42: AVC43 Submittal 27 50 19-2.0 - IES PS DAS Submitt - 22-60846 - Submittal # 272073-05 | D42: 45524 | E42: Completed 8/19
A43: 45520 | B43: SAT40 | C43: RFI-00228 - ERRCS Active Equipment Nema Rating - Microsoft SAT40 Design | D43: 45524 | E43: Completed 8/19 | G43: BW answered
A44: 45523 | B44: QRO01 | C44: QRO01 - PCO 117 DAS - FCR Cabinet Relocation per RFI 619 Response | D44: ASAP | E44: Completed | G44: GC requesting change order - HS Responded 8/20
A45: 45526 | B45: IAD11 | C45: DAS Cell Coverage Issues. (Not S2A's issue but we want to track it.) - HS checking back with contractor week of 9/16. | D45: ? | E45: Complete | G45: 10/22: Closed per HS 10/22 - in the owners court to resolve.
A46: 45527 | B46: SAT40 | C46: RFI-00241 - Carrier Signal Sources - Microsoft SAT40 Design | D46: 45532 | E46: Completed | G46: Bram completed 8/25
A47: 45530 | B47: PHX13 | C47: Submittal 275019-001-00 - ERRCS Systems | D47: 45534 | E47: Completed 8/30 | G47: BW
A48: 45530 | B48: PHX13 | C48: Submittal 275019-002-01 - DAS System (PSDAS Design) | D48: 45534 | E48: Completed 8/30 | G48: BW
A49: 45531 | B49: LVL06 | C49: LVL06 RFI 357 - Antennae and Splitter Location Co - 23-60857 | D49: 45533 | E49: Completed 8/30 | G49: BW
A50: 45532 | B50: AVC11 | C50: Issue #861 - OVERALL SITE PLAN | D50: 45541 | E50: Complete 8/30 | G50: Bram answered - ok to mark complete?
A51: 45532 | B51: AVC11 | C51: Issue #862 - FCR REMOTE UNITS | D51: 45541 | E51: Complete 8/30 | G51: Bram answered - ok to mark complete?
A52: 45532 | B52: AVC11 | C52: Issue #863 - SER EQUIPMENT | D52: 45541 | E52: Complete 8/30 | G52: Bram answered - ok to mark complete?
A53: 45532 | B53: AVC11 | C53: Issue #864 - OVERALL SITE PLAN | D53: 45541 | E53: Complete 8/30 | G53: Bram answered - ok to mark complete?
A54: 45533 | B54: AVC11 | C54: Issue #1027 - REMOTE UNIT LOCATION | D54: 45541 | E54: Complete 8/30
A55: 45533 | B55: AVC11 | C55: Issue #1028 - EQUIPMENT IN SER | D55: 45541 | E55: Complete 8/30
A56: 45533 | B56: AVC11 | C56: Issue #962 - TWO DRAWING PACKAGES | D56: 45541 | E56: Complete 8/30 | G56: Mouna answered - ok to mark complete?
A57: 45533 | B57: AVC11 | C57: Issue #964 - AVC11 COLO3 | D57: 45541 | E57: Complete 8/30 | G57: Mouna answered - ok to mark complete?
A58: 45533 | B58: AVC11 | C58: Issue #965 - 1x BASE STATION FOR SECURITY OFFICE | D58: 45541 | E58: Complete 8/30 | G58: Mouna answered - ok to mark complete?
A59: 45533 | B59: AVC11 | C59: Issue #966 - SITE COVERAGE | D59: 45541 | E59: Complete 8/30 | G59: Mouna answered - ok to mark complete?
A60: 45533 | B60: AVC11 | C60: Issue #967 - COVERAGE | D60: 45541 | E60: Complete 8/30 | G60: Mouna answered - ok to mark complete?
A61: 45533 | B61: AVC11 | C61: Issue #968 - COVERAGE | D61: 45541 | E61: Complete 8/30 | G61: Mouna answered - ok to mark complete?
A62: 45533 | B62: AVC11 | C62: Issue #969 - SECURITY OFFICE BASE STATION | D62: 45541 | E62: Complete 8/30 | G62: Mouna answered - ok to mark complete?
A63: 45533 | B63: AVC11 | C63: Issue #970 - BASE STATION LOCATION | D63: 45541 | E63: Complete 8/30 | G63: Mouna answered - ok to mark complete?
A64: 45533 | B64: AVC11 | C64: Issue #971 - CHARGER LOCATION | D64: 45541 | E64: Complete 8/30 | G64: Mouna answered - ok to mark complete?
A65: 45533 | B65: AVC11 | C65: Issue #972 - POWER SUPPLY | D65: 45541 | E65: Complete 8/30 | G65: Mouna answered - ok to mark complete?
A66: 45533 | B66: AVC11 | C66: Issue #973 - EXISTING VS. NEW | D66: 45541 | E66: Complete 8/30 | G66: Mouna answered - ok to mark complete?
A67: 45533 | B67: AVC11 | C67: Issue #974 - SECURITY OFFICE BASE STATION | D67: 45541 | E67: Complete 8/30 | G67: Mouna answered - ok to mark complete?
... A70: 45534 | B70: LVL09 | C70: LVL09-273241-011-R1 - (IES)- Admin and COLO 1 to - 21-60832 | D70: 45547 | E70: Complete | G70: HS
A71: 45539 | B71: LVL07 | C71: RFI 87 - PSDAS Archictecture. | D71: 45544 | E71: Complete
A72: 45540 | B72: PHX14 | C72: D3127072 - Submittal 273241-001-00 - ROIP System | D72: 45546 | E72: Complete
A73: 45540 | B73: PHX14 | C73: D3127072 - Submittal 275019-001-00 - DAS System | D73: 45546 | E73: Complete
A74: 45544 | B74: EAT03 | C74: RFI #404 - EAT03 - ERRCS Design Concerns | D74: 45545 | E74: Completed 9/9 | G74: See email thread.
A75: 45545 | B75: LVL06 | C75: LVL06 RFI 362 - FCR DAS Cabinet Clarifications - 23-60857 | D75: 45548 | E75: Complete
A76: 45546 | B76: AVC43 | C76: AVC43 RFI 27.012.1 - FCR PDAS Cabinet Location - 22-60846 | D76: 45548 | E76: Complete
A77: 45546 | B77: LVL07 | C77: LVL07 RFI 96 - CDAS Verizon BDA - 23-60861 | D77: 45551 | E77: Complete
A78: 45547 | B78: LVL11 | C78: LVL11-270519-001-R1 - (ComNet)-Das System Equipme - 22-60853 | D78: 45561 | E78: Complete | G78: HS 9/13 noted as responded to.
A79: 45551 | B79: IAD12-13 | C79: IAD12-13 | Submittal 055000-2.0_Metal Fabrications_Sure Steel_Antenna Support_SD | D79: 45553 | E79: Completed | G79: Not for S2A
A80: 45555 | B80: CPQ03 | C80: CPQ3 - 728 - 001-CPQ03-RFI-T-DAS-R01-202409201218 | D80: ASAP | E80: Completed 09/23
A81: 45555 | B81: CPQ03 | C81: CPQ3 - 739 - 003-CPQ03-RFI-T-DAS-R00 | D81: ASAP | E81: Completed 09/23
A82: 45555 | B82: CPQ03 | C82: CPQ3 - 741 - 004-CPQ03-RFI-T-DAS-R00 | D82: ASAP | E82: Completed 09/23
A83: 45555 | B83: CPQ03 | C83: CPQ3 - RFI 729 - 002-CPQ03-RFI-T-DAS-R00 | D83: ASAP | E83: Completed 09/23
A84: 45555 | B84: QRO01 | C84: WAMC QRO 01: New RFI 718 (RoIP - Connection between Head End equipment and outdoor antena) | D84: 45555 | E84: Complete-9/20
A85: 45555 | B85: SAT15 | C85: 275019-005 - DAS Communication Systems - Cell DAS Benchmark Study - TR | D85: 45562 | E85: Complete | G85: 09/27: No reminder email received in the am so marking complete. 09/26: We got another reminder email! 09/25: HS re-uploaded
A86: 45558 | B86: AVC43 | C86: AVC43 RFI 27.025.0 - PSDAS Repeater Model Replace - 22-60846 | D86: 45561 | E86: Complete | G86: BW completed 09/24
A87: 45558 | B87: QRO01 | C87: #27 32 41-11.0: Radio Over IP - Commissioning Document | D87: 45562 | E87: Complete | G87: HS completed 09/25
A88: 45559 | B88: LVL05 | C88: LVL05 Record Docs - MSFT request for update | D88: 45560 | E88: Complete | G88: HS responded 09/24
A89: 45559 | B89: LVL11 | C89: Submittal 270519-001-R1 (ComNet)-Das System Equipment | D89: 45561 | E89: Complete | G89: HS reponsded 09/25
A90: 45559 | B90: LVL11 | C90: Submittal 273241-004-R1 (ComNet)-Roip System Design Equipment | D90: 45561 | E90: Complete | G90: HS comment 09/26 - not for S2A: S2A – did not provide the RoIP design; unless the client wants our team to review the submittal, as an independent consultant, S2A is going to pass on this ask.
A91: 45560 | B91: AVC43 | C91: AVC43 RFI 27.018.0 - Cell DAS Design Clarificatio - 22-60846 - HOT! | D91: 45560 | E91: Completed | G91: 09/25: BW emailed Kellee Bell and let her know completed.
A92: 45560 | B92: FTY01 | C92: Submittal #27 50 19-4.0: COMMUNICATION SYSTEM DISTRIBUTED ANTENNA SYSTEM (DAS) - Commissioning | D92: 45560 | E92: Complete
A93: 45560 | B93: FTY01 | C93: Submittal #27 50 19-5.0: COMMUNICATION SYSTEM DISTRIBUTED ANTENNA SYSTEM (DAS) - Commissioning | D93: 45560 | E93: Complete
A94: 45561 | B94: CHI22 | C94: MSF19010 275019-19.0 - Phase 2 Distributed Antena System | D94: 45569 | E94: Complete | G94: 09/26: HS submitted.
A95: 45575 | B95: LVL09 | C95: LVL09-273241-012-R1 - (IES) - DAS As-Built Drawin - 21-60832 | D95: 45589 | E95: Complete | G95: Session ID: 868-911-489 - Neither BW/KP can access anymore - KP emailed Kbell to confirm if open or not. 10/16: KBelll confirmed submitted 10/14.
A96: 45575 | B96: QRO01 | C96: WAMC QRO 01: (#27 32 41-2.0: Radio Over IP - Frequency License Documentation) | D96: 45582 | E96: Complete | G96: HS completed 10/10.
A97: 45576 | B97: LVL06 | C97: LVL06 RFI 383 - Donor Antenna Placement - 23-60857 Session ID: 515-807-717 | D97: 45581 | E97: Complete | G97: Session ID: 515-807-717 HS completed 10/21
A98: 45576 | B98: LVL09 | C98: LVL09-273241-013-R1 - (IES) - ROIP As-Built Drawi - 21-60832 | D98: 45589 | E98: Complete | G98: Session ID: 455-748-724
A99: 45579 | B99: CHI22 | C99: CHI22 Franklin Park - MSF19010 - Design 275019-21.0 - Phase 2 Distributed Antenna System - PS SD | D99: 45586 | E99: Complete | G99: HS emailed response 10/16
A100: 45579 | B100: CHI22 | C100: CHI22 Franklin Park - MSF19010 - Design275019-20.0 - Phase 2 Distributed Antenna System - Commercial SD | D100: 45586 | E100: Complete | G100: HS emailed response 10/16
A101: 45580 | B101: LVL11 | C101: LVL11 RFI 330 - (ComNet) - FCR DAS RACK (CN).pdf - 22-60853 | D101: 45583 | E101: Complete | G101: Session ID: 861-904-615 BW completed 10/16
A102: 45580 | B102: SAT15 | C102: 275019-014 - DAS Communication Systems - Comba Substitution - PD | D102: 45587 | E102: Complete | G102: HS responded 10/15.
...

Sheet Billing Issue Log
A1: Added | B1: Priority Level | C1: Completed Date | D1: Project | E1: Proposal | F1: Contract | G1: Balance | H1: Invoiced to Date | I1: Status
D2: MNZ03 | E2: 78748 | F2: =H2+I2 -> 78748 | G2: =IFERROR((K2/F2),0) -> 0.99161883 | H2: 73548 | I2: 5200 | J2: 0 | K2: 78088 | L2: 46158 | M2: =F2-K2 -> 660 | O2: 23381 | P2: =K2-O2 -> 54707
D3: LVL12-14DS | E3: 140124 | F3: =H3+I3 -> 140124 | G3: =IFERROR((K3/F3),0) -> 0.99305615 | H3: 140124 | I3: 0 | J3: 0 | K3: 139151 | L3: 46159 | M3: =F3-K3 -> 973 | N3: BILLED COMPLETE | O3: 127801 | P3: =K3-O3 -> 11350
D4: QRO02 | E4: 97200 | F4: =H4+I4 -> 38546 | G4: =IFERROR((K4/F4),0) -> 1.0246978 | H4: 38546 | I4: 0 | J4: 0 | K4: 39498 | L4: 45986 | M4: =F4-K4 -> -952 | N4: Must notify contractor when billings hit 80% of contract. | O4: 37001 | P4: =K4-O4 -> 2497
D5: CPQ04DS | E5: =45460+5842+45490 -> 96792 | F5: =H5+I5 -> 45460 | G5: =IFERROR((K5/F5),0) -> 0.92877255 | H5: 40860 | I5: 4600 | J5: 0 | K5: 42222 | L5: 46167 | M5: =F5-K5 -> 3238 | O5: 41314 | P5: =K5-O5 -> 908
D6: FTY02 | E6: 67106 | F6: =H6+I6 -> 33553 | G6: =IFERROR((K6/F6),0) -> 0.8930349 | H6: 33553 | I6: 0 | J6: 0 | K6: 29964 | L6: 46142 | M6: =F6-K6 -> 3589 | O6: 7037 | P6: =K6-O6 -> 22927
D7: IAD04_05CA | E7: 116306 | F7: 116306 | G7: =IFERROR((K7/F7),0) -> 0.85382947 | H7: 116306 | I7: 0 | J7: =1193.89+1636.6 -> 2830.49 | K7: 99305.49 | L7: 46155 | M7: =F7-K7 -> 17000.51 | O7: 45173 | P7: =K7-O7 -> 54132.49
D8: LVL07 | E8: 77045.5 | F8: =H8+I8 -> 79645.5 | G8: =IFERROR((K8/F8),0) -> 0.88639032 | H8: =38522.75+38522.75 -> 77045.5 | I8: 2600 | J8: 0 | K8: 70597 | L8: 46168 | M8: =F8-K8 -> 9048.5 | O8: 38590 | P8: =K8-O8 -> 32007
D9: PHX15 | E9: 83536 | F9: =H9+I9 -> 41768 | G9: =IFERROR((K9/F9),0) -> 0.92391304 | H9: 41768 | I9: 0 | J9: 0 | K9: 38590 | L9: 45763 | M9: =F9-K9 -> 3178 | O9: 38590 | P9: =K9-O9 -> 0

Sheet Travel-Project Close Out
A1: Project | B1: Date Added | C1: Contacts | D1: Notes | E1: Completed? | F1: Expense Report Captured? | G1: Scheduled Date | H1: Travel Confirmed | I1: Punchwalk date | J1: Testing Reports Received | K1: Closeout Materials Received? | L1: Site walk report status | M1: Expenses Submitted for Invoicing
A2: AVC17/18 | C2: Todd Wescott | D2: 4/15: On weekly touch base call T Wescott indicated he'd be reaching out to all disciplines to coordinate site visits within the next couple of weeks. | G2: 8/20-8/23/25 | H2: BW - Yes
A3: IAD04 | G3: 6/3-6/4 | H3: BW | M3: Y
A4: LVL06 | D4: BIR
A5: LVL08 | D5: BW walkthrough with Verizon. Out all day Thursday, out in the morning on Friday. | G5: 8/20-8/21 | H5: BW
A6: LVL10 | D6: BIR
A7: LYH10 | D7: 7/9/25: HS asked to have added to site visit list. | G7: 8/27-8/29 | H7: BW- Yes
A8: PHX13 | C8: remington.Clausen@skanska.com - on site Candy.Glass@jacobs.com - Jacobs On-site CM | D8: Emailed Remington/Candy S2A contacts 4/10/25
A9: PHX14 | C9: michael.Cheung@skanska.com - on site coordinator Candy.Glass@jacobs.com - Jacobs On-site CM | D9: Michael advised 4/10/25 - target week of 5/25 | G9: 45807 | H9: HS
A10: PHX14-COLO3 | C10: michael.Cheung@skanska.com - on site coordinator Candy.Glass@jacobs.com - Jacobs On-site CM | D10: TENTATIVE - 7/24: Email received from Michael Cheung requesting to pick date/time for punch walk visit. S2A advised not going. | G10: 45888 | H10: BW
A11: PHX71 | C11: karen.walker@jacobs.com - Jacobs On-site CM | D11: Per K Walker 4/15: turned over to client.
A12: PHX72 | C12: karen.walker@jacobs.com - Jacobs On-site CM | D12: Per K Walker 4/15/25: PHX72 is at erecting steel framing and roofing, along with constructing infrastructure. Will keep us posted on walk thru sched - still aways out.
A13: PHX81 | C13: Brian.Gailfus@jacobs.com | D13: 8/26: Test data is being reviewed. | G13: TBD
A14: QRO02 | D14: BURNS | G14: 4/22-4/24 - HS | H14: Yes
A15: QRO06 | D15: BURNS
A16: SAT14 | D16: LINX
A17: SAT15 | D17: LINX | G17: 6/9-6/12 | H17: BW - Yes | M17: Y
A18: SAT80 | D18: LINX
A19: IAD | D19: DWS
A20: ATL06 | D20: 6/16/25: BW called out may need visit soon.
A21: YQB's | D21: 6/16/25: HW called out may be coming up.
A22: MNZ03 | B22: 45945 | D22: 10/14/25: BW called out may need visit soon. TBD.
A23: PHX13 | B23: 45967 | D23: 11/6: Need two hours at each site | E23: x
A24: PHX14 | B24: 45967 | D24: 11/6: Need two hours at each site | E24: x
A25: CHI11 | B25: 45967 | D25: 10/31: Sultan Katrangi: S2A will do a single visit when the system is tested. ($5,200 for expenses)
A26: YTO11 | B26: 45967 | D26: 11/07: Punchwalk will be first week of December - Scope is Package 1, but COLO1+Admin only, COLO2 will come later, at which we’ll be setting up another punch walk.
A27: CPQs | D27: 11/10-11/15
A28: ATL06 | B28: Early Dec | D28: 11/10: The DAS Cx team will be on site the week of 11/17/2025.

Sheet Centerline-OpenPO
A1: Open PO | B1: =25000+25000+25000 -> 75000 | D1: Estimates to Date | E1: =SUM(G4:G95) -> 48250 | G1: Balance: | H1: =B1-E1 -> 26750 | J1: Invoiced Amount | K1: =SUM(J4:J68) -> 48400
A3: Project | B3: Scope | G3: Estimate | H3: Approved | I3: Delivered | J3: Inv Amt | K3: Balance | L3: Invoiced to A/E | M3: Month Billed | N3: Centerline Invoice # | O3: S2A Invoice# | P3: Notes
A4: EAT03CA | B4: Colo 4 did not pass AHJ test | G4: 400 | H4: Y | I4: Y | J4: 400 | K4: =G4-J4 -> 0 | L4: Y | M4: 45809 | N4: 176399
A5: EAT12CA | B5: Moving PS Antenna | G5: 900 | H5: Y | I5: Y | J5: 900 | K5: =G5-J5 -> 0 | L5: Y | M5: 45839 | N5: 178716
A6: IAD04DRB10 | B6: IAD04 HeadEnd Mod | G6: 650 | H6: Y | I6: Y | J6: 650 | K6: =G6-J6 -> 0 | L6: Y | M6: 45839 | N6: 180730
A7: IAD11DRB | B7: IAD11 HeadEnd Mod | G7: 650 | H7: Y | I7: Y | J7: 650 | K7: =G7-J7 -> 0 | L7: Y | M7: 45839 | N7: 180730 | P7: IAD11DCN08
A8: LVL09 | B8: update ibwaves - reflect new dedicated signal source in LVL08 | G8: 350 | H8: Y | I8: Y | J8: 350 | K8: =G8-J8 -> 0 | L8: Y | M8: 45839 | N8: 181437
A9: LVL10 | B9: update ibwaves - reflect new dedicated signal source in LVL08 | G9: 350 | H9: Y | I9: Y | J9: 350 | K9: =G9-J9 -> 0 | L9: Y | M9: 45839 | N9: 181437
A10: MNZ03DRB04 | B10: MNZ03 HeadEnd Mod | G10: 650 | H10: Y | I10: Y | J10: 650 | K10: =G10-J10 -> 0 | L10: Y | M10: 45809 | N10: 176399
A11: SJC02Revision | B11: Substation ROiP Revisions - to be delivered in IFP/IFC package | G11: 650 | H11: Y | I11: Y | J11: 650 | K11: =G11-J11 -> 0 | L11: Y | M11: 45901 | N11: 187434 | P11: Needs to be billed to A/E after IFP issuance 8/14
A12: YTO40DCN03 | B12: run test without shell space antennas | G12: 350 | H12: Y | I12: Y | J12: 350 | K12: =G12-J12 -> 0 | L12: Y | M12: 45839 | N12: 180730
A13: CCO08 | B13: PSDAS Update - City of Palmetto code changes - design+CAD | G13: 2100 | H13: Y | I13: Y | J13: 2100 | K13: =G13-J13 -> 0 | L13: Y | M13: 45839 | N13: 184126 | P13: CADS delivered 7/17 ($1,300) - ibWaves delivered 7/10 - S2A to review and then CL will start CADS
A14: PHX82 | B14: 7/1 Title and Date CAD updates | G14: 375 | H14: Y | I14: Y | J14: 375 | K14: =G14-J14 -> 0 | L14: Y | M14: 45870 | N14: 184126
A15: CYS17 | B15: 7/11 Title and Date CAD (PDF?) updates | G15: 375 | H15: Y | I15: Y | J15: 375 | K15: =G15-J15 -> 0 | L15: Y | M15: 45839 | N15: 184126 | P15: sheet index, too, and CADs. client to be billed with July cycle.
A16: IAD11 | B16: Update cads based on updated ibWaves | G16: 1500 | H16: Y | I16: Y | J16: 1500 | K16: =G16-J16 -> 0 | L16: Y | M16: 45839 | N16: 187432 | P16: delievered 7/16
A17: PHX72 | B17: Descope DRB08 IFC package 7/10 | G17: 375 | H17: Y | I17: Y | J17: 375 | K17: =G17-J17 -> 0 | L17: Y | M17: 45809 | N17: 184126
A18: LVL | B18: Consolidation of LVL 9,10,11 data centers into LVL08 file | G18: 2000 | H18: Y | I18: Y | J18: 2000 | K18: =G18-J18 -> 0 | L18: Y | M18: 45870 | N18: 187433 | P18: bill to LVL10CA contract.
A19: PHX72 | B19: Reverse of PHX72 descope done in May | G19: 700 | H19: Y | I19: Y | J19: 700 | K19: =G19-J19 -> 0 | L19: Y | M19: 45870 | N19: 212237 | P19: 11/03: Only partially billed. Original estimate was $2,350 for both PHX72 and 82. 8/28: Estimate $2,350 CADS only
A20: PHX82 | B20: Reverse of PHX82 descope done in May (CANCELED) | G20: 0 | H20: Y | I20: N | J20: 0 | K20: 0 | L20: Y | M20: - | N20: - | P20: 1/26: Work canceled and never billed by CL11/07: CL work back on but reduced, similar to work done for PHX72 11/03: CL work canceled. 8/28: Estimate $2,350 CADS only
A21: CPQ11 | B21: add in colo 4 to ibwaves | G21: 2600 | H21: Y | I21: Y | J21: 2600 | K21: 0 | L21: Y | M21: 45901 | P21: 10/1: Contract added to Notora Open PO contract folder
A22: YTO11 | B22: CAD Updates | G22: 500 | H22: ? | I22: Y | J22: 650 | K22: =G22-J22 -> -150 | L22: Y | M22: 45931 | N22: 201632 | P22: Had a note about a $500 obligation to Stephen. Perhaps the original estimate amount was changed?
A23: CCO08 | B23: CAD Reprint? | G23: 650 | H23: Y | I23: Y | J23: 650 | K23: =G23-J23 -> 0 | L23: Y | M23: 45931 | N23: 203713 | P23: This was a NTP (BW has email)
A24: CCO08 | B24: PSDAS design that includes the Admin area and all 5 COLOs | G24: 1300 | H24: Y | I24: Y | J24: 1300 | K24: =G24-J24 -> 0 | L24: Y | M24: 45931 | N24: 201629
A25: LVL13 | B25: Design Revision + CADs | G25: 2800 | H25: Y | I25: Y | J25: 2800 | K25: =G25-J25 -> 0 | L25: Y | M25: 45962 | N25: 212233
A26: IAD12 | B26: Design Revision | G26: 1300 | H26: Y | I26: Y | J26: 1300 | K26: 0 | L26: Y | M26: 45992 | N26: 228337 | P26: $1,300 for DES REV per site, $3,150 for CADs per site
A27: IAD13 | B27: Design Revision | G27: 1300 | H27: Y | I27: Y | J27: 1300 | K27: 0 | L27: Y | M27: 45992 | N27: 228340 | P27: $1,300 for DES REV per site, $3,150 for CADs per site
A28: IAD12 | B28: CADS | G28: 3150 | H28: Y | I28: Y | J28: 3150 | K28: 0 | L28: Y | M28: 46023 | N28: 232308 | P28: $1,300 for DES REV per site, $3,150 for CADs per site
A29: IAD13 | B29: CADS | G29: 3150 | H29: Y | I29: Y | J29: 3150 | K29: 0 | L29: Y | M29: 46023 | N29: 232309 | P29: $1,300 for DES REV per site, $3,150 for CADs per site
A30: CLT04 | B30: Design Revision | G30: 1300 | H30: Y | I30: Y | J30: 1300 | K30: 1300 | L30: Y | M30: 45992 | N30: 228331 | O30: 2733 | P30: Each project would be $1,300 for the revision and $1,500 for the CAD updates
A31: CLT04 | B31: CADS | G31: 1500 | H31: Y | I31: Y | J31: 1500 | K31: 1500 | L31: Y | M31: 45992 | N31: 228332 | O31: 2733 | P31: Each project would be $1,300 for the revision and $1,500 for the CAD updates
A32: CLT10 | B32: Design Revision | G32: 1300 | H32: Y | I32: Y | J32: 1300 | K32: 1300 | L32: Y | M32: 45992 | N32: 228334 | O32: 2734 | P32: Each project would be $1,300 for the revision and $1,500 for the CAD updates
A33: CLT010 | B33: CADS | G33: 1500 | H33: Y | I33: Y | J33: 1500 | K33: 1500 | L33: Y | M33: 46082 | N33: 236332 | O33: 2830 | P33: Each project would be $1,300 for the revision and $1,500 for the CAD updates
A34: CLT17 | B34: Design Revision | G34: 1300 | H34: Y | I34: Y | J34: 1300 | K34: 1300 | L34: Y | M34: 45992 | N34: 228335 | O34: 2735 | P34: Each project would be $1,300 for the revision and $1,500 for the CAD updates
A35: CLT17 | B35: CADS | G35: 1500 | H35: Y | I35: Y | J35: 1500 | K35: 1500 | L35: Y | M35: 46079 | N35: 233523_x000D_ | O35: 2784 | P35: Each project would be $1,300 for the revision and $1,500 for the CAD updates
A36: CCO07 | B36: Design Revision | G36: 1000 | H36: Y | I36: Y | J36: 1000 | K36: 1000 | L36: Y | M36: 46107 | N36: 240955 | O36: 2845
A37: LYH10 | B37: Verizon iBwave Package | G37: 700 | H37: Y | I37: Y | J37: 700 | K37: 700 | L37: Y | M37: 46138 | N37: 243440 | O37: 2871
A38: QRO01 | B38: Design | G38: 700 | H38: Y | I38: Y | J38: 700 | K38: 700 | L38: Y | M38: 46138 | N38: 243444 | O38: 2899
A39: MNZ03 | B39: Update design | G39: 700 | H39: Y | I39: Y | J39: 700 | K39: 700 | L39: Y | M39: 46138 | N39: 243061 | O39: 2855
A40: FTY02 | B40: iBwave Design Package | G40: 700 | H40: Y | I40: Y | J40: 700 | K40: 700 | L40: Y | M40: 46107 | N40: 239646 | O40: 2839
A41: QRO01 | B41: CAD set | G41: 1125 | H41: Y | I41: Y | J41: 1125 | K41: 1125 | L41: Y | M41: 46159 | N41: 247235 | O41: 2839
A42: CCO08 | B42: Design Revision | G42: 1300 | H42: Y | I42: Y | J42: 1300 | K42: 1300 | L42: Y | M42: 46113 | N42: 243982 | O42: 2864
A43: LVL10/11 | B43: Contractor Questions | G43: 700 | H43: Y | I43: Y | J43: 700 | K43: 700 | L43: N | N43: 241963
A44: LVL10/11 | B44: OEM Research and Revision | G44: 625 | H44: Y | I44: Y | J44: 625 | K44: 625 | L44: N | N44: 247697
A45: LVL10/11 | B45: Public Safety Design Revision | G45: 1300 | H45: Y | I45: Y | J45: 1300 | K45: 1300 | L45: N | N45: 241963
A46: CCO08 | B46: CAD Updates | G46: 1125 | H46: Y | I46: Y | J46: 1125 | K46: 1125 | L46: Y | M46: 46143 | N46: 245268 | O46: 2864
A47: CHI11 | B47: CAD Revisions | G47: 750 | H47: Y | I47: Y | J47: 750 | K47: 750 | L47: N | N47: 248558

Sheet Program Management
A1: Week | B1: Day | C1: Task | D1: January | E1: February | F1: March | G1: April | H1: May | I1: June | J1: July | K1: August | L1: Sep | M1: October | N1: November | O1: December
A2: Week 1 | B2: Monday | C2: Open Items
C3: Prepare Invoice Template & Time Tracker Doc For Each Project
B4: Tuesday | C4: Open Items
C5: 3:00 PM - Weekly Touch Base Meeting
B6: Wednesday | C6: Open Items
C7: Update Project List and Create New Timesheets
B8: Thursday | C8: Open Items
B9: Friday | C9: Open Items
C10: YQB Invoices Due
A11: Week 2 | B11: Monday | C11: Open Items
B12: Tuesday | C12: Open Items
C13: 3:00 PM - Weekly Touch Base Meeting
B14: Wednesday | C14: Open Items
B15: Thursday | C15: Open Items
C16: Notora Invoice Reconciliation
B17: Friday | C17: Open Items
A18: Week 3 | B18: Monday | C18: Open Items
C19: Log Into MSFT Account
B20: Tuesday | C20: Open Items
C21: 3:00 PM - Weekly Touch Base Meeting
B22: Wednesday | C22: Open Items
B23: Thursday | C23: Open Items
B24: Friday | C24: Open Items
C25: All Invoicing Due Date
A26: Week 4 | B26: Monday | C26: Open Items
C27: Reconcile Received to Date Amount in Billing Spreadsheet
C28: Send out A/R Reports
C29: Archive Important Docs
B30: Tuesday | C30: Open Items
C31: 3:00 PM - Weekly Touch Base Meeting
B32: Wednesday | C32: Open Items
B33: Thursday | C33: Open Items
C34: Notora Invoice Reconciliation
B35: Friday | C35: Open Items
C36: Process Timesheets
C37: Monthly Billing/Contracts/AR Status Meeting with Harold
A38: Week 5 | B38: Monday | C38: Open Items
B39: Tuesday | C39: Open Items
C40: 3:00 PM - Weekly Touch Base Meeting
C41: Last Day of the Month - Prepare Monthly Billing Spreadsheet

Sheet CA
A1: Active | B1: NAME | C1: LOCATION | D1: A/E | E1: Phase (Design or CA) | F1: AE-PM Name | G1: AE-PM Contact | H1: S2 PM | I1: 50% IFR - Notora | J1: 50% IFR - AE | K1: 100% IFR - Notora | L1: 100% IFR - AE | M1: IFP - Notora | N1: IFP - AE | O1: IFC | P1: Project Start | Q1: Submittal | R1: Substantial Completion | S1: Completion | T1: Commissioning | U1: Action Item Needed | V1: Comments
A2: 1 | B2: ATL06 | C2: ATLANTA, GA | D2: Highland Associates | E2: CA | F2: Hector Hernandez | G2: hhernandez@ha-ny.com | H2: Catherine Hannon | I2: Complete | J2: Complete | K2: Complete | L2: Complete | M2: Complete | N2: Complete | O2: Complete
A3: 2 | B3: AVC01 | C3: SOUTH HILL, VA | D3: Highland Associates | E3: CA | F3: Hector Hernandez | G3: hhernandez@ha-ny.com | H3: Nick Mayor | I3: Complete | J3: Complete | K3: Complete | L3: Complete | M3: Complete | N3: Complete | O3: Complete
A4: 3 | B4: AVC09 | C4: SOUTH HILL, VA | D4: Highland Associates | E4: CA | F4: Hector Hernandez | G4: hhernandez@ha-ny.com | H4: Nick Mayor | I4: Complete | J4: Complete | K4: Complete | L4: Complete | M4: Complete | N4: Complete | O4: Complete
A5: 4 | B5: BN49-CA | C5: BOYDTON, VA | D5: Syska | E5: CA | F5: Daniel Jones | H5: Nick Mayor | I5: Complete | J5: Complete | K5: Complete | L5: Complete | M5: Complete | N5: Complete | O5: Complete
A6: 5 | B6: BN80-CA | C6: BOYDTON, VA | D6: Syska | E6: CA | F6: Daniel Jones | H6: Nick Mayor | I6: Complete | J6: Complete | K6: Complete | L6: Complete | M6: Complete | N6: Complete | O6: Complete
A7: 6 | B7: CCO06 | C7: BOYDTON, VA | D7: Highland Associates | E7: CA | F7: Hector Hernandez | G7: hhernandez@ha-ny.com | H7: Catherine Hannon | I7: Complete | J7: Complete | K7: Complete | L7: Complete | M7: Complete | N7: Complete | O7: Complete
A8: 7 | B8: CHI05 | C8: CHICAGO | D8: Syska | E8: CA | F8: Andrew Krebs | G8: akrebs@syska.com | H8: Harold Sheley | I8: Complete | J8: Complete | K8: Complete | L8: Complete | M8: Complete | N8: Complete | O8: Complete
A9: 8 | B9: CHI10 | C9: CHICAGO | D9: Syska | E9: CA | F9: Andrew Krebs | G9: akrebs@syska.com | H9: Harold Sheley | I9: Complete | J9: Complete | K9: Complete | L9: Complete | M9: Complete | N9: Complete | O9: Complete
A10: 9 | B10: CHI11 | C10: CHICAGO | D10: Syska | E10: CA | F10: Andrew Krebs | G10: akrebs@syska.com | H10: Harold Sheley | I10: Complete | J10: Complete | K10: Complete | L10: Complete | M10: Complete | N10: Complete | O10: Complete
A11: 10 | B11: CHI22 | C11: CHICAGO | D11: Syska | E11: CA | F11: Clint Moreno | H11: Harold Sheley | I11: Complete | J11: Complete | K11: Complete | L11: Complete | M11: Complete | N11: Complete | O11: Complete
A12: 11 | B12: CO09 | C12: QUINCY, WA | D12: CPG | E12: CA | F12: Mark Heinrich | H12: Harold Sheley | I12: Complete | J12: Complete | K12: Complete | L12: Complete | M12: Complete | N12: Complete | O12: Complete
A13: 12 | B13: CYS13 | D13: Jacobs | E13: CA | F13: Kristin McCue | G13: Kristin.McCue@jacobs.com | H13: Harold Sheley | I13: Complete | J13: Complete | K13: Complete | L13: Complete | M13: Complete | N13: Complete | O13: Complete
A14: 13 | B14: CYS17 | D14: Turner
A15: 13 | B15: EAT02 | C15: WEANATCHEE, WA | D15: ESD | E15: CA | F15: Chad Mendell | G15: cmendell@esdglobal.com | H15: Harold Sheley | I15: Complete | J15: Complete | K15: Complete | L15: Complete | M15: Complete | N15: Complete | O15: Complete
A16: 14 | B16: EAT03 | C16: WEANATCHEE, WA | D16: ESD | E16: CA | F16: Chad Mendell | G16: cmendell@esdglobal.com | H16: John Clark | I16: Complete | J16: Complete | K16: Complete | L16: Complete | M16: Complete | N16: Complete | O16: Complete
A17: 15 | B17: FTY01 | C17: GEORGIA | D17: Morrison Hershfield | E17: CA | F17: Lee Percy | G17: LPercy@morrisonhershfield.com | H17: Catherine Hannon | I17: Complete | J17: Complete | K17: Complete | L17: Complete | M17: Complete | N17: Complete | O17: Complete | P17: 44959 | V17: Colo 1 is scheduled to start being built around 6/5/2023
A18: 16 | B18: IAD02/03 | C18: LEESBURG, VA | D18: Syska | E18: CA | F18: Christopher Lay | G18: clay@syska.com | H18: Catherine Hannon | I18: Complete | J18: Complete | K18: Complete | L18: Complete | M18: Complete | N18: Complete | O18: Complete | V18: POC is Marty Angeli
A19: 17 | B19: IAD04 | C19: LEESBURG, VA | D19: Syska | E19: CA | F19: Christopher Lay | G19: clay@syska.com | H19: Catherine Hannon | I19: Complete | J19: Complete | K19: Complete | L19: Complete | M19: Complete | N19: Complete | O19: Complete
A20: 18 | B20: IAD05 | C20: LEESBURG, VA | D20: Syska | E20: CA | F20: Christopher Lay | G20: clay@syska.com | H20: Catherine Hannon | I20: Complete | J20: Complete | K20: Complete | L20: Complete | M20: Complete | N20: Complete | O20: Complete
A21: 19 | B21: IAD11 | C21: LEESBURG, VA | D21: Syska | E21: CA | F21: Christopher Lay | G21: clay@syska.com | H21: Catherine Hannon | I21: Complete | J21: Complete | K21: Complete | L21: Complete | M21: Complete | N21: Complete | O21: Complete
A22: 20 | B22: LVL01-03 | C22: BOYDTON, VA | D22: K-WMCE | E22: CA | F22: Ryan Sims | H22: Harold Sheley | I22: Complete | J22: Complete | K22: Complete | L22: Complete | M22: Complete | N22: Complete | O22: Complete
A23: 21 | B23: LVL04 | C23: BOYDTON, VA | D23: Swanson Rink | E23: CA | F23: Ryan Sims | G23: RSims@swansonrink.com | H23: Catherine Hannon | I23: Complete | J23: Complete | K23: Complete | L23: Complete | M23: Complete | N23: Complete | O23: Complete
A24: 22 | B24: LVL05 | C24: BOYDTON, VA | D24: Swanson Rink | E24: CA | F24: Ryan Sims | G24: RSims@swansonrink.com | H24: Catherine Hannon | I24: Complete | J24: Complete | K24: Complete | L24: Complete | M24: Complete | N24: Complete | O24: Complete
A25: 23 | B25: LVL08 | C25: BOYDTON, VA | D25: Swanson Rink | E25: CA | F25: Ryan Sims | G25: RSims@swansonrink.com | H25: Harold Sheley | I25: Complete | J25: Complete | K25: Complete | L25: Complete | M25: Complete | N25: Complete | O25: Complete
A26: 24 | B26: LVL09 | C26: BOYDTON, VA | D26: Swanson Rink | E26: CA | F26: Ryan Sims | G26: RSims@swansonrink.com | H26: Catherine Hannon | I26: Complete | J26: Complete | K26: Complete | L26: Complete | M26: Complete | N26: Complete | O26: Complete
A27: 25 | B27: LVL10 | C27: BOYDTON, VA | D27: Swanson Rink | E27: CA | F27: Ryan Sims | G27: RSims@swansonrink.com | H27: Catherine Hannon | I27: Complete | J27: Complete | K27: Complete | L27: Complete | M27: Complete | N27: Complete | O27: Complete
A28: 26 | B28: PHX11 | C28: PHOENIX, AZ | D28: Jacobs | E28: CA | F28: Howard Way | G28: Howard.Way@jacobs.com | H28: John Clark | I28: Complete | J28: Complete | K28: Complete | L28: Complete | M28: Complete | N28: Complete | O28: Complete
A29: 27 | B29: PHX12 | C29: PHOENIX, AZ | D29: Jacobs | E29: CA | F29: Blake Giles | G29: Blake.Giles@jacobs.com | H29: John Clark | I29: Complete | J29: Complete | K29: Complete | L29: Complete | M29: Complete | N29: Complete | O29: Complete
A30: 28 | B30: PHX13 | C30: PHOENIX, AZ | D30: Jacobs | E30: CA | F30: Blake Giles | G30: Blake.Giles@jacobs.com | H30: John Clark | I30: Complete | J30: Complete | K30: Complete | L30: Complete | M30: Complete | N30: Complete | O30: Complete
A31: 29 | B31: PHX14 | C31: PHOENIX, AZ | D31: Jacobs | E31: CA | F31: Blake Giles | G31: Blake.Giles@jacobs.com | H31: John Clark | I31: Complete | J31: Complete | K31: Complete | L31: Complete | M31: Complete | N31: Complete | O31: Complete
A32: 30 | B32: QRO1 | C32: MEXICO CITY, MEXICO | D32: Burns & McDonnell | E32: CA | F32: Charlie Ussery | G32: cmussery@burnsmcd.com | H32: John Clark | I32: Complete | J32: Complete | K32: Complete | L32: Complete | M32: Complete | N32: Complete | O32: Complete
A33: 31 | B33: QRO2 | C33: MEXICO CITY, MEXICO | D33: Burns & McDonnell | E33: CA | F33: Charlie Ussery | G33: cmussery@burnsmcd.com | H33: John Clark | I33: Complete | J33: Complete | K33: Complete | L33: Complete | M33: Complete | N33: Complete | O33: Complete
A34: 32 | B34: QRO6 | C34: MEXICO CITY, MEXICO | D34: Burns & McDonnell | E34: CA | F34: Charlie Ussery | G34: cmussery@burnsmcd.com | H34: John Clark | I34: Complete | J34: Complete | K34: Complete | L34: Complete | M34: Complete | N34: Complete | O34: Complete
A35: 33 | B35: SAT12 | C35: SAN ANTONIO, TX | D35: K-WMCE | E35: CA | F35: James Ball | H35: Harold Sheley | I35: Complete | J35: Complete | K35: Complete | L35: Complete | M35: Complete | N35: Complete | O35: Complete
A36: 34 | B36: SAT14 | C36: SAN ANTONIO, TX | D36: Page Southerland Page Inc. | E36: CA | F36: Lauren Alexander | G36: lalexander@pagethink.com | H36: Nick Mayor | I36: Complete | J36: Complete | K36: Complete | L36: Complete | M36: Complete | N36: Complete | O36: Complete
A37: 35 | B37: SCL03 | C37: LIMA, CHILE | D37: Black and Veatch | E37: CA | F37: Shilpa A. Maganti | G37: MagantiSA@bv.com | H37: John Clark | I37: Complete | J37: Complete | K37: Complete | L37: Complete | M37: Complete | N37: Complete | O37: Complete
A38: 36 | B38: SCL05 | C38: LIMA, CHILE | D38: Black and Veatch | E38: CA | F38: Shilpa A. Maganti | G38: MagantiSA@bv.com | H38: John Clark | I38: Complete | J38: Complete | K38: Complete | L38: Complete | M38: Complete | N38: Complete | O38: Complete
A39: KP Adds:
A40: A | B40: SAT80-81 | D40: Pagethink | E40: CA | F40: David Lamutt | G40: dlamutt@pagethink.com
A41: A | B41: LYH10 | D41: Highland Associates | E41: CA | F41: Jason Guzman | G41: jguzman@ha-ny.com
A42: A | B42: PHX12 | C42: PHOENIX, AZ | D42: Jacobs | E42: CA | F42: Blake Giles | G42: Blake.Giles@jacobs.com | H42: John Clark
A43: A | B43: DSM40 | D43: ? | E43: CA | F43: ? | G43: ? | H43: ?
A44: A | B44: YBQ01 | D44: WZMH | E44: CA | F44: kyurkovska@wzmh.com
A45: A | B45: YQB04 | D45: WZMH | E45: CA | F45: kyurkovska@wzmh.com
A46: A | B46: YQB06 | D46: WZMH | E46: CA | F46: kyurkovska@wzmh.com
A47: A | B47: YQB11 | D47: WZMH | E47: CA | F47: kyurkovska@wzmh.com
A48: A | B48: CYS13CA | D48: Jacobs | E48: CA | F48: Kristin McCue | P48: 45505 | V48: CYS13 Record Drawings (Admin and COLOs 1 through 5) to close out the project. The latest federated model is available in Navisworks and all disciplines should have final approved redlines (with the exception of Mechanical, where we are tracking down some last info). Please begin working on Record Drawings with the idea to submit as early as possible in August (date TBC once we receive final Mech info). The client has asked us to submit these as soon as possible, so we’re being asked to advance what we can.

Sheet Sheet1
A1: Phase | B1: Task | C1: Subtask | D1: Due Date | E1: Microsoft (Progress) | F1: Andrews (Progress) | G1: S2 Advisors (Progress) | H1: DAS Contractor (Progress)
A2: PAPERWORK | B2: Contract Organization | C2: Draft contracts | D2: 45899 | E2: [Progress ▼] | F2: [Progress ▼] | G2: [Progress ▼] | H2: [Progress ▼]
A3: PAPERWORK | B3: Purchase Orders | C3: Submit to finance | D3: 45905 | E3: [Progress ▼] | F3: [Progress ▼] | G3: [Progress ▼] | H3: [Progress ▼]
A4: CONSTRUCTION | B4: Site Prep | C4: Clear land | D4: 45920 | E4: [Progress ▼] | F4: [Progress ▼] | G4: [Progress ▼] | H4: [Progress ▼]
A5: CONSTRUCTION | B5: Electrical Install | C5: Install conduits | D5: 45931 | E5: [Progress ▼] | F5: [Progress ▼] | G5: [Progress ▼] | H5: [Progress ▼]
